Workbook

Sheet Inputs
A1: INPUTS — SINGLE SOURCE OF TRUTH
A2: Blue = input (edit here). Black = derived formula. Green (other tabs) = link into this tab. No numeric constant may live outside this tab and the reported-data tabs (IS/BS/CF).
A4: COMPANY BASE — Apple Inc. (AAPL) · FY2025 · nominal $mm unless noted
A5: Total debt incl. finance leases | B5: 0.112377 | C5: $mm | D5: Source: uploaded BS, Total Debt FY2025
A6: Cash & equivalents | B6: 0.035934 | C6: $mm | D6: Source: uploaded BS FY2025
A7: Short-term investments | B7: 0.018763 | C7: $mm | D7: Source: uploaded BS FY2025 (none reported)
A8: of which finance/capital lease obligation | B8: 0 | C8: $mm | D8: Source: uploaded BS FY2025 (LT capital lease)
A9: Common shares outstanding | B9: 0.015005 | C9: mm | D9: Source: Ordinary Shares Number FY2025 (7,037,502,356 / 1e6) — full precision
A10: Common stock equity (CSE) | B10: 0.073733 | C10: $mm | D10: Source: Common Stock Equity FY2025 (excl. $17.96bn minority int.)
A11: Interest expense (FY2025) | B11: 0 | C11: $mm | D11: Source: uploaded IS FY2025
A12: Operating income, adjusted (FY2025) | B12: 0.13305 | C12: $mm | D12: Source: Operating Income FY2025
A13: Diluted EPS (FY2025) | B13: 7.464996 | C13: $ | D13: Source: uploaded IS FY2025
A14: Effective tax rate (FY2025) | B14: 0.1561 | C14: frac | D14: Source: Tax Rate for Calcs FY2025
A15: Dividends per share, period-0 (FY2025) | B15: 0.96 | C15: $ | D15: Source: uploaded dividends CSV, 4×0.278 ex-2025
A17: — derived —
A18: NFO = debt − cash − STI | B18: =in_debt-in_cash-in_sti -> 0.05768 | C18: $mm
A19: NOA = CSE + NFO | B19: =anchor_cse0+anchor_nfo0 -> 0.131413 | C19: $mm | D19: [ADD] completes A.1 anchor
A20: NFO per share (nominal $) | B20: =anchor_nfo0/anchor_shares0 -> 3.844052
A21: BPS = CSE / shares (nominal $) | B21: =anchor_cse0/anchor_shares0 -> 4.9138954
A22: FLEV = NFO / CSE | B22: =anchor_nfo0/anchor_cse0 -> 0.78228202
A24: VALUATION CONTROLS
A25: Current price ($/sh) [LIVE — refresh each session] | B25: 315
A26: Explicit forecast horizon N (≤ 30) | B26: 4
A27: Terminal growth g (continuing, real) | B27: 0 | D27: Enterprise continuing NOA growth; equity AEG tail is normal-earnings capitalisation (no separate g)
A28: Equity risk premium ERP (real) | B28: 0.04 | D28: flat; replace with beta/ERP build (Backlog)
A29: COE mode {Single | Term} (ρE) | B29: Term | D29: equity ρE term-structure vs single
A30: Enterprise ρF mode {Single | Term} | B30: Term
A31: Enterprise ρF single (real) | B31: 0.06
A32: Enterprise ρF long-run r_LR (real) | B32: 0.07
A33: ρD mode {Single | Term} | B33: Term
A34: Valuation READ toggle {Equity path | Enterprise path} | B34: Equity path | D34: [ADD] second toggle (C.2): which forecast series valuation reads
A36: FORECAST CONTROLS (toggle wired in Step 5)
A37: Forecast-side {Equity | Enterprise} | B37: Enterprise | D37: Equity default: type EPS/DPS → derive OI, NOA
A38: EPS / DPS path | B38: (forecast-tab driver rows) | D38: per-year drivers on the forecast tab (G.1); migrate in Step 5
A39: Default dividend payout (seed; per-year driver in Step 5) | B39: 0.1286 | D39: [ADD reserved] seed = DPS0/EPS0 = 1.112/3.04; payout is a driver, not a scalar (fork 2)
A41: REFORMULATION ASSUMPTIONS (wired in Step 3)
A42: PP&E composite depreciable life L (yr) | B42: 10.37 | D42: gross PP&E $370B ÷ deprec $20.7B ≈ 18; avg age ≈11
A43: R&D amortization life (yr; ≈0 telecom) | B43: 5 | D43: R&D reserve life (yr); 0 if R&D immaterial
A44: Deflator base year | B44: 2026
A45: R&D expense, period-0 ($mm) | B45: 0 | D45: Reported R&D read here; 0 if none reported.
A46: BUYBACK CONTROLS (wired in Step 7)
A47: Buyback adjustment {On | Off} | B47: On | D47: default On; wire into mainline equity+enterprise
A49: PROMOTED MAGIC NUMBERS (named here; formulas repointed in their step)
A50: Econ materiality threshold (frac) | B50: 0.15 | D50: Econ Statements flag; Step 3
A51: Bridge day-count (days/yr) | B51: 365 | D51: Bridge tenor conversion; also allow-list structural
A52: Presentation COE grid — pt 1 (low) | B52: 0.05
A53: Presentation COE grid — pt 2 | B53: 0.055
A54: Presentation COE grid — pt 3 (mid) | B54: 0.06
A55: Presentation COE grid — pt 4 | B55: 0.065
A56: Presentation COE grid — pt 5 (high) | B56: 0.07
A57: Presentation growth axis — low | B57: 0.04
A58: Presentation growth axis — mid | B58: 0.06
A59: Presentation growth axis — high | B59: 0.08
A60: Enterprise NOA growth (real) — placeholder | B60: 0.02 | D60: Step 3 rebuild redefines the enterprise growth path
A62: ALLOW-LIST (structural constants tolerated inside formulas)
A63: 0, 1, unit conversion 1e6, day-count 365, tenor index 1..30. Market Data rate SPOT rows and tenor axis are SOURCED market observations — the rate-side data tab — not violations.
A64: Tie tolerance (structural ε) | B64: 1e-05
A65: AS-OF / GLOBAL
A66: Anchor / period-0 fiscal year | B66: 2025 | D66: Latest reported FY; the reformulation period-0.
A67: Restatement view {Economic | Reported} | B67: Economic | D67: Economic = BEA-restated real 2026$; Reported = as-filed nominal basic reformulation.
A68: Financing mode {Target FLEV | Funding policy} | B68: Target FLEV
A69: Scenario {Bear | Consensus | Bull | Normal} | B69: Consensus | D69: Normal = zero-economic-profit structural floor (no growth, no buyback).
A70: Implied grid — g start | B70: -0.08
A71: Implied grid — g step | B71: 0.01

Sheet Audit
A1: AUDIT — STANDING FORMULA-INTEGRITY & TIE CHECKS
A2: B5/B6 cover the LIVE in-sheet identity ties only. Constants/magic/colour are NOT computed in-sheet: run the out-of-band auditor (audit.py) separately — it must read TOTAL 0. BOTH gates (this PASS and audit.py TOTAL 0) must be green to trust output.
A4: MASTER STATUS
A5: Grand total (LIVE identity residuals only; target 0) — tautological terms excluded, see rows 27/28 | B5: =B31+B44+B50+B58+B29+B63+B72+B77 -> 1.007007e-15
A6: Status | B6: =IF(B5<in_tie_tol,"PASS — all identities tie","FAIL — investigate") -> PASS — all identities tie | D6: tolerance 1e-5 absorbs floating-point residuals on the FCFE/clean-surplus ties
A8: CHECK 1-3 — EXTERNAL AUDITOR (audit.py): constants / magic / colour. Run separately; NOT summed into B5.
A9: (external) stray-constant count — informational mirror, may be stale | B9: =SUM(B11:B12) -> 0
A10: Tab | B10: count | C10: target
A11: (no calc tabs yet — rows added as IS/BS/CF/reform/rates/forecast/val land)
A14: CHECK 2 — Magic numbers in formulas (auditor-fed; run audit.py to refresh)
A15: (external) magic-literal count — informational mirror, may be stale | B15: 0 | C15: → target 0 | D15: auditor diagnostic readout; 0 = fresh book, no formulas off-surface
A17: CHECK 3 — Colour integrity (auditor-fed)
A18: (external) colour-violation count — informational mirror, may be stale | B18: 0 | C18: → target 0 | D18: blue only on Inputs / reported-data / forecast driver surface (G.1)
A20: CHECK 4 — Tie block (identities = 0; live in-sheet)
A21: Identity | B21: residual | C21: target | D21: status
A22: NOA = CSE + NFO | B22: =in_noa0-anchor_cse0-anchor_nfo0 -> 0 | C22: 0 | D22: =IF(ABS(B22)<0.000001,"tie","BREAK") -> tie
A23: FLEV·CSE = NFO | B23: =in_flev0*anchor_cse0-anchor_nfo0 -> 0 | C23: 0 | D23: =IF(ABS(B23)<0.000001,"tie","BREAK") -> tie
A24: BPS·shares = CSE | B24: =in_bps0*anchor_shares0-anchor_cse0 -> 0 | C24: 0 | D24: =IF(ABS(B24)<0.000001,"tie","BREAK") -> tie
A25: NFO/sh·shares = NFO | B25: =in_nfops0*anchor_shares0-anchor_nfo0 -> 0 | C25: 0 | D25: =IF(ABS(B25)<0.000001,"tie","BREAK") -> tie
A26: Clean-surplus articulation (Step 3) | D26: (reserved)
A27: (decorative) Equity↔Enterprise tie — identically 0; NOT summed into B5 | B27: =ABS(ev_tie) -> 0 | D27: =IF(ABS(B27)<0.00001,"tie","BREAK") -> tie
A28: (decorative) Value-additivity V(OI)=V(EPS)+V(NFE) — identically 0 by definition; NOT summed into B5 | B28: =ABS(val_voi-val_intrinsic-val_vnfe) -> 0 | D28: =IF(ABS(B28)<0.00001,"tie","BREAK") -> tie
A29: Buyback VP6 invariance (V_with=V_without) | B29: =ABS(bb_vp6_tie) -> 0 | D29: =IF(ABS(B29)<in_tie_tol,"tie","BREAK") -> tie
A31: Σ |tie residuals| (target 0) | B31: =SUMPRODUCT(ABS(B22:B25)) -> 0
A33: CHECK 4b — Inputs anchor = reported FY2025 (reconciliation ties)
A34: Identity | B34: residual | C34: target | D34: status
A35: in_debt = reported Total Debt | B35: =in_debt-rep_debt_fy0 -> 0 | C35: 0 | D35: =IF(ABS(B35)<0.000001,"tie","BREAK") -> tie
A36: in_cash = reported Cash | B36: =in_cash-rep_cash_fy0 -> 0 | C36: 0 | D36: =IF(ABS(B36)<0.000001,"tie","BREAK") -> tie
A37: anchor_cse0 = reported CSE | B37: =anchor_cse0-rep_cse_fy0 -> 0 | C37: 0 | D37: =IF(ABS(B37)<0.000001,"tie","BREAK") -> tie
A38: anchor_shares0 = reported shares | B38: =anchor_shares0-rep_shares_fy0 -> 0 | C38: 0 | D38: =IF(ABS(B38)<0.000001,"tie","BREAK") -> tie
A39: anchor_eps0 = reported Diluted EPS | B39: =anchor_eps0-rep_eps_fy0 -> 0 | C39: 0 | D39: =IF(ABS(B39)<0.000001,"tie","BREAK") -> tie
A40: in_intexp0 = reported Interest Exp | B40: =in_intexp0-rep_intexp_fy0 -> 0 | C40: 0 | D40: =IF(ABS(B40)<0.000001,"tie","BREAK") -> tie
A41: in_oiadj0 = reported Operating Income | B41: =in_oiadj0-rep_oi_fy0 -> 0 | C41: 0 | D41: =IF(ABS(B41)<0.000001,"tie","BREAK") -> tie
A42: in_tax0 = reported Tax Rate | B42: =in_tax0-rep_tax_fy0 -> 0 | C42: 0 | D42: =IF(ABS(B42)<0.000001,"tie","BREAK") -> tie
A44: Σ |reconciliation residuals| (target 0) | B44: =SUMPRODUCT(ABS(B35:B42)) -> 0
A46: CHECK 4c — Reformulation ties (=0)
A47: Σ|partition tie NOA−NFO−CSE (nom)| | B47: =SUMPRODUCT(ABS(es_tie_partition)) -> 0 | D47: =IF(ABS(B47)<0.000001,"tie","BREAK") -> tie
A48: Σ|real tie NOA−NFO−CSE| | B48: =SUMPRODUCT(ABS(es_tie_real)) -> 0 | D48: =IF(ABS(B48)<0.000001,"tie","BREAK") -> tie
A49: Cap Engine anchor = per-year 2025 | B49: =anchor_real_net_ppe-INDEX(ce_real_net_series,MATCH(in_anchor_year,ce_years,0)) -> 0 | D49: =IF(ABS(B49)<0.000001,"tie","BREAK") -> tie
A50: Σ |reformulation ties| | B50: =SUMPRODUCT(ABS(B47:B49)) -> 0
A52: memo: clean-surplus is a dirty-surplus residual (Econ St r70), not a =0 tie; reformulated CI absorbs it.
A54: CHECK 4d — Forecast engine identities (=0)
A55: Σ|NOA−NFO−CSE| | B55: =SUMPRODUCT(ABS(fc_tie_bs)) -> 0 | D55: =IF(ABS(B55)<0.00001,"tie","BREAK") -> tie
A56: Σ|EPS×sh−NI| | B56: =SUMPRODUCT(ABS(fc_tie_eps)) -> 0 | D56: =IF(ABS(B56)<0.00001,"tie","BREAK") -> tie
A57: Σ|FCFE−distribution| | B57: =SUMPRODUCT(ABS(fc_tie_fcfe)) -> 1.6740082e-16 | D57: =IF(ABS(B57)<0.00001,"tie","BREAK") -> tie
A58: Σ |forecast ties| | B58: =SUMPRODUCT(ABS(B55:B57)) -> 1.6740082e-16
A60: CHECK 5 — DCF / RI / FCFE / FCFF reconciliation (=0)
A61: V(FCFE) − V(RI) | B61: =ABS(dcf_tie_fcfe) -> 0 | D61: =IF(ABS(B61)<in_tie_tol*ABS(dcf_ri),"tie","BREAK") -> tie
A62: Equity(FCFF) − V(RI) | B62: =ABS(dcf_tie_fcff) -> 0 | D62: =IF(ABS(B62)<in_tie_tol*ABS(dcf_ri),"tie","BREAK") -> tie
A63: Σ |DCF recon ties| | B63: =B61+B62 -> 0
A66: CHECK 6 — cross-tab: Valuation AEG form vs DCF Reconciliation RI form (=0)
A67: Valuation V(EPS) $/sh [HEADLINE, AEG form] | B67: =Valuation!B52 -> 146.5168
A68: DCF Rec V(RI) $/sh [residual-income form, four-method tied] | B68: ='DCF Reconciliation'!B45 -> 146.5168
A69: gap $/sh (AEG - RI) | B69: =B67-B68 -> 0
A70: gap as % of RI form | B70: =IF(B68=0,"",B69/B68) -> 0
A71: NOTE: identical only when the AEG terms are capitalised with the annuity factor implied by the ACTUAL cost-of-equity curve.
A72: Sigma |cross-tab tie| [GATE: summed into B5] | B72: =ABS(B69) -> 0
A74: CHECK 7 — operations: value-weighted direct vs additive, and flow additivity [both LIVE, both summed into B5]
A75: V(ops)@rho_F* − V(ops) additive | B75: =ABS('DCF Reconciliation'!B56) -> 0
A76: Σ|FCFF − (FCFE + FCFD)| | B76: =ABS('DCF Reconciliation'!B57) -> 8.3960616e-16
A77: Σ |CHECK 7| [GATE: summed into B5] | B77: =B75+B76 -> 8.3960616e-16

Sheet Income Statement
A1: INCOME STATEMENT — Apple Inc. (AAPL)
A2: Filed data (Apple Inc.). $mm unless noted · per-share $ · ratios frac · shares mm. Blue = filed input. Loaded by the AEG data pipeline.
A3: Line item | B3: 1985 | C3: 1986 | D3: 1987 | E3: 1988 | F3: 1989 | G3: 1990 | H3: 1991 | I3: 1992 | J3: 1993 | K3: 1994 | L3: 1995 | M3: 1996 | N3: 1997 | O3: 1998 | P3: 1999 | Q3: 2000 | R3: 2001 | S3: 2002 | T3: 2003 | U3: 2004 | V3: 2005 | W3: 2006 | X3: 2007 | Y3: 2008 | Z3: 2009 | AA3: 2010 | AB3: 2011 | AC3: 2012 | AD3: 2013 | AE3: 2014 | AF3: 2015 | AG3: 2016 | AH3: 2017 | AI3: 2018 | AJ3: 2019 | AK3: 2020 | AL3: 2021 | AM3: 2022 | AN3: 2023 | AO3: 2024 | AP3: 2025
A4: Total Revenue | B4: 0.001918 | C4: 0.001902 | D4: 0.002661 | E4: 0.004071 | F4: 0.005284 | G4: 0.005558 | H4: 0.006309 | I4: 0.007087 | J4: 0.007977 | K4: 0.009189 | L4: 0.011062 | M4: 0.009833 | N4: 0.007081 | O4: 0.005941 | P4: 0.006134 | Q4: 0.007983 | R4: 0.005363 | S4: 0.005742 | T4: 0.006207 | U4: 0.008279 | V4: 0.013931 | W4: 0.019315 | X4: 0.024006 | Y4: 0.032479 | Z4: 0.042603 | AA4: 0.065225 | AB4: 0.108249 | AC4: 0.156508 | AD4: 0.17091 | AE4: 0.182795 | AF4: 0.233715 | AG4: 0.215639 | AH4: 0.229234 | AI4: 0.265595 | AJ4: 0.260174 | AK4: 0.274515 | AL4: 0.365817 | AM4: 0.394328 | AN4: 0.383285 | AO4: 0.391035 | AP4: 0.416161
A5: Operating Revenue
A6: Cost of Revenue | B6: 0.001076 | C6: 0.00084 | D6: 0.001226 | E6: 0.001913 | F6: 0.00257 | G6: 0.002403 | H6: 0.00311 | I6: 0.003991 | J6: 0.005249 | K6: 0.006845 | L6: 0.008204 | M6: 0.008865 | N6: 0.005713 | O6: 0.004462 | P6: 0.004438 | Q6: 0.005817 | R6: 0.004128 | S6: 0.004139 | T6: 0.004499 | U6: 0.006022 | V6: 0.009889 | W6: 0.013717 | X6: 0.015852 | Y6: 0.021334 | Z6: 0.025751 | AA6: 0.039541 | AB6: 0.064431 | AC6: 0.087846 | AD6: 0.106606 | AE6: 0.112258 | AF6: 0.140089 | AG6: 0.131376 | AH6: 0.141048 | AI6: 0.163756 | AJ6: 0.161782 | AK6: 0.169559 | AL6: 0.212981 | AM6: 0.223546 | AN6: 0.214137 | AO6: 0.210352 | AP6: 0.22096
A7: Gross Profit | B7: 0.000842 | C7: 0.001062 | D7: 0.001435 | E7: 0.002158 | F7: 0.002714 | G7: 0.003155 | H7: 0.003199 | I7: 0.003095 | J7: 0.002728 | K7: 0.002344 | L7: 0.002858 | M7: 0.000968 | N7: 0.001368 | O7: 0.001479 | P7: 0.001696 | Q7: 0.002166 | R7: 0.001235 | S7: 0.001603 | T7: 0.001708 | U7: 0.002259 | V7: 0.004042 | W7: 0.005598 | X7: 0.008154 | Y7: 0.011145 | Z7: 0.016852 | AA7: 0.025684 | AB7: 0.043818 | AC7: 0.068662 | AD7: 0.064304 | AE7: 0.070537 | AF7: 0.093626 | AG7: 0.084263 | AH7: 0.088186 | AI7: 0.101839 | AJ7: 0.098392 | AK7: 0.104956 | AL7: 0.152836 | AM7: 0.170782 | AN7: 0.169148 | AO7: 0.180683 | AP7: 0.195201
A8: Operating Expense
A9: Selling General and Administrative | B9: 0.000653 | C9: 0.000737 | D9: 0.000993 | E9: 0.00146 | F9: 0.001955 | G9: 0.00224 | H9: 0.002547 | I9: 0.002289 | J9: 0.002618 | K9: 0.001384 | L9: 0.001583 | M9: 0.001568 | N9: 0.001286 | O9: 0.000908 | P9: 0.000996 | Q9: 0.001166 | R9: 0.001138 | S9: 0.001111 | T9: 0.001212 | U9: 0.001421 | V9: 0.001859 | W9: 0.002433 | X9: 0.002963 | Y9: 0.003761 | Z9: 0.004149 | AA9: 0.005517 | AB9: 0.007599 | AC9: 0.00904 | AD9: 0.00973 | AE9: 0.011993 | AF9: 0.014329 | AG9: 0.014194 | AH9: 0.015261 | AI9: 0.016705 | AJ9: 0.018245 | AK9: 0.019916 | AL9: 0.021973 | AM9: 0.025094 | AN9: 0.024932 | AO9: 0.026097 | AP9: 0.027601
A10: Depreciation Amortization Depletion
A11: Depreciation & amortization
A12: Other Operating Expenses
A13: Operating Income | B13: 0.000147 | C13: 0.000273 | D13: 0.000371 | E13: 0.00062 | F13: 0.000634 | G13: 0.000712 | H13: 0.000447 | I13: 0.000806 | J13: 0.00011 | K13: 0.000522 | L13: 0.000684 | M13: -0.001383 | N13: -0.00107 | O13: 0.000261 | P13: 0.000359 | Q13: 0.000522 | R13: -0.000344 | S13: 1.7e-05 | T13: -1e-06 | U13: 0.000313 | V13: 0.001643 | W13: 0.002453 | X13: 0.004409 | Y13: 0.006275 | Z13: 0.01137 | AA13: 0.018385 | AB13: 0.03379 | AC13: 0.055241 | AD13: 0.048999 | AE13: 0.052503 | AF13: 0.07123 | AG13: 0.060024 | AH13: 0.061344 | AI13: 0.070898 | AJ13: 0.06393 | AK13: 0.066288 | AL13: 0.108949 | AM13: 0.119437 | AN13: 0.114301 | AO13: 0.123216 | AP13: 0.13305
A14: Net Non Operating Interest Income Expense
A15: Interest Income Non Operating
A16: Interest Expense Non Operating
A17: Other Income Expense
A18: Earnings from Equity Interest
A19: Special Income Charges
A20: Restructuring & Mergers Acquisition
A21: Impairment of Capital Assets
A22: Write Off
A23: Other Special Charges
A24: Gain on Sale of PPE
A25: Other Non Operating Income Expenses
A26: Pretax Income | B26: 0.00012 | C26: 0.00031 | D26: 0.00041 | E26: 0.000656 | F26: 0.000744 | G26: 0.000779 | H26: 0.0005 | I26: 0.000856 | J26: 0.00014 | K26: 0.0005 | L26: 0.000674 | M26: -0.001295 | N26: -0.001045 | O26: 0.000329 | P26: 0.000676 | Q26: 0.001092 | R26: -5.2e-05 | S26: 8.7e-05 | T26: 9.2e-05 | U26: 0.00037 | V26: 0.001808 | W26: 0.002818 | X26: 0.005008 | Y26: 0.006895 | Z26: 0.012066 | AA26: 0.01854 | AB26: 0.034205 | AC26: 0.055763 | AD26: 0.050155 | AE26: 0.053483 | AF26: 0.072515 | AG26: 0.061372 | AH26: 0.064089 | AI26: 0.072903 | AJ26: 0.065737 | AK26: 0.067091 | AL26: 0.109207 | AM26: 0.119103 | AN26: 0.113736 | AO26: 0.123485 | AP26: 0.132729
A27: Tax Provision | B27: 5.9e-05 | C27: 0.000156 | D27: 0.000193 | E27: 0.000256 | F27: 0.00029 | G27: 0.000304 | H27: 0.00019 | I27: 0.000325 | J27: 5.3e-05 | K27: 0.00019 | L27: 0.00025 | M27: -0.000479 | N27: 0.000281 | O27: 2e-05 | P27: 7.5e-05 | Q27: 0.000306 | R27: -1.5e-05 | S27: 2.2e-05 | T27: 2.4e-05 | U27: 0.000104 | V27: 0.00048 | W27: 0.000829 | X27: 0.001512 | Y27: 0.002061 | Z27: 0.003831 | AA27: 0.004527 | AB27: 0.008283 | AC27: 0.01403 | AD27: 0.013118 | AE27: 0.013973 | AF27: 0.019121 | AG27: 0.015685 | AH27: 0.015738 | AI27: 0.013372 | AJ27: 0.010481 | AK27: 0.00968 | AL27: 0.014527 | AM27: 0.0193 | AN27: 0.016741 | AO27: 0.029749 | AP27: 0.020719
A28: Net Income Common Stockholders | Q28: 0.000786 | S28: 6.5e-05 | T28: 6.8e-05 | U28: 0.000276 | V28: 0.001335 | W28: 0.001989 | X28: 0.003496 | Y28: 0.004834 | Z28: 0.008235 | AA28: 0.014013 | AB28: 0.025922 | AC28: 0.041733 | AD28: 0.037037 | AE28: 0.03951 | AF28: 0.053394 | AG28: 0.045687 | AH28: 0.048351 | AI28: 0.059531 | AJ28: 0.055256 | AK28: 0.057411 | AL28: 0.09468 | AM28: 0.099803 | AN28: 0.096995 | AO28: 0.093736 | AP28: 0.11201
A29: Net Income
A30: Net Income Including Non-Controlling Interests
A31: Net Income Continuous Operations
A32: Net Income Discontinuous Operations
A33: Net Income Extraordinary
A34: Net Income from Tax Loss Carryforward
A35: Minority Interests
A36: Preferred Stock Dividends
A37: Otherunder Preferred Stock Dividend
A38: Average Dilution Earnings
A39: Diluted NI Available to Com Stockholders
A40: Basic EPS
A41: Diluted EPS | B41: 0.004464 | C41: 0.010714 | D41: 0.014821 | E41: 0.0275 | F41: 0.031607 | G41: 0.03375 | H41: 0.023036 | I41: 0.03863 | J41: 0.006481 | K41: 0.023311 | L41: 0.030766 | M41: -0.058882 | N41: -0.074014 | O41: 0.01643 | P41: 0.03081 | Q41: 0.038953 | R41: -0.001292 | S41: 0.003208 | T41: 0.003341 | U41: 0.012723 | V41: 0.055642 | W41: 0.08095 | X41: 0.140401 | Y41: 0.191371 | Z41: 0.324262 | AA41: 0.541211 | AB41: 0.988406 | AC41: 1.576619 | AD41: 1.419775 | AE41: 1.613269 | AF41: 2.304219 | AG41: 2.076576 | AH41: 2.301687 | AI41: 2.976485 | AJ41: 2.971447 | AK41: 3.275348 | AL41: 5.61402 | AM41: 6.1132 | AN41: 6.134053 | AO41: 6.083555 | AP41: 7.464996
A42: Basic Average Shares
A43: Diluted Average Shares
A44: Total Operating Income as Reported
A45: Total Expenses
A46: Net Income from Continuing & Discontinued Operation
A47: Normalized Income
A48: Interest Income
A49: Interest Expense | B49: 5.5e-05 | C49: 7.3e-05 | D49: 7.8e-05 | E49: 7.2e-05 | F49: 0.00022 | G49: 0.000133 | H49: 0.000105 | I49: 9e-06 | J49: 1.2e-05 | K49: 4e-05 | L49: 4.8e-05 | M49: 6e-05 | N49: 7.1e-05 | O49: 6.2e-05 | P49: 4.7e-05 | Q49: 2.1e-05 | R49: 1.6e-05 | S49: 1.1e-05 | T49: 8e-06 | U49: 3e-06 | V49: 0.000165 | W49: 0.000365 | X49: 0.000599 | Y49: 0.00062 | Z49: 0.000326 | AA49: 0.000155 | AB49: 0.000415 | AC49: 0.000522 | AD49: 0.000136 | AE49: 0.000384 | AF49: 0.000733 | AG49: 0.001456 | AH49: 0.002323 | AI49: 0.00324 | AJ49: 0.003576 | AK49: 0.002873 | AL49: 0.002645 | AM49: 0.002931 | AN49: 0.003933 | AO49: 0
A50: Net Interest Income
A51: EBIT
A52: EBITDA | B52: 0.000189 | C52: 0.000325 | D52: 0.000442 | E52: 0.000698 | F52: 0.000759 | G52: 0.000915 | H52: 0.000652 | I52: 0.001081 | J52: 0.000318 | K52: 0.000708 | L52: 0.000849 | M52: -0.001119 | N52: -0.000856 | O52: 0.000502 | P52: 0.000808 | Q52: 0.001197 | R52: 6.4e-05 | S52: 0.000212 | T52: 0.000138 | U52: 0.000523 | V52: 0.001822 | W52: 0.002678 | X52: 0.004724 | Y52: 0.007304 | Z52: 0.012029 | AA52: 0.019412 | AB52: 0.036019 | AC52: 0.05904 | AD52: 0.057048 | AE52: 0.061813 | AF52: 0.084505 | AG52: 0.073333 | AH52: 0.076569 | AI52: 0.087046 | AJ52: 0.08186 | AK52: 0.08102 | AL52: 0.123136 | AM52: 0.130541 | AN52: 0.12582 | AO52: 0.134661 | AP52: 0.144427
A53: Reconciled Cost of Revenue
A54: Reconciled Depreciation | AH54: 0.010157 | AI54: 0.010903 | AJ54: 0.012547 | AK54: 0.011056 | AL54: 0.011284 | AM54: 0.011104 | AN54: 0.011519 | AO54: 0.011445 | AP54: 0.011698
A55: Net Income from Continuing Operation Net Minority Interest
A56: Total Unusual Items Excluding Goodwill
A57: Total Unusual Items
A58: Normalized EBITDA
A59: Tax Rate for Calcs | B59: 0.49 | C59: 0.502905 | D59: 0.470029 | E59: 0.389973 | F59: 0.390031 | G59: 0.389981 | H59: 0.380028 | I59: 0.380012 | J59: 0.3801 | K59: 0.379999 | L59: 0.37092 | O59: 0.06079 | P59: 0.110947 | Q59: 0.28022 | S59: 0.252874 | T59: 0.26087 | U59: 0.281081 | V59: 0.265487 | W59: 0.29418 | X59: 0.301917 | Y59: 0.298912 | Z59: 0.317504 | AA59: 0.244175 | AB59: 0.242158 | AC59: 0.251601 | AD59: 0.261549 | AE59: 0.261261 | AF59: 0.263683 | AG59: 0.255573 | AH59: 0.245565 | AI59: 0.183422 | AJ59: 0.159438 | AK59: 0.144282 | AL59: 0.133023 | AM59: 0.162045 | AN59: 0.147192 | AO59: 0.240912 | AP59: 0.1561
A60: Tax Effect of Unusual Items

Sheet Balance Sheet
A1: BALANCE SHEET — Apple Inc. (AAPL)
A2: Filed data (Apple Inc.). $mm unless noted · per-share $ · ratios frac · shares mm. Blue = filed input. Loaded by the AEG data pipeline.
A3: Line item | B3: 1985 | C3: 1986 | D3: 1987 | E3: 1988 | F3: 1989 | G3: 1990 | H3: 1991 | I3: 1992 | J3: 1993 | K3: 1994 | L3: 1995 | M3: 1996 | N3: 1997 | O3: 1998 | P3: 1999 | Q3: 2000 | R3: 2001 | S3: 2002 | T3: 2003 | U3: 2004 | V3: 2005 | W3: 2006 | X3: 2007 | Y3: 2008 | Z3: 2009 | AA3: 2010 | AB3: 2011 | AC3: 2012 | AD3: 2013 | AE3: 2014 | AF3: 2015 | AG3: 2016 | AH3: 2017 | AI3: 2018 | AJ3: 2019 | AK3: 2020 | AL3: 2021 | AM3: 2022 | AN3: 2023 | AO3: 2024 | AP3: 2025
A4: Total Assets | B4: 0.000936 | C4: 0.00116 | D4: 0.001478 | E4: 0.002082 | F4: 0.002744 | G4: 0.002976 | H4: 0.003494 | I4: 0.004224 | J4: 0.005171 | K4: 0.005303 | L4: 0.006231 | M4: 0.005364 | N4: 0.004233 | O4: 0.004289 | P4: 0.005161 | Q4: 0.006803 | R4: 0.006021 | S4: 0.006298 | T4: 0.006815 | U4: 0.00805 | V4: 0.011551 | W4: 0.017205 | X4: 0.025347 | Y4: 0.039572 | Z4: 0.053851 | AA4: 0.075183 | AB4: 0.116371 | AC4: 0.176064 | AD4: 0.207 | AE4: 0.231839 | AF4: 0.290479 | AG4: 0.321686 | AH4: 0.375319 | AI4: 0.365725 | AJ4: 0.338516 | AK4: 0.323888 | AL4: 0.351002 | AM4: 0.352755 | AN4: 0.352583 | AO4: 0.36498 | AP4: 0.359241
A5: Current Assets
A6: Cash, Cash Equivalents & Short Term Investments
A7: Cash And Cash Equivalents | B7: 0.000337 | C7: 0.000576 | D7: 0.000565 | E7: 0.000546 | F7: 0.000438 | G7: 0.000375 | H7: 0.000604 | I7: 0.000499 | J7: 0.000676 | K7: 0.001203 | L7: 0.000756 | M7: 0.001552 | N7: 0.00123 | O7: 0.001481 | P7: 0.001326 | Q7: 0.001191 | R7: 0.00231 | S7: 0.002252 | T7: 0.003396 | U7: 0.002969 | V7: 0.003491 | W7: 0.006392 | X7: 0.009352 | Y7: 0.011875 | Z7: 0.005263 | AA7: 0.011261 | AB7: 0.009815 | AC7: 0.010746 | AD7: 0.014259 | AE7: 0.013844 | AF7: 0.02112 | AG7: 0.020484 | AH7: 0.020289 | AI7: 0.025913 | AJ7: 0.048844 | AK7: 0.038016 | AL7: 0.03494 | AM7: 0.023646 | AN7: 0.029965 | AO7: 0.029943 | AP7: 0.035934
A8: Cash
A9: Cash Equivalents
A10: Other Short Term Investments | J10: 0.000216 | K10: 5.4e-05 | L10: 0.000196 | M10: 0.000193 | N10: 0.000229 | O10: 0.000819 | P10: 0.0019 | Q10: 0.002836 | R10: 0.002026 | S10: 0.002085 | T10: 0.00117 | U10: 0.002495 | V10: 0.00477 | W10: 0.003718 | X10: 0.006034 | Y10: 0.012615 | Z10: 0.018201 | AA10: 0.014359 | AB10: 0.016137 | AC10: 0.018383 | AD10: 0.026287 | AE10: 0.011233 | AF10: 0.020481 | AG10: 0.046671 | AH10: 0.053892 | AI10: 0.040388 | AJ10: 0.051713 | AK10: 0.052927 | AL10: 0.027699 | AM10: 0.024658 | AN10: 0.03159 | AO10: 0.035228 | AP10: 0.018763
A11: Receivables
A12: Accounts receivable
A13: Gross Accounts Receivable
A14: Allowance For Doubtful Accounts Receivable
A15: Loans Receivable
A16: Notes Receivable
A17: Inventory
A18: Raw Materials
A19: Prepaid Assets
A20: Restricted Cash
A21: Current Deferred Assets
A22: Current Deferred Taxes Assets
... A25: Total non-current assets
A26: Net PPE | B26: 9e-05 | C26: 0.000107 | D26: 0.00013 | E26: 0.000207 | F26: 0.000334 | G26: 0.000398 | H26: 0.000448 | I26: 0.000462 | J26: 0.00066 | K26: 0.000667 | L26: 0.000711 | M26: 0.000598 | N26: 0.000486 | O26: 0.000348 | P26: 0.000318 | Q26: 0.000313 | R26: 0.000564 | S26: 0.000621 | T26: 0.000669 | U26: 0.000707 | V26: 0.000817 | W26: 0.001281 | X26: 0.001832 | Y26: 0.002455 | Z26: 0.002954 | AA26: 0.004768 | AB26: 0.007777 | AC26: 0.015452 | AD26: 0.016597 | AE26: 0.020624 | AF26: 0.022471 | AG26: 0.02701 | AH26: 0.033783 | AI26: 0.041304 | AJ26: 0.037378 | AK26: 0.036766 | AL26: 0.03944 | AM26: 0.042117 | AN26: 0.043715 | AO26: 0.04568 | AP26: 0.049834
A27: Gross PPE | J27: 0.001413 | K27: 0.001452 | L27: 0.001492 | M27: 0.001348 | N27: 0.001195 | O27: 0.000824 | P27: 0.000729 | Q27: 0.0007 | R27: 0.00096 | S27: 0.001057 | T27: 0.001174 | U27: 0.001298 | V27: 0.001481 | W27: 0.002075 | X27: 0.002841 | Y27: 0.003747 | Z27: 0.004667 | AA27: 0.007234 | AB27: 0.011768 | AC27: 0.021887 | AD27: 0.028519 | AE27: 0.039015 | AF27: 0.049257 | AG27: 0.061245 | AH27: 0.075076 | AI27: 0.090403 | AJ27: 0.095957 | AK27: 0.103526 | AL27: 0.109723 | AM27: 0.114457 | AN27: 0.114599 | AO27: 0.119128 | AP27: 0.125848
A28: Properties
A29: Land And Improvements
A30: Buildings And Improvements
A31: Machinery Furniture Equipment
A32: Other Properties
A33: Construction in Progress
A34: Accumulated Depreciation
A35: Goodwill And Other Intangible Assets
A36: Goodwill
A37: Other Intangible Assets
A38: Investments And Advances
A39: Long Term Equity Investment
... A45: Other Non Current Assets
A46: Total Liabilities Net Minority Interest | B46: 0.000386 | C46: 0.000466 | D46: 0.000641 | E46: 0.001079 | F46: 0.001258 | G46: 0.001529 | H46: 0.001727 | I46: 0.002036 | J46: 0.003145 | K46: 0.002919 | L46: 0.00333 | M46: 0.003306 | N46: 0.003033 | O46: 0.002647 | P46: 0.002057 | Q46: 0.002696 | R46: 0.002101 | S46: 0.002203 | T46: 0.002592 | U46: 0.002974 | V46: 0.004085 | W46: 0.007221 | X46: 0.010815 | Y46: 0.018542 | Z46: 0.026019 | AA46: 0.027392 | AB46: 0.039756 | AC46: 0.057854 | AD46: 0.083451 | AE46: 0.120292 | AF46: 0.171124 | AG46: 0.193437 | AH46: 0.241272 | AI46: 0.258578 | AJ46: 0.248028 | AK46: 0.258549 | AL46: 0.287912 | AM46: 0.302083 | AN46: 0.290437 | AO46: 0.30803 | AP46: 0.285508
A47: Current Liabilities
A48: Payables And Accrued Expenses
A49: Payables
A50: Accounts Payable
A51: Total Tax Payable
A52: Income Tax Payable
A53: Dividends Payable
A54: Other Payable
A55: Current Accrued Expenses
A56: Interest Payable
A57: Pension & Other Post Retirement Benefit Plans Current
A58: Current Debt And Capital Lease Obligation
... A83: Additional Paid in Capital
A84: Retained Earnings | B84: 0.00032 | C84: 0.000474 | D84: 0.000573 | E84: 0.000776 | F84: 0.001176 | G84: 0.001312 | H84: 0.001492 | I84: 0.001904 | J84: 0.001843 | K84: 0.002096 | L84: 0.002464 | M84: 0.001634 | N84: 0.000589 | O84: 0.000898 | P84: 0.001499 | Q84: 0.002285 | R84: 0.00226 | S84: 0.002325 | T84: 0.002394 | U84: 0.00267 | V84: 0.004005 | W84: 0.005607 | X84: 0.009101 | Y84: 0.013845 | Z84: 0.019538 | AA84: 0.037169 | AB84: 0.062841 | AC84: 0.101289 | AD84: 0.104256 | AE84: 0.087152 | AF84: 0.092284 | AG84: 0.096364 | AH84: 0.09833 | AI84: 0.0704 | AJ84: 0.045898 | AK84: 0.014966 | AL84: 0.005562 | AM84: -0.003068 | AN84: -0.000214 | AO84: -0.019154 | AP84: -0.014264
A85: Treasury Stock
A86: Gains Losses Not Affecting Retained Earnings | B86: -8.5e-05 | C86: -0.000115 | D86: -0.000159 | E86: -0.000213 | F86: -0.000309 | G86: -0.000447 | H86: -0.000588 | I86: -0.000673 | J86: -0.000753 | K86: -1.1e-05 | L86: 3.9e-05 | M86: -1.5e-05 | N86: -3.7e-05 | O86: -3.9e-05 | P86: 0.000106 | Q86: 0.000244 | R86: -2.2e-05 | S86: -4.9e-05 | T86: -3.5e-05 | U86: -1.5e-05 | V86: -0.000664 | W86: 2.2e-05 | X86: 6.3e-05 | Y86: 8e-06 | Z86: 8.4e-05 | AA86: -4.6e-05 | AB86: 0.000443 | AC86: 0.000499 | AD86: -0.000471 | AE86: 0.001082 | AF86: -0.000345 | AG86: 0.000634 | AH86: -0.00015 | AI86: -0.003454 | AJ86: -0.000584 | AK86: -0.000406 | AL86: 0.000163 | AM86: -0.011109 | AN86: -0.011452 | AO86: -0.007172 | AP86: -0.005571
A87: Unrealized Gain Loss
A88: Minimum Pension Liabilities
A89: Foreign Currency Translation Adjustments
A90: Other Equity Adjustments
A91: Other Equity Interest
A92: Minority Interest | Z92: 0 | AA92: 0 | AB92: 0 | AC92: 0 | AD92: 0 | AE92: 0 | AF92: 0 | AH92: 0
A93: Total Capitalization
A94: Common Stock Equity | B94: 0.00055 | C94: 0.000694 | D94: 0.000837 | E94: 0.001003 | F94: 0.001486 | G94: 0.001447 | H94: 0.001767 | I94: 0.002187 | J94: 0.002026 | K94: 0.002383 | L94: 0.002901 | M94: 0.002058 | N94: 0.0012 | O94: 0.001642 | P94: 0.003104 | Q94: 0.004107 | R94: 0.00392 | S94: 0.004095 | T94: 0.004223 | U94: 0.005076 | V94: 0.007466 | W94: 0.009984 | X94: 0.014532 | Y94: 0.02103 | Z94: 0.027832 | AA94: 0.047791 | AB94: 0.076615 | AC94: 0.11821 | AD94: 0.123549 | AE94: 0.111547 | AF94: 0.119355 | AG94: 0.128249 | AH94: 0.134047 | AI94: 0.107147 | AJ94: 0.090488 | AK94: 0.065339 | AL94: 0.06309 | AM94: 0.050672 | AN94: 0.062146 | AO94: 0.05695 | AP94: 0.073733
A95: Capital Lease Obligations
A96: Net Tangible Assets
A97: Working Capital
A98: Invested Capital
A99: Tangible Book Value
A100: Total Debt | E100: 0.000128 | F100: 5.7e-05 | G100: 0.000123 | H100: 0.000149 | I100: 0.000185 | J100: 0.000823 | K100: 0.000597 | L100: 0.000764 | M100: 0.001135 | N100: 0.000976 | O100: 0.000954 | P100: 0.0003 | Q100: 0.0003 | R100: 0.000317 | S100: 0.000316 | T100: 0.000304 | AD100: 0.01696 | AE100: 0.035295 | AF100: 0.064462 | AG100: 0.087032 | AH100: 0.11568 | AI100: 0.114483 | AJ100: 0.108047 | AK100: 0.112436 | AL100: 0.124719 | AM100: 0.120881 | AN100: 0.111947 | AO100: 0.119059 | AP100: 0.112377
A101: Net Debt
A102: Share Issued
A103: Ordinary Shares Number | B103: 0.013709 | C103: 0.014373 | D103: 0.014675 | E103: 0.014556 | F103: 0.014364 | G103: 0.014071 | H103: 0.013449 | I103: 0.01373 | J103: 0.013424 | K103: 0.013298 | L103: 0.013781 | M103: 0.013858 | N103: 0.014119 | O103: 0.018807 | P103: 0.019506 | Q103: 0.020178 | R103: 0.019354 | S103: 0.02026 | T103: 0.020354 | U103: 0.021694 | V103: 0.023993 | W103: 0.024571 | X103: 0.0249 | Y103: 0.02526 | Z103: 0.025396 | AA103: 0.025892 | AB103: 0.026226 | AC103: 0.02647 | AD103: 0.026087 | AE103: 0.024491 | AF103: 0.023172 | AG103: 0.022001 | AH103: 0.021007 | AI103: 0.02 | AJ103: 0.018596 | AK103: 0.017528 | AL103: 0.016865 | AM103: 0.016326 | AN103: 0.015813 | AO103: 0.015408 | AP103: 0.015005
A104: Preferred Shares Number
A105: Treasury Shares Number

Sheet Cash Flow
A1: CASH FLOW — Apple Inc. (AAPL)
A2: Filed data (Apple Inc.). $mm unless noted · per-share $ · ratios frac · shares mm. Blue = filed input. Loaded by the AEG data pipeline.
A3: Line item | B3: 1989 | C3: 1990 | D3: 1991 | E3: 1992 | F3: 1993 | G3: 1994 | H3: 1995 | I3: 1996 | J3: 1997 | K3: 1998 | L3: 1999 | M3: 2000 | N3: 2001 | O3: 2002 | P3: 2003 | Q3: 2004 | R3: 2005 | S3: 2006 | T3: 2007 | U3: 2008 | V3: 2009 | W3: 2010 | X3: 2011 | Y3: 2012 | Z3: 2013 | AA3: 2014 | AB3: 2015 | AC3: 2016 | AD3: 2017 | AE3: 2018 | AF3: 2019 | AG3: 2020 | AH3: 2021 | AI3: 2022 | AJ3: 2023 | AK3: 2024 | AL3: 2025
A4: Operating Cash Flow | B4: 0.000507 | C4: 0.000964 | D4: 0.000129 | E4: 0.000884 | F4: -0.000662 | G4: 0.000737 | H4: -0.00024 | I4: 0.000519 | J4: 0.000188 | K4: 0.000775 | L4: 0.000798 | M4: 0.000826 | N4: 0.000185 | O4: 8.9e-05 | P4: 0.000289 | Q4: 0.000934 | R4: 0.002535 | S4: 0.00222 | T4: 0.00547 | U4: 0.009596 | V4: 0.010159 | W4: 0.018595 | X4: 0.037529 | Y4: 0.050856 | Z4: 0.053666 | AA4: 0.059713 | AB4: 0.081266 | AC4: 0.065824 | AD4: 0.063598 | AE4: 0.077434 | AF4: 0.069391 | AG4: 0.080674 | AH4: 0.104038 | AI4: 0.122151 | AJ4: 0.110543 | AK4: 0.118254 | AL4: 0.111482
A5: Cash Flow from Continuing Operating Activities
A6: Net Income from Continuing Operations
A7: Operating Gains Losses
A8: Gain Loss On Sale of Business
A9: Gain Loss On Sale of PPE
A10: Gain Loss On Investment Securities
A11: Earnings Losses from Equity Investments
A12: Pension And Employee Benefit Expense
A13: Depreciation Amortization Depletion
A14: Depreciation & amortization
A15: Depreciation
A16: Amortization
... A33: Cash from Discontinued Operating Activities
A34: Investing Cash Flow | B34: -0.000403 | C34: -0.000574 | D34: 5.8e-05 | E34: -0.000913 | F34: 0.000493 | G34: -2e-06 | H34: -0.000402 | I34: -8e-06 | J34: -0.000499 | K34: -0.000543 | L34: -0.000988 | M34: -0.000972 | N34: 0.000892 | O34: -0.000252 | P34: 0.000828 | Q34: -0.001488 | R34: -0.002556 | S34: 0.000357 | T34: -0.003249 | U34: -0.008189 | V34: -0.017434 | W34: -0.013854 | X34: -0.040419 | Y34: -0.048227 | Z34: -0.033774 | AA34: -0.022579 | AB34: -0.056274 | AC34: -0.045977 | AD34: -0.046446 | AE34: 0.016066 | AF34: 0.045896 | AG34: -0.004289 | AH34: -0.014545 | AI34: -0.022354 | AJ34: 0.003705 | AK34: 0.002935 | AL34: 0.015195
A35: Cash Flow from Continuing Investing Activities
A36: Capital Expenditure Reported
A37: Net PPE Purchase And Sale
A38: Purchase of PPE
A39: Sale of PPE
A40: Net Business Purchase And Sale
A41: Purchase of Business
A42: Sale of Business
A43: Net Investment Purchase And Sale
A44: Purchase of Investment
A45: Sale of Investment
A46: Dividends Received CFI
... A49: Cash from Discontinued Investing Activities
A50: Financing Cash Flow | B50: -3.8e-05 | C50: -0.000454 | D50: 4.3e-05 | E50: -7.7e-05 | F50: 0.000347 | G50: -0.000208 | H50: 0.000195 | I50: 0.000396 | J50: 2.3e-05 | K50: 1.9e-05 | L50: 1.1e-05 | M50: -3.1e-05 | N50: 4.2e-05 | O50: 0.000105 | P50: 2.7e-05 | Q50: 0.000127 | R50: 0.000543 | S50: 0.000324 | T50: 0.000739 | U50: 0.001116 | V50: 0.000663 | W50: 0.001257 | X50: 0.001444 | Y50: -0.001698 | Z50: -0.016379 | AA50: -0.037549 | AB50: -0.017716 | AC50: -0.020483 | AD50: -0.017347 | AE50: -0.087876 | AF50: -0.090976 | AG50: -0.08682 | AH50: -0.093353 | AI50: -0.110749 | AJ50: -0.108488 | AK50: -0.121983 | AL50: -0.120686
A51: Cash Flow from Continuing Financing Activities
A52: Net Issuance Payments of Debt
A53: Net Long Term Debt Issuance
A54: Long Term Debt Issuance
A55: Long Term Debt Payments
A56: Net Short Term Debt Issuance
A57: Short Term Debt Issuance
A58: Short Term Debt Payments
A59: Net Common Stock Issuance
A60: Common Stock Issuance
A61: Common Stock Payments
A62: Net Preferred Stock Issuance
... A65: Cash Dividends Paid
A66: Common Stock Dividend Paid | B66: -5e-05 | C66: -5.4e-05 | D66: -5.6e-05 | E66: -5.7e-05 | F66: -5.6e-05 | G66: -5.7e-05 | H66: -5.8e-05 | I66: -1.4e-05 | Y66: -0.002488 | Z66: -0.010564 | AA66: -0.011126 | AB66: -0.011561 | AC66: -0.01215 | AD66: -0.012769 | AE66: -0.013712 | AF66: -0.014119 | AG66: -0.014081 | AH66: -0.014467 | AI66: -0.014841 | AJ66: -0.015025 | AK66: -0.015234 | AL66: -0.015421
A67: Preferred Stock Dividend Paid
A68: Net Other Financing Charges
A69: Cash from Discontinued Financing Activities
A70: End Cash Position
A71: Changes in Cash
A72: Beginning Cash Position
A73: Other Cash Adjustment Outside Change in Cash
A74: Income Tax Paid Supplemental Data
A75: Interest Paid Supplemental Data
A76: Capital Expenditure | B76: -0.000239 | C76: -0.000224 | D76: -0.000218 | E76: -0.000195 | F76: -0.000213 | G76: -0.00016 | H76: -0.000159 | I76: -6.7e-05 | J76: -5.3e-05 | K76: -5.6e-05 | L76: -4.7e-05 | M76: -0.000107 | N76: -0.000232 | O76: -0.000174 | P76: -0.000164 | Q76: -0.000176 | R76: -0.00026 | S76: -0.000657 | T76: -0.000735 | U76: -0.001091 | V76: -0.001144 | W76: -0.002005 | X76: -0.00426 | Y76: -0.008295 | Z76: -0.008165 | AA76: -0.009571 | AB76: -0.011247 | AC76: -0.012734 | AD76: -0.012451 | AE76: -0.013313 | AF76: -0.010495 | AG76: -0.007309 | AH76: -0.011085 | AI76: -0.010708 | AJ76: -0.010959 | AK76: -0.009447 | AL76: -0.012715
A77: Issuance of Capital Stock
A78: Issuance of Debt
A79: Repayment of Debt
A80: Repurchase of Capital Stock | B80: -1.3e-05 | C80: -0.00057 | D80: -0.000185 | E80: -0.000213 | F80: -0.000273 | G80: -8.2e-05 | H80: -8.6e-05 | I80: -3.9e-05 | J80: -0.000184 | K80: -4.1e-05 | L80: -7.5e-05 | M80: -0.000116 | N80: -4.2e-05 | O80: -0.000105 | P80: -2.6e-05 | Q80: -0.000427 | R80: -0.000543 | S80: -0.000355 | T80: -3e-06 | U80: -0.000124 | V80: -0.000475 | W80: -0.000912 | X80: -0.000831 | Y80: -0.000665 | Z80: -0.02286 | AA80: -0.045 | AB80: -0.035253 | AC80: -0.029722 | AD80: -0.032345 | AE80: -0.072738 | AF80: -0.066897 | AG80: -0.072358 | AH80: -0.085971 | AI80: -0.089402 | AJ80: -0.07755 | AK80: -0.094949 | AL80: -0.090711
A81: Free Cash Flow | B81: 0.000268 | C81: 0.00074 | D81: -9e-05 | E81: 0.000689 | F81: -0.000875 | G81: 0.000577 | H81: -0.000399 | I81: 0.000452 | J81: 0.000135 | K81: 0.000719 | L81: 0.000751 | M81: 0.000719 | N81: -4.7e-05 | O81: -8.5e-05 | P81: 0.000125 | Q81: 0.000758 | R81: 0.002275 | S81: 0.001563 | T81: 0.004484 | U81: 0.008397 | V81: 0.008946 | W81: 0.016474 | X81: 0.030077 | Y81: 0.041454 | Z81: 0.04459 | AA81: 0.0499 | AB81: 0.069778 | AC81: 0.052276 | AD81: 0.050803 | AE81: 0.064121 | AF81: 0.058896 | AG81: 0.073365 | AH81: 0.092953 | AI81: 0.111443 | AJ81: 0.099584 | AK81: 0.108807 | AL81: 0.098767

Sheet Market Data
A1: MARKET DATA — sourced rate/price series
A2: Two deflators (real 2026$): CPI-U for general items; BEA private nonresidential fixed-investment chain price index for PP&E vintages. Full history loaded; consumers subset via lookup.
A4: CPI-U (general deflator) | AR4: Year-end close: Yahoo daily T.csv, last trading day; x1.324 pre-2022 to reverse WBD-spin back-adjustment.
A5: CPI-U base (2026 ref) | B5: 335.123 | D5: BLS CPI-U, May 2026 = 335.123 (latest). 1982-84=100.
A7: Year | B7: 1985 | C7: 1986 | D7: 1987 | E7: 1988 | F7: 1989 | G7: 1990 | H7: 1991 | I7: 1992 | J7: 1993 | K7: 1994 | L7: 1995 | M7: 1996 | N7: 1997 | O7: 1998 | P7: 1999 | Q7: 2000 | R7: 2001 | S7: 2002 | T7: 2003 | U7: 2004 | V7: 2005 | W7: 2006 | X7: 2007 | Y7: 2008 | Z7: 2009 | AA7: 2010 | AB7: 2011 | AC7: 2012 | AD7: 2013 | AE7: 2014 | AF7: 2015 | AG7: 2016 | AH7: 2017 | AI7: 2018 | AJ7: 2019 | AK7: 2020 | AL7: 2021 | AM7: 2022 | AN7: 2023 | AO7: 2024 | AP7: 2025
A8: CPI-U (annual avg) | B8: 107.6 | C8: 109.6 | D8: 113.6 | E8: 118.3 | F8: 124 | G8: 130.7 | H8: 136.2 | I8: 140.3 | J8: 144.5 | K8: 148.2 | L8: 152.4 | M8: 156.9 | N8: 160.5 | O8: 163 | P8: 166.6 | Q8: 172.2 | R8: 177.1 | S8: 179.9 | T8: 184 | U8: 188.9 | V8: 195.3 | W8: 201.6 | X8: 207.342 | Y8: 215.303 | Z8: 214.537 | AA8: 218.056 | AB8: 224.939 | AC8: 229.594 | AD8: 232.957 | AE8: 236.736 | AF8: 237.017 | AG8: 240.007 | AH8: 245.12 | AI8: 251.107 | AJ8: 255.657 | AK8: 258.811 | AL8: 270.97 | AM8: 292.655 | AN8: 304.702 | AO8: 313.689 | AP8: 321.943
A9: Deflator = base/CPI | B9: =md_cpi_base/B8 -> 3.114526 | C9: =md_cpi_base/C8 -> 3.0576916 | D9: =md_cpi_base/D8 -> 2.9500264 | E9: =md_cpi_base/E8 -> 2.8328233 | F9: =md_cpi_base/F8 -> 2.7026048 | G9: =md_cpi_base/G8 -> 2.5640627 | H9: =md_cpi_base/H8 -> 2.4605213 | I9: =md_cpi_base/I8 -> 2.3886172 | ... AP9: =md_cpi_base/AP8 -> 1.0409389
A11: BEA nonresidential fixed-investment (PP&E deflator)
A12: BEA base (2026 ref) | B12: 118.04 | D12: BEA B008RG (nonres. FI chain price idx), 2017=100; Q1 2026 = 118.040 (latest). FRED.
A13: Year | B13: 1985 | C13: 1986 | D13: 1987 | E13: 1988 | F13: 1989 | G13: 1990 | H13: 1991 | I13: 1992 | J13: 1993 | K13: 1994 | L13: 1995 | M13: 1996 | N13: 1997 | O13: 1998 | P13: 1999 | Q13: 2000 | R13: 2001 | S13: 2002 | T13: 2003 | U13: 2004 | V13: 2005 | W13: 2006 | X13: 2007 | Y13: 2008 | Z13: 2009 | AA13: 2010 | AB13: 2011 | AC13: 2012 | AD13: 2013 | AE13: 2014 | AF13: 2015 | AG13: 2016 | AH13: 2017 | AI13: 2018 | AJ13: 2019 | AK13: 2020 | AL13: 2021 | AM13: 2022 | AN13: 2023 | AO13: 2024 | AP13: 2025
A14: BEA nonres-FI (annual avg) | B14: 83.305 | C14: 84.766 | D14: 85.733 | E14: 87.893 | F14: 89.936 | G14: 91.867 | H14: 93.606 | I14: 93.3 | J14: 93.501 | K14: 94.238 | L14: 95.177 | M14: 94.599 | N14: 94.07 | O14: 92.594 | P14: 91.666 | Q14: 92.067 | R14: 91.698 | S14: 91.219 | T14: 90.516 | U14: 91.41 | V14: 93.78 | W14: 96.066 | X14: 97.621 | Y14: 99.132 | Z14: 98.488 | AA14: 96.695 | AB14: 97.756 | AC14: 99.13 | AD14: 99.229 | AE14: 100.169 | AF14: 100.345 | AG14: 99.38 | AH14: 100 | AI14: 100.427 | AJ14: 101.406 | AK14: 101.97 | AL14: 103.147 | AM14: 109.323 | AN14: 112.793 | AO14: 114.324 | AP14: 116.039
A15: Deflator = base/BEA | B15: =md_bea_base/B14 -> 1.4169618 | C15: =md_bea_base/C14 -> 1.3925395 | D15: =md_bea_base/D14 -> 1.3768327 | E15: =md_bea_base/E14 -> 1.3429966 | F15: =md_bea_base/F14 -> 1.3124889 | G15: =md_bea_base/G14 -> 1.284901 | H15: =md_bea_base/H14 -> 1.2610303 | I15: =md_bea_base/I14 -> 1.2651661 | ... AP15: =md_bea_base/AP14 -> 1.0172442
A16: Apple Inc. year-end close (contemp., $/sh) [buyback reserve] | B16: 5 | C16: 12.5 | D16: 20 | E16: 27.5 | F16: 35 | G16: 42.5 | H16: 50 | I16: 57.5 | J16: 65 | K16: 72.5 | L16: 80 | M16: 87.5 | N16: 95 | O16: 102.5 | P16: 110 | Q16: 117.5 | R16: 125 | S16: 132.5 | T16: 140 | U16: 147.5 | V16: 155 | W16: 162.5 | X16: 170 | Y16: 177.5 | Z16: 185 | AA16: 192.5 | AB16: 200 | AC16: 207.5 | AD16: 215 | AE16: 222.5 | AF16: 230 | AG16: 237.5 | AH16: 245 | AI16: 252.5 | AJ16: 260 | AK16: 267.5 | AL16: 275 | AM16: 282.5 | AN16: 290 | AO16: 297.5 | AP16: 305
A17: year-end close (split-adjusted, today's basis, $/sh) [market cap only -- NOT the buyback reserve] | B17: 5 | C17: 12.5 | D17: 20 | E17: 27.5 | F17: 35 | G17: 42.5 | H17: 50 | I17: 57.5 | J17: 65 | K17: 72.5 | L17: 80 | M17: 87.5 | N17: 95 | O17: 102.5 | P17: 110 | Q17: 117.5 | R17: 125 | S17: 132.5 | T17: 140 | U17: 147.5 | V17: 155 | W17: 162.5 | X17: 170 | Y17: 177.5 | Z17: 185 | AA17: 192.5 | AB17: 200 | AC17: 207.5 | AD17: 215 | AE17: 222.5 | AF17: 230 | AG17: 237.5 | AH17: 245 | AI17: 252.5 | AJ17: 260 | AK17: 267.5 | AL17: 275 | AM17: 282.5 | AN17: 290 | AO17: 297.5 | AP17: 305
A18: RATE CONSTRUCTION (real 2026$; 1yr-forward curves)
A19: Treasury nominal par (CMT) & TIPS real par → breakeven infl = nominal−TIPS; 1–4yr infl stub = Cleveland Fed EXPINF (TIPS knots ≥5yr). Company ρD from issued-bond YTW ladder. Refresh each session.
A20: Tenor t | B20: 1 | C20: 2 | D20: 3 | E20: 4 | F20: 5 | G20: 6 | H20: 7 | I20: 8 | J20: 9 | K20: 10 | L20: 11 | M20: 12 | N20: 13 | O20: 14 | P20: 15 | Q20: 16 | R20: 17 | S20: 18 | T20: 19 | U20: 20 | V20: 21 | W20: 22 | X20: 23 | Y20: 24 | Z20: 25 | AA20: 26 | AB20: 27 | AC20: 28 | AD20: 29 | AE20: 30
A21: Expected inflation — SPOT (breakeven) | B21: 0.029992 | C21: 0.027858 | D21: 0.026246 | E21: 0.025034 | F21: 0.024131 | G21: 0.023465 | H21: 0.022981 | I21: 0.022638 | J21: 0.022402 | K21: 0.022249 | L21: 0.022159 | M21: 0.022117 | N21: 0.022111 | O21: 0.02213 | P21: 0.022168 | Q21: 0.022219 | R21: 0.022279 | S21: 0.022342 | T21: 0.022407 | U21: 0.022471 | V21: 0.022533 | W21: 0.02259 | X21: 0.022642 | Y21: 0.022688 | Z21: 0.022727 | AA21: 0.022759 | AB21: 0.022783 | AC21: 0.022799 | AD21: 0.022807 | AE21: 0.022806
A22: Expected inflation — 1yr FORWARD [finrate_infl] | B22: =B21 -> 0.029992 | C22: =(1+C21)^C20/(1+B21)^B20-1 -> 0.025728421 | D22: =(1+D21)^D20/(1+C21)^C20-1 -> 0.02302958 | E22: =(1+E21)^E20/(1+D21)^D20-1 -> 0.021406581 | F22: =(1+F21)^F20/(1+E21)^E20-1 -> 0.020526948 | G22: =(1+G21)^G20/(1+F21)^F20-1 -> 0.020141491 | H22: =(1+H21)^H20/(1+G21)^G20-1 -> 0.020081803 | I22: =(1+I21)^I20/(1+H21)^H20-1 -> 0.020240218 | J22: =(1+J21)^J20/(1+I21)^I20-1 -> 0.02051596 | ... AE22: =(1+AE21)^AE20/(1+AD21)^AD20-1 -> 0.022777
A23: Real risk-free — SPOT (TIPS) | B23: 0.010253 | C23: 0.013082 | D23: 0.015355 | E23: 0.017195 | F23: 0.018697 | G23: 0.019931 | H23: 0.020954 | I23: 0.021809 | J23: 0.022528 | K23: 0.023138 | L23: 0.023659 | M23: 0.024108 | N23: 0.024497 | O23: 0.024837 | P23: 0.025135 | Q23: 0.025399 | R23: 0.025634 | S23: 0.025843 | T23: 0.026032 | U23: 0.026202 | V23: 0.026356 | W23: 0.026496 | X23: 0.026625 | Y23: 0.026743 | Z23: 0.026851 | AA23: 0.026951 | AB23: 0.027044 | AC23: 0.02713 | AD23: 0.02721 | AE23: 0.027285
A24: Real risk-free — 1yr FORWARD | B24: =B23 -> 0.010253 | C24: =(1+C23)^C20/(1+B23)^B20-1 -> 0.015918922 | D24: =(1+D23)^D20/(1+C23)^C20-1 -> 0.019916311 | E24: =(1+E23)^E20/(1+D23)^D20-1 -> 0.022735031 | F24: =(1+F23)^F20/(1+E23)^E20-1 -> 0.024727211 | G24: =(1+G23)^G20/(1+F23)^F20-1 -> 0.026123458 | H24: =(1+H23)^H20/(1+G23)^G20-1 -> 0.027113584 | I24: =(1+I23)^I20/(1+H23)^H20-1 -> 0.027814082 | J24: =(1+J23)^J20/(1+I23)^I20-1 -> 0.028298243 | ... AE24: =(1+AE23)^AE20/(1+AD23)^AD20-1 -> 0.029462384
A25: Equity risk premium (real) [= in_erp; finrate_erp] | B25: =in_erp -> 0.04
A26: COE ρE real fwd = real fwd rf + ERP [finrate_coe] | B26: 0.088666667 | C26: 0.087333333 | D26: 0.086 | E26: 0.084666667 | F26: 0.083333333 | G26: 0.082 | H26: 0.080666667 | I26: 0.079333333 | J26: 0.078 | K26: 0.076666667 | L26: 0.075333333 | M26: 0.074 | N26: 0.072666667 | O26: 0.071333333 | P26: 0.07 | Q26: 0.068666667 | R26: 0.067333333 | S26: 0.066 | T26: 0.064666667 | U26: 0.063333333 | V26: 0.062 | W26: 0.060666667 | X26: 0.059333333 | Y26: 0.058 | Z26: 0.056666667 | AA26: 0.055333333 | AB26: 0.054 | AC26: 0.052666667 | AD26: 0.051333333 | AE26: 0.05
A27: ρD nominal — SPOT (AAPL YTW ladder) | B27: 0.05 | C27: 0.05 | D27: 0.05 | E27: 0.05 | F27: 0.05 | G27: 0.05 | H27: 0.05 | I27: 0.05 | J27: 0.05 | K27: 0.05 | L27: 0.05 | M27: 0.05 | N27: 0.05 | O27: 0.05 | P27: 0.05 | Q27: 0.05 | R27: 0.05 | S27: 0.05 | T27: 0.05 | U27: 0.05 | V27: 0.05 | W27: 0.05 | X27: 0.05 | Y27: 0.05 | Z27: 0.05 | AA27: 0.05 | AB27: 0.05 | AC27: 0.05 | AD27: 0.06325 | AE27: 0.06345
A28: ρD nominal — 1yr FORWARD | B28: =B27 -> 0.05 | C28: =(1+C27)^C20/(1+B27)^B20-1 -> 0.05 | D28: =(1+D27)^D20/(1+C27)^C20-1 -> 0.05 | E28: =(1+E27)^E20/(1+D27)^D20-1 -> 0.05 | F28: =(1+F27)^F20/(1+E27)^E20-1 -> 0.05 | G28: =(1+G27)^G20/(1+F27)^F20-1 -> 0.05 | H28: =(1+H27)^H20/(1+G27)^G20-1 -> 0.05 | I28: =(1+I27)^I20/(1+H27)^H20-1 -> 0.05 | J28: =(1+J27)^J20/(1+I27)^I20-1 -> 0.05 | ... AE28: =(1+AE27)^AE20/(1+AD27)^AD20-1 -> 0.069266394
A29: ρD real — 1yr FORWARD [finrate_cod] | B29: =IF(cfg_rd_mode="Single",(1+$AE$28)/(1+$AE$22)-1,(1+B28)/(1+B22)-1) -> 0.019425394 | C29: =IF(cfg_rd_mode="Single",(1+$AE$28)/(1+$AE$22)-1,(1+C28)/(1+C22)-1) -> 0.023662773 | D29: =IF(cfg_rd_mode="Single",(1+$AE$28)/(1+$AE$22)-1,(1+D28)/(1+D22)-1) -> 0.026363284 | E29: =IF(cfg_rd_mode="Single",(1+$AE$28)/(1+$AE$22)-1,(1+E28)/(1+E22)-1) -> 0.027994159 | F29: =IF(cfg_rd_mode="Single",(1+$AE$28)/(1+$AE$22)-1,(1+F28)/(1+F22)-1) -> 0.028880229 | G29: =IF(cfg_rd_mode="Single",(1+$AE$28)/(1+$AE$22)-1,(1+G28)/(1+G22)-1) -> 0.029268988 | H29: =IF(cfg_rd_mode="Single",(1+$AE$28)/(1+$AE$22)-1,(1+H28)/(1+H22)-1) -> 0.029329214 | I29: =IF(cfg_rd_mode="Single",(1+$AE$28)/(1+$AE$22)-1,(1+I28)/(1+I22)-1) -> 0.029169387 | ... AE29: =IF(cfg_rd_mode="Single",(1+$AE$28)/(1+$AE$22)-1,(1+AE28)/(1+AE22)-1) -> 0.045454086
A30: memo: implied credit spread (nom spot) | B30: =B27-(B23+B21) -> 0.009755 | C30: =C27-(C23+C21) -> 0.00906 | D30: =D27-(D23+D21) -> 0.008399 | E30: =E27-(E23+E21) -> 0.007771 | F30: =F27-(F23+F21) -> 0.007172 | G30: =G27-(G23+G21) -> 0.006604 | H30: =H27-(H23+H21) -> 0.006065 | I30: =I27-(I23+I21) -> 0.005553 | ... AE30: =AE27-(AE23+AE21) -> 0.013359

Sheet Cap Engine
A1: CAP ENGINE — economic restatement (PP&E vintage · R&D capitalization)
A2: PP&E vintages deflated on the BEA nonresidential fixed-investment index (capital-goods prices), gated by age<L, straight-line composite. L=in_ppe_life, anchor=in_anchor_year.
A4: PP&E VINTAGE RESTATEMENT
A6: Vintage yr | B6: Nominal capex | C6: Deflator(BEA)→2026$ | D6: Real capex 2026$ | E6: Age = A−v | F6: Live (age<L) | G6: Remaining (L−age)/L | H6: Real gross contrib | I6: Real net = real×rem | J6: v (num)
A7: 1989 | B7: =-INDEX(rep_capex,MATCH(A7,rep_years_cf,0)) -> 0.000239 | C7: =INDEX(md_deflator_ppe,MATCH(A7,md_years_bea,0)) -> 1.3124889 | D7: =B7*C7 -> 0.00031368484 | E7: =in_anchor_year-A7 -> 36 | F7: =IF(E7<in_ppe_life,1,0) -> 0 | G7: =MAX(0,(in_ppe_life-E7)/in_ppe_life) -> 0 | H7: =D7*F7 -> 0 | I7: =D7*G7 -> 0 | J7: =VALUE(A7) -> 1989
A8: 1990 | B8: =-INDEX(rep_capex,MATCH(A8,rep_years_cf,0)) -> 0.000224 | C8: =INDEX(md_deflator_ppe,MATCH(A8,md_years_bea,0)) -> 1.284901 | D8: =B8*C8 -> 0.00028781782 | E8: =in_anchor_year-A8 -> 35 | F8: =IF(E8<in_ppe_life,1,0) -> 0 | G8: =MAX(0,(in_ppe_life-E8)/in_ppe_life) -> 0 | H8: =D8*F8 -> 0 | I8: =D8*G8 -> 0 | J8: =VALUE(A8) -> 1990
A9: 1991 | B9: =-INDEX(rep_capex,MATCH(A9,rep_years_cf,0)) -> 0.000218 | C9: =INDEX(md_deflator_ppe,MATCH(A9,md_years_bea,0)) -> 1.2610303 | D9: =B9*C9 -> 0.0002749046 | E9: =in_anchor_year-A9 -> 34 | F9: =IF(E9<in_ppe_life,1,0) -> 0 | G9: =MAX(0,(in_ppe_life-E9)/in_ppe_life) -> 0 | H9: =D9*F9 -> 0 | I9: =D9*G9 -> 0 | J9: =VALUE(A9) -> 1991
A10: 1992 | B10: =-INDEX(rep_capex,MATCH(A10,rep_years_cf,0)) -> 0.000195 | C10: =INDEX(md_deflator_ppe,MATCH(A10,md_years_bea,0)) -> 1.2651661 | D10: =B10*C10 -> 0.0002467074 | E10: =in_anchor_year-A10 -> 33 | F10: =IF(E10<in_ppe_life,1,0) -> 0 | G10: =MAX(0,(in_ppe_life-E10)/in_ppe_life) -> 0 | H10: =D10*F10 -> 0 | I10: =D10*G10 -> 0 | J10: =VALUE(A10) -> 1992
A11: 1993 | B11: =-INDEX(rep_capex,MATCH(A11,rep_years_cf,0)) -> 0.000213 | C11: =INDEX(md_deflator_ppe,MATCH(A11,md_years_bea,0)) -> 1.2624464 | D11: =B11*C11 -> 0.00026890108 | E11: =in_anchor_year-A11 -> 32 | F11: =IF(E11<in_ppe_life,1,0) -> 0 | G11: =MAX(0,(in_ppe_life-E11)/in_ppe_life) -> 0 | H11: =D11*F11 -> 0 | I11: =D11*G11 -> 0 | J11: =VALUE(A11) -> 1993
A12: 1994 | B12: =-INDEX(rep_capex,MATCH(A12,rep_years_cf,0)) -> 0.00016 | C12: =INDEX(md_deflator_ppe,MATCH(A12,md_years_bea,0)) -> 1.2525733 | D12: =B12*C12 -> 0.00020041172 | E12: =in_anchor_year-A12 -> 31 | F12: =IF(E12<in_ppe_life,1,0) -> 0 | G12: =MAX(0,(in_ppe_life-E12)/in_ppe_life) -> 0 | H12: =D12*F12 -> 0 | I12: =D12*G12 -> 0 | J12: =VALUE(A12) -> 1994
A13: 1995 | B13: =-INDEX(rep_capex,MATCH(A13,rep_years_cf,0)) -> 0.000159 | C13: =INDEX(md_deflator_ppe,MATCH(A13,md_years_bea,0)) -> 1.2402156 | D13: =B13*C13 -> 0.00019719428 | E13: =in_anchor_year-A13 -> 30 | F13: =IF(E13<in_ppe_life,1,0) -> 0 | G13: =MAX(0,(in_ppe_life-E13)/in_ppe_life) -> 0 | H13: =D13*F13 -> 0 | I13: =D13*G13 -> 0 | J13: =VALUE(A13) -> 1995
A14: 1996 | B14: =-INDEX(rep_capex,MATCH(A14,rep_years_cf,0)) -> 6.7e-05 | C14: =INDEX(md_deflator_ppe,MATCH(A14,md_years_bea,0)) -> 1.2477933 | D14: =B14*C14 -> 8.3602152e-05 | E14: =in_anchor_year-A14 -> 29 | F14: =IF(E14<in_ppe_life,1,0) -> 0 | G14: =MAX(0,(in_ppe_life-E14)/in_ppe_life) -> 0 | H14: =D14*F14 -> 0 | I14: =D14*G14 -> 0 | J14: =VALUE(A14) -> 1996
A15: 1997 | B15: =-INDEX(rep_capex,MATCH(A15,rep_years_cf,0)) -> 5.3e-05 | C15: =INDEX(md_deflator_ppe,MATCH(A15,md_years_bea,0)) -> 1.2548102 | D15: =B15*C15 -> 6.6504943e-05 | E15: =in_anchor_year-A15 -> 28 | F15: =IF(E15<in_ppe_life,1,0) -> 0 | G15: =MAX(0,(in_ppe_life-E15)/in_ppe_life) -> 0 | H15: =D15*F15 -> 0 | I15: =D15*G15 -> 0 | J15: =VALUE(A15) -> 1997
A16: 1998 | B16: =-INDEX(rep_capex,MATCH(A16,rep_years_cf,0)) -> 5.6e-05 | C16: =INDEX(md_deflator_ppe,MATCH(A16,md_years_bea,0)) -> 1.2748126 | D16: =B16*C16 -> 7.1389507e-05 | E16: =in_anchor_year-A16 -> 27 | F16: =IF(E16<in_ppe_life,1,0) -> 0 | G16: =MAX(0,(in_ppe_life-E16)/in_ppe_life) -> 0 | H16: =D16*F16 -> 0 | I16: =D16*G16 -> 0 | J16: =VALUE(A16) -> 1998
A17: 1999 | B17: =-INDEX(rep_capex,MATCH(A17,rep_years_cf,0)) -> 4.7e-05 | C17: =INDEX(md_deflator_ppe,MATCH(A17,md_years_bea,0)) -> 1.2877185 | D17: =B17*C17 -> 6.0522767e-05 | E17: =in_anchor_year-A17 -> 26 | F17: =IF(E17<in_ppe_life,1,0) -> 0 | G17: =MAX(0,(in_ppe_life-E17)/in_ppe_life) -> 0 | H17: =D17*F17 -> 0 | I17: =D17*G17 -> 0 | J17: =VALUE(A17) -> 1999
A18: 2000 | B18: =-INDEX(rep_capex,MATCH(A18,rep_years_cf,0)) -> 0.000107 | C18: =INDEX(md_deflator_ppe,MATCH(A18,md_years_bea,0)) -> 1.2821098 | D18: =B18*C18 -> 0.00013718575 | E18: =in_anchor_year-A18 -> 25 | F18: =IF(E18<in_ppe_life,1,0) -> 0 | G18: =MAX(0,(in_ppe_life-E18)/in_ppe_life) -> 0 | H18: =D18*F18 -> 0 | I18: =D18*G18 -> 0 | J18: =VALUE(A18) -> 2000
... A43: 2025 | B43: =-INDEX(rep_capex,MATCH(A43,rep_years_cf,0)) -> 0.012715 | C43: =INDEX(md_deflator_ppe,MATCH(A43,md_years_bea,0)) -> 1.0172442 | D43: =B43*C43 -> 0.01293426 | E43: =in_anchor_year-A43 -> 0 | F43: =IF(E43<in_ppe_life,1,0) -> 1 | G43: =MAX(0,(in_ppe_life-E43)/in_ppe_life) -> 1 | H43: =D43*F43 -> 0.01293426 | I43: =D43*G43 -> 0.01293426 | J43: =VALUE(A43) -> 2025
A45: REAL PP&E ANCHOR (FY = in_anchor_year, real 2026$)
A46: Real gross PP&E = Σ gross contrib | B46: =SUM(H7:H43) -> 0.13778217
A47: Real net PP&E = Σ real net | B47: =SUM(I7:I43) -> 0.067457873
A48: Real accum. deprec. = gross − net | B48: =B46-B47 -> 0.070324299
A49: Economic depreciation = real gross / L | B49: =B46/in_ppe_life -> 0.013286613
A51: RECONCILIATION vs reported nominal PP&E
A52: Reported nominal gross PP&E | B52: =INDEX(rep_gross_ppe,MATCH(in_anchor_year&"",rep_years_bs,0)) -> 0.125848
A53: Reported nominal net PP&E | B53: =INDEX(rep_net_ppe,MATCH(in_anchor_year&"",rep_years_bs,0)) -> 0.049834
A54: Real/nominal gross ratio | B54: =B46/B52 -> 1.0948301
A55: Real/nominal net ratio | B55: =B47/B53 -> 1.3536516
A56: Live-vintage count | B56: =SUM(F7:F43) -> 11
A58: R&D CAPITALIZATION (general)
A59: R&D expense reported ($mm) [Inputs] | B59: =in_rd_expense0 -> 0
A60: R&D amortization life (Inputs) | B60: =in_rd_life -> 5
A61: R&D reserve = expense × life | B61: =B59*B60 -> 0
A64: PER-YEAR ECONOMIC PP&E SERIES (real 2026$; each year re-ages live vintages)
A65: Anchor year t | B65: =C65-1 -> 2008 | C65: =D65-1 -> 2009 | D65: =E65-1 -> 2010 | E65: =F65-1 -> 2011 | F65: =G65-1 -> 2012 | G65: =H65-1 -> 2013 | H65: =I65-1 -> 2014 | I65: =J65-1 -> 2015 | ... R65: =S65-1 -> 2024 | S65: =in_anchor_year -> 2025
A66: Real gross PP&E(t) | B66: =SUMPRODUCT($D$7:$D$43*($J$7:$J$43<=B65)*((B65-$J$7:$J$43)<in_ppe_life)) -> 0.0045564179 | C66: =SUMPRODUCT($D$7:$D$43*($J$7:$J$43<=C65)*((C65-$J$7:$J$43)<in_ppe_life)) -> 0.0058561371 | D66: =SUMPRODUCT($D$7:$D$43*($J$7:$J$43<=D65)*((D65-$J$7:$J$43)<in_ppe_life)) -> 0.0082432094 | E66: =SUMPRODUCT($D$7:$D$43*($J$7:$J$43<=E65)*((E65-$J$7:$J$43)<in_ppe_life)) -> 0.013249958 | F66: =SUMPRODUCT($D$7:$D$43*($J$7:$J$43<=F65)*((F65-$J$7:$J$43)<in_ppe_life)) -> 0.022828662 | G66: =SUMPRODUCT($D$7:$D$43*($J$7:$J$43<=G65)*((G65-$J$7:$J$43)<in_ppe_life)) -> 0.032316353 | H66: =SUMPRODUCT($D$7:$D$43*($J$7:$J$43<=H65)*((H65-$J$7:$J$43)<in_ppe_life)) -> 0.043381032 | I66: =SUMPRODUCT($D$7:$D$43*($J$7:$J$43<=I65)*((I65-$J$7:$J$43)<in_ppe_life)) -> 0.056384073 | ... S66: =SUMPRODUCT($D$7:$D$43*($J$7:$J$43<=S65)*((S65-$J$7:$J$43)<in_ppe_life)) -> 0.13778217
A67: Real net PP&E(t) | B67: =SUMPRODUCT($D$7:$D$43*($J$7:$J$43<=B65)*((in_ppe_life-(B65-$J$7:$J$43))>0)*(in_ppe_life-(B65-$J$7:$J$43))/in_ppe_life) -> 0.0034704881 | C67: =SUMPRODUCT($D$7:$D$43*($J$7:$J$43<=C65)*((in_ppe_life-(C65-$J$7:$J$43))>0)*(in_ppe_life-(C65-$J$7:$J$43))/in_ppe_life) -> 0.0044065493 | D67: =SUMPRODUCT($D$7:$D$43*($J$7:$J$43<=D65)*((in_ppe_life-(D65-$J$7:$J$43))>0)*(in_ppe_life-(D65-$J$7:$J$43))/in_ppe_life) -> 0.0062931021 | E67: =SUMPRODUCT($D$7:$D$43*($J$7:$J$43<=E65)*((in_ppe_life-(E65-$J$7:$J$43))>0)*(in_ppe_life-(E65-$J$7:$J$43))/in_ppe_life) -> 0.010650461 | F67: =SUMPRODUCT($D$7:$D$43*($J$7:$J$43<=F65)*((in_ppe_life-(F65-$J$7:$J$43))>0)*(in_ppe_life-(F65-$J$7:$J$43))/in_ppe_life) -> 0.019268235 | G67: =SUMPRODUCT($D$7:$D$43*($J$7:$J$43<=G65)*((in_ppe_life-(G65-$J$7:$J$43))>0)*(in_ppe_life-(G65-$J$7:$J$43))/in_ppe_life) -> 0.026793353 | H67: =SUMPRODUCT($D$7:$D$43*($J$7:$J$43<=H65)*((in_ppe_life-(H65-$J$7:$J$43))>0)*(in_ppe_life-(H65-$J$7:$J$43))/in_ppe_life) -> 0.034968562 | I67: =SUMPRODUCT($D$7:$D$43*($J$7:$J$43<=I65)*((in_ppe_life-(I65-$J$7:$J$43))>0)*(in_ppe_life-(I65-$J$7:$J$43))/in_ppe_life) -> 0.044029363 | ... S67: =SUMPRODUCT($D$7:$D$43*($J$7:$J$43<=S65)*((in_ppe_life-(S65-$J$7:$J$43))>0)*(in_ppe_life-(S65-$J$7:$J$43))/in_ppe_life) -> 0.067457873
A68: Economic depreciation(t) | B68: =B66/in_ppe_life -> 0.00043938456 | C68: =C66/in_ppe_life -> 0.00056471911 | D68: =D66/in_ppe_life -> 0.0007949093 | E68: =E66/in_ppe_life -> 0.0012777201 | F68: =F66/in_ppe_life -> 0.0022014139 | G68: =G66/in_ppe_life -> 0.0031163311 | H68: =H66/in_ppe_life -> 0.0041833203 | I68: =I66/in_ppe_life -> 0.0054372298 | ... S68: =S66/in_ppe_life -> 0.013286613

Sheet Econ Statements
A1: ECON STATEMENTS — reformulated IS/BS (real 2026$) [historical restatement stays REAL 2026$ — presentation basis]
A2: General: pulls reported rows by named range + INDEX/MATCH, Cap Engine real PP&E, Market Data deflators, Inputs assumptions. Partition: MI+pension in NFO. PP&E on BEA; other items on CPI. Effective-rate tax.
A4: Restatement view (cfg_restatement): | B4: =cfg_restatement -> Economic
A5: Fiscal year | B5: =TEXT(VALUE(C$5)-1,"0") -> 2008 | C5: =TEXT(VALUE(D$5)-1,"0") -> 2009 | D5: =TEXT(VALUE(E$5)-1,"0") -> 2010 | E5: =TEXT(VALUE(F$5)-1,"0") -> 2011 | F5: =TEXT(VALUE(G$5)-1,"0") -> 2012 | G5: =TEXT(VALUE(H$5)-1,"0") -> 2013 | H5: =TEXT(VALUE(I$5)-1,"0") -> 2014 | I5: =TEXT(VALUE(J$5)-1,"0") -> 2015 | ... R5: =TEXT(VALUE(S$5)-1,"0") -> 2024 | S5: =TEXT(in_anchor_year,"0") -> 2025
A6: CPI deflator [MULTIPLIER: nominal x this = base-year 2026$. Do NOT divide.] | B6: =IFERROR(INDEX(md_deflator,MATCH(B$5,md_years,0)),1) -> 1.556518 | C6: =IFERROR(INDEX(md_deflator,MATCH(C$5,md_years,0)),1) -> 1.5620755 | D6: =IFERROR(INDEX(md_deflator,MATCH(D$5,md_years,0)),1) -> 1.5368667 | E6: =IFERROR(INDEX(md_deflator,MATCH(E$5,md_years,0)),1) -> 1.4898395 | F6: =IFERROR(INDEX(md_deflator,MATCH(F$5,md_years,0)),1) -> 1.4596331 | G6: =IFERROR(INDEX(md_deflator,MATCH(G$5,md_years,0)),1) -> 1.4385616 | H6: =IFERROR(INDEX(md_deflator,MATCH(H$5,md_years,0)),1) -> 1.415598 | I6: =IFERROR(INDEX(md_deflator,MATCH(I$5,md_years,0)),1) -> 1.4139197 | ... S6: =IFERROR(INDEX(md_deflator,MATCH(S$5,md_years,0)),1) -> 1.0409389
A7: BEA deflator [MULTIPLIER: nominal x this = base-year 2026$. Do NOT divide.] | B7: =IFERROR(INDEX(md_deflator_ppe,MATCH(B$5,md_years_bea,0)),1) -> 1.1907356 | C7: =IFERROR(INDEX(md_deflator_ppe,MATCH(C$5,md_years_bea,0)),1) -> 1.1985216 | D7: =IFERROR(INDEX(md_deflator_ppe,MATCH(D$5,md_years_bea,0)),1) -> 1.2207456 | E7: =IFERROR(INDEX(md_deflator_ppe,MATCH(E$5,md_years_bea,0)),1) -> 1.2074962 | F7: =IFERROR(INDEX(md_deflator_ppe,MATCH(F$5,md_years_bea,0)),1) -> 1.1907596 | G7: =IFERROR(INDEX(md_deflator_ppe,MATCH(G$5,md_years_bea,0)),1) -> 1.1895716 | H7: =IFERROR(INDEX(md_deflator_ppe,MATCH(H$5,md_years_bea,0)),1) -> 1.1784085 | I7: =IFERROR(INDEX(md_deflator_ppe,MATCH(I$5,md_years_bea,0)),1) -> 1.1763416 | ... S7: =IFERROR(INDEX(md_deflator_ppe,MATCH(S$5,md_years_bea,0)),1) -> 1.0172442
A9: REPORTED (nominal $mm)
A10: Total assets | B10: =IFERROR(INDEX(rep_total_assets,MATCH(B$5,rep_years_bs,0)),0) -> 0.039572 | C10: =IFERROR(INDEX(rep_total_assets,MATCH(C$5,rep_years_bs,0)),0) -> 0.053851 | D10: =IFERROR(INDEX(rep_total_assets,MATCH(D$5,rep_years_bs,0)),0) -> 0.075183 | E10: =IFERROR(INDEX(rep_total_assets,MATCH(E$5,rep_years_bs,0)),0) -> 0.116371 | F10: =IFERROR(INDEX(rep_total_assets,MATCH(F$5,rep_years_bs,0)),0) -> 0.176064 | G10: =IFERROR(INDEX(rep_total_assets,MATCH(G$5,rep_years_bs,0)),0) -> 0.207 | H10: =IFERROR(INDEX(rep_total_assets,MATCH(H$5,rep_years_bs,0)),0) -> 0.231839 | I10: =IFERROR(INDEX(rep_total_assets,MATCH(I$5,rep_years_bs,0)),0) -> 0.290479 | ... S10: =IFERROR(INDEX(rep_total_assets,MATCH(S$5,rep_years_bs,0)),0) -> 0.359241
A11: Total liabilities | B11: =IFERROR(INDEX(rep_total_liab,MATCH(B$5,rep_years_bs,0)),0) -> 0.018542 | C11: =IFERROR(INDEX(rep_total_liab,MATCH(C$5,rep_years_bs,0)),0) -> 0.026019 | D11: =IFERROR(INDEX(rep_total_liab,MATCH(D$5,rep_years_bs,0)),0) -> 0.027392 | E11: =IFERROR(INDEX(rep_total_liab,MATCH(E$5,rep_years_bs,0)),0) -> 0.039756 | F11: =IFERROR(INDEX(rep_total_liab,MATCH(F$5,rep_years_bs,0)),0) -> 0.057854 | G11: =IFERROR(INDEX(rep_total_liab,MATCH(G$5,rep_years_bs,0)),0) -> 0.083451 | H11: =IFERROR(INDEX(rep_total_liab,MATCH(H$5,rep_years_bs,0)),0) -> 0.120292 | I11: =IFERROR(INDEX(rep_total_liab,MATCH(I$5,rep_years_bs,0)),0) -> 0.171124 | ... S11: =IFERROR(INDEX(rep_total_liab,MATCH(S$5,rep_years_bs,0)),0) -> 0.285508
A12: Cash | B12: =IFERROR(INDEX(rep_cash,MATCH(B$5,rep_years_bs,0)),0) -> 0.011875 | C12: =IFERROR(INDEX(rep_cash,MATCH(C$5,rep_years_bs,0)),0) -> 0.005263 | D12: =IFERROR(INDEX(rep_cash,MATCH(D$5,rep_years_bs,0)),0) -> 0.011261 | E12: =IFERROR(INDEX(rep_cash,MATCH(E$5,rep_years_bs,0)),0) -> 0.009815 | F12: =IFERROR(INDEX(rep_cash,MATCH(F$5,rep_years_bs,0)),0) -> 0.010746 | G12: =IFERROR(INDEX(rep_cash,MATCH(G$5,rep_years_bs,0)),0) -> 0.014259 | H12: =IFERROR(INDEX(rep_cash,MATCH(H$5,rep_years_bs,0)),0) -> 0.013844 | I12: =IFERROR(INDEX(rep_cash,MATCH(I$5,rep_years_bs,0)),0) -> 0.02112 | ... S12: =IFERROR(INDEX(rep_cash,MATCH(S$5,rep_years_bs,0)),0) -> 0.035934
A13: Short-term investments | B13: =IFERROR(INDEX(rep_sti,MATCH(B$5,rep_years_bs,0)),0) -> 0.012615 | C13: =IFERROR(INDEX(rep_sti,MATCH(C$5,rep_years_bs,0)),0) -> 0.018201 | D13: =IFERROR(INDEX(rep_sti,MATCH(D$5,rep_years_bs,0)),0) -> 0.014359 | E13: =IFERROR(INDEX(rep_sti,MATCH(E$5,rep_years_bs,0)),0) -> 0.016137 | F13: =IFERROR(INDEX(rep_sti,MATCH(F$5,rep_years_bs,0)),0) -> 0.018383 | G13: =IFERROR(INDEX(rep_sti,MATCH(G$5,rep_years_bs,0)),0) -> 0.026287 | H13: =IFERROR(INDEX(rep_sti,MATCH(H$5,rep_years_bs,0)),0) -> 0.011233 | I13: =IFERROR(INDEX(rep_sti,MATCH(I$5,rep_years_bs,0)),0) -> 0.020481 | ... S13: =IFERROR(INDEX(rep_sti,MATCH(S$5,rep_years_bs,0)),0) -> 0.018763
A14: Total debt | B14: =IFERROR(INDEX(rep_total_debt,MATCH(B$5,rep_years_bs,0)),0) -> 0 | C14: =IFERROR(INDEX(rep_total_debt,MATCH(C$5,rep_years_bs,0)),0) -> 0 | D14: =IFERROR(INDEX(rep_total_debt,MATCH(D$5,rep_years_bs,0)),0) -> 0 | E14: =IFERROR(INDEX(rep_total_debt,MATCH(E$5,rep_years_bs,0)),0) -> 0 | F14: =IFERROR(INDEX(rep_total_debt,MATCH(F$5,rep_years_bs,0)),0) -> 0 | G14: =IFERROR(INDEX(rep_total_debt,MATCH(G$5,rep_years_bs,0)),0) -> 0.01696 | H14: =IFERROR(INDEX(rep_total_debt,MATCH(H$5,rep_years_bs,0)),0) -> 0.035295 | I14: =IFERROR(INDEX(rep_total_debt,MATCH(I$5,rep_years_bs,0)),0) -> 0.064462 | ... S14: =IFERROR(INDEX(rep_total_debt,MATCH(S$5,rep_years_bs,0)),0) -> 0.112377
A15: Pension (NC) | B15: =IFERROR(INDEX(rep_pension,MATCH(B$5,rep_years_bs,0)),0) -> 0 | C15: =IFERROR(INDEX(rep_pension,MATCH(C$5,rep_years_bs,0)),0) -> 0 | D15: =IFERROR(INDEX(rep_pension,MATCH(D$5,rep_years_bs,0)),0) -> 0 | E15: =IFERROR(INDEX(rep_pension,MATCH(E$5,rep_years_bs,0)),0) -> 0 | F15: =IFERROR(INDEX(rep_pension,MATCH(F$5,rep_years_bs,0)),0) -> 0 | G15: =IFERROR(INDEX(rep_pension,MATCH(G$5,rep_years_bs,0)),0) -> 0 | H15: =IFERROR(INDEX(rep_pension,MATCH(H$5,rep_years_bs,0)),0) -> 0 | I15: =IFERROR(INDEX(rep_pension,MATCH(I$5,rep_years_bs,0)),0) -> 0 | ... S15: =IFERROR(INDEX(rep_pension,MATCH(S$5,rep_years_bs,0)),0) -> 0
A16: Minority interest | B16: =IFERROR(INDEX(rep_mi,MATCH(B$5,rep_years_bs,0)),0) -> 0 | C16: =IFERROR(INDEX(rep_mi,MATCH(C$5,rep_years_bs,0)),0) -> 0 | D16: =IFERROR(INDEX(rep_mi,MATCH(D$5,rep_years_bs,0)),0) -> 0 | E16: =IFERROR(INDEX(rep_mi,MATCH(E$5,rep_years_bs,0)),0) -> 0 | F16: =IFERROR(INDEX(rep_mi,MATCH(F$5,rep_years_bs,0)),0) -> 0 | G16: =IFERROR(INDEX(rep_mi,MATCH(G$5,rep_years_bs,0)),0) -> 0 | H16: =IFERROR(INDEX(rep_mi,MATCH(H$5,rep_years_bs,0)),0) -> 0 | I16: =IFERROR(INDEX(rep_mi,MATCH(I$5,rep_years_bs,0)),0) -> 0 | ... S16: =IFERROR(INDEX(rep_mi,MATCH(S$5,rep_years_bs,0)),0) -> 0
A17: Reported net PP&E | B17: =IFERROR(INDEX(rep_net_ppe,MATCH(B$5,rep_years_bs,0)),0) -> 0.002455 | C17: =IFERROR(INDEX(rep_net_ppe,MATCH(C$5,rep_years_bs,0)),0) -> 0.002954 | D17: =IFERROR(INDEX(rep_net_ppe,MATCH(D$5,rep_years_bs,0)),0) -> 0.004768 | E17: =IFERROR(INDEX(rep_net_ppe,MATCH(E$5,rep_years_bs,0)),0) -> 0.007777 | F17: =IFERROR(INDEX(rep_net_ppe,MATCH(F$5,rep_years_bs,0)),0) -> 0.015452 | G17: =IFERROR(INDEX(rep_net_ppe,MATCH(G$5,rep_years_bs,0)),0) -> 0.016597 | H17: =IFERROR(INDEX(rep_net_ppe,MATCH(H$5,rep_years_bs,0)),0) -> 0.020624 | I17: =IFERROR(INDEX(rep_net_ppe,MATCH(I$5,rep_years_bs,0)),0) -> 0.022471 | ... S17: =IFERROR(INDEX(rep_net_ppe,MATCH(S$5,rep_years_bs,0)),0) -> 0.049834
A18: Reported CSE (common) | B18: =IFERROR(INDEX(rep_cse,MATCH(B$5,rep_years_bs,0)),0) -> 0.02103 | C18: =IFERROR(INDEX(rep_cse,MATCH(C$5,rep_years_bs,0)),0) -> 0.027832 | D18: =IFERROR(INDEX(rep_cse,MATCH(D$5,rep_years_bs,0)),0) -> 0.047791 | E18: =IFERROR(INDEX(rep_cse,MATCH(E$5,rep_years_bs,0)),0) -> 0.076615 | F18: =IFERROR(INDEX(rep_cse,MATCH(F$5,rep_years_bs,0)),0) -> 0.11821 | G18: =IFERROR(INDEX(rep_cse,MATCH(G$5,rep_years_bs,0)),0) -> 0.123549 | H18: =IFERROR(INDEX(rep_cse,MATCH(H$5,rep_years_bs,0)),0) -> 0.111547 | I18: =IFERROR(INDEX(rep_cse,MATCH(I$5,rep_years_bs,0)),0) -> 0.119355 | ... S18: =IFERROR(INDEX(rep_cse,MATCH(S$5,rep_years_bs,0)),0) -> 0.073733
A19: Shares (mm) | B19: =IFERROR(INDEX(rep_shares,MATCH(B$5,rep_years_bs,0)),0) -> 0.02526 | C19: =IFERROR(INDEX(rep_shares,MATCH(C$5,rep_years_bs,0)),0) -> 0.025396 | D19: =IFERROR(INDEX(rep_shares,MATCH(D$5,rep_years_bs,0)),0) -> 0.025892 | E19: =IFERROR(INDEX(rep_shares,MATCH(E$5,rep_years_bs,0)),0) -> 0.026226 | F19: =IFERROR(INDEX(rep_shares,MATCH(F$5,rep_years_bs,0)),0) -> 0.02647 | G19: =IFERROR(INDEX(rep_shares,MATCH(G$5,rep_years_bs,0)),0) -> 0.026087 | H19: =IFERROR(INDEX(rep_shares,MATCH(H$5,rep_years_bs,0)),0) -> 0.024491 | I19: =IFERROR(INDEX(rep_shares,MATCH(I$5,rep_years_bs,0)),0) -> 0.023172 | ... S19: =IFERROR(INDEX(rep_shares,MATCH(S$5,rep_years_bs,0)),0) -> 0.015005
A20: Operating income | B20: =IFERROR(INDEX(rep_oi,MATCH(B$5,rep_years_is,0)),0) -> 0.006275 | C20: =IFERROR(INDEX(rep_oi,MATCH(C$5,rep_years_is,0)),0) -> 0.01137 | D20: =IFERROR(INDEX(rep_oi,MATCH(D$5,rep_years_is,0)),0) -> 0.018385 | E20: =IFERROR(INDEX(rep_oi,MATCH(E$5,rep_years_is,0)),0) -> 0.03379 | F20: =IFERROR(INDEX(rep_oi,MATCH(F$5,rep_years_is,0)),0) -> 0.055241 | G20: =IFERROR(INDEX(rep_oi,MATCH(G$5,rep_years_is,0)),0) -> 0.048999 | H20: =IFERROR(INDEX(rep_oi,MATCH(H$5,rep_years_is,0)),0) -> 0.052503 | I20: =IFERROR(INDEX(rep_oi,MATCH(I$5,rep_years_is,0)),0) -> 0.07123 | ... S20: =IFERROR(INDEX(rep_oi,MATCH(S$5,rep_years_is,0)),0) -> 0.13305
A21: D&A (reconciled) | B21: =IFERROR(INDEX(rep_da,MATCH(B$5,rep_years_is,0)),0) -> 0 | C21: =IFERROR(INDEX(rep_da,MATCH(C$5,rep_years_is,0)),0) -> 0 | D21: =IFERROR(INDEX(rep_da,MATCH(D$5,rep_years_is,0)),0) -> 0 | E21: =IFERROR(INDEX(rep_da,MATCH(E$5,rep_years_is,0)),0) -> 0 | F21: =IFERROR(INDEX(rep_da,MATCH(F$5,rep_years_is,0)),0) -> 0 | G21: =IFERROR(INDEX(rep_da,MATCH(G$5,rep_years_is,0)),0) -> 0 | H21: =IFERROR(INDEX(rep_da,MATCH(H$5,rep_years_is,0)),0) -> 0 | I21: =IFERROR(INDEX(rep_da,MATCH(I$5,rep_years_is,0)),0) -> 0 | ... S21: =IFERROR(INDEX(rep_da,MATCH(S$5,rep_years_is,0)),0) -> 0.011698
A22: Net income (common) | B22: =IFERROR(INDEX(rep_ni,MATCH(B$5,rep_years_is,0)),0) -> 0.004834 | C22: =IFERROR(INDEX(rep_ni,MATCH(C$5,rep_years_is,0)),0) -> 0.008235 | D22: =IFERROR(INDEX(rep_ni,MATCH(D$5,rep_years_is,0)),0) -> 0.014013 | E22: =IFERROR(INDEX(rep_ni,MATCH(E$5,rep_years_is,0)),0) -> 0.025922 | F22: =IFERROR(INDEX(rep_ni,MATCH(F$5,rep_years_is,0)),0) -> 0.041733 | G22: =IFERROR(INDEX(rep_ni,MATCH(G$5,rep_years_is,0)),0) -> 0.037037 | H22: =IFERROR(INDEX(rep_ni,MATCH(H$5,rep_years_is,0)),0) -> 0.03951 | I22: =IFERROR(INDEX(rep_ni,MATCH(I$5,rep_years_is,0)),0) -> 0.053394 | ... S22: =IFERROR(INDEX(rep_ni,MATCH(S$5,rep_years_is,0)),0) -> 0.11201
A23: Interest expense | B23: =IFERROR(INDEX(rep_intexp,MATCH(B$5,rep_years_is,0)),0) -> 0.00062 | C23: =IFERROR(INDEX(rep_intexp,MATCH(C$5,rep_years_is,0)),0) -> 0.000326 | D23: =IFERROR(INDEX(rep_intexp,MATCH(D$5,rep_years_is,0)),0) -> 0.000155 | E23: =IFERROR(INDEX(rep_intexp,MATCH(E$5,rep_years_is,0)),0) -> 0.000415 | F23: =IFERROR(INDEX(rep_intexp,MATCH(F$5,rep_years_is,0)),0) -> 0.000522 | G23: =IFERROR(INDEX(rep_intexp,MATCH(G$5,rep_years_is,0)),0) -> 0.000136 | H23: =IFERROR(INDEX(rep_intexp,MATCH(H$5,rep_years_is,0)),0) -> 0.000384 | I23: =IFERROR(INDEX(rep_intexp,MATCH(I$5,rep_years_is,0)),0) -> 0.000733 | ... S23: =IFERROR(INDEX(rep_intexp,MATCH(S$5,rep_years_is,0)),0) -> 0
A24: Tax rate | B24: =IFERROR(INDEX(rep_taxrate,MATCH(B$5,rep_years_is,0)),0) -> 0.298912 | C24: =IFERROR(INDEX(rep_taxrate,MATCH(C$5,rep_years_is,0)),0) -> 0.317504 | D24: =IFERROR(INDEX(rep_taxrate,MATCH(D$5,rep_years_is,0)),0) -> 0.244175 | E24: =IFERROR(INDEX(rep_taxrate,MATCH(E$5,rep_years_is,0)),0) -> 0.242158 | F24: =IFERROR(INDEX(rep_taxrate,MATCH(F$5,rep_years_is,0)),0) -> 0.251601 | G24: =IFERROR(INDEX(rep_taxrate,MATCH(G$5,rep_years_is,0)),0) -> 0.261549 | H24: =IFERROR(INDEX(rep_taxrate,MATCH(H$5,rep_years_is,0)),0) -> 0.261261 | I24: =IFERROR(INDEX(rep_taxrate,MATCH(I$5,rep_years_is,0)),0) -> 0.263683 | ... S24: =IFERROR(INDEX(rep_taxrate,MATCH(S$5,rep_years_is,0)),0) -> 0.1561
A25: OCI | B25: =IFERROR(INDEX(rep_oci,MATCH(B$5,rep_years_bs,0)),0) -> 8e-06 | C25: =IFERROR(INDEX(rep_oci,MATCH(C$5,rep_years_bs,0)),0) -> 8.4e-05 | D25: =IFERROR(INDEX(rep_oci,MATCH(D$5,rep_years_bs,0)),0) -> -4.6e-05 | E25: =IFERROR(INDEX(rep_oci,MATCH(E$5,rep_years_bs,0)),0) -> 0.000443 | F25: =IFERROR(INDEX(rep_oci,MATCH(F$5,rep_years_bs,0)),0) -> 0.000499 | G25: =IFERROR(INDEX(rep_oci,MATCH(G$5,rep_years_bs,0)),0) -> -0.000471 | H25: =IFERROR(INDEX(rep_oci,MATCH(H$5,rep_years_bs,0)),0) -> 0.001082 | I25: =IFERROR(INDEX(rep_oci,MATCH(I$5,rep_years_bs,0)),0) -> -0.000345 | ... S25: =IFERROR(INDEX(rep_oci,MATCH(S$5,rep_years_bs,0)),0) -> -0.005571
A26: Dividends paid | B26: =IFERROR(INDEX(rep_div,MATCH(B$5,rep_years_cf,0)),0) -> 0 | C26: =IFERROR(INDEX(rep_div,MATCH(C$5,rep_years_cf,0)),0) -> 0 | D26: =IFERROR(INDEX(rep_div,MATCH(D$5,rep_years_cf,0)),0) -> 0 | E26: =IFERROR(INDEX(rep_div,MATCH(E$5,rep_years_cf,0)),0) -> 0 | F26: =IFERROR(INDEX(rep_div,MATCH(F$5,rep_years_cf,0)),0) -> -0.002488 | G26: =IFERROR(INDEX(rep_div,MATCH(G$5,rep_years_cf,0)),0) -> -0.010564 | H26: =IFERROR(INDEX(rep_div,MATCH(H$5,rep_years_cf,0)),0) -> -0.011126 | I26: =IFERROR(INDEX(rep_div,MATCH(I$5,rep_years_cf,0)),0) -> -0.011561 | ... S26: =IFERROR(INDEX(rep_div,MATCH(S$5,rep_years_cf,0)),0) -> -0.015421
A27: Repurchases | B27: =IFERROR(INDEX(rep_repurch,MATCH(B$5,rep_years_cf,0)),0) -> -0.000124 | C27: =IFERROR(INDEX(rep_repurch,MATCH(C$5,rep_years_cf,0)),0) -> -0.000475 | D27: =IFERROR(INDEX(rep_repurch,MATCH(D$5,rep_years_cf,0)),0) -> -0.000912 | E27: =IFERROR(INDEX(rep_repurch,MATCH(E$5,rep_years_cf,0)),0) -> -0.000831 | F27: =IFERROR(INDEX(rep_repurch,MATCH(F$5,rep_years_cf,0)),0) -> -0.000665 | G27: =IFERROR(INDEX(rep_repurch,MATCH(G$5,rep_years_cf,0)),0) -> -0.02286 | H27: =IFERROR(INDEX(rep_repurch,MATCH(H$5,rep_years_cf,0)),0) -> -0.045 | I27: =IFERROR(INDEX(rep_repurch,MATCH(I$5,rep_years_cf,0)),0) -> -0.035253 | ... S27: =IFERROR(INDEX(rep_repurch,MATCH(S$5,rep_years_cf,0)),0) -> -0.090711
A29: PARTITION (nominal)
A30: Financial obligations | B30: =B14+B15 -> 0 | C30: =C14+C15 -> 0 | D30: =D14+D15 -> 0 | E30: =E14+E15 -> 0 | F30: =F14+F15 -> 0 | G30: =G14+G15 -> 0.01696 | H30: =H14+H15 -> 0.035295 | I30: =I14+I15 -> 0.064462 | ... S30: =S14+S15 -> 0.112377
A31: Financial assets | B31: =B12+B13 -> 0.02449 | C31: =C12+C13 -> 0.023464 | D31: =D12+D13 -> 0.02562 | E31: =E12+E13 -> 0.025952 | F31: =F12+F13 -> 0.029129 | G31: =G12+G13 -> 0.040546 | H31: =H12+H13 -> 0.025077 | I31: =I12+I13 -> 0.041601 | ... S31: =S12+S13 -> 0.054697
A32: NFO (nominal) | B32: =B30-B31+B16 -> -0.02449 | C32: =C30-C31+C16 -> -0.023464 | D32: =D30-D31+D16 -> -0.02562 | E32: =E30-E31+E16 -> -0.025952 | F32: =F30-F31+F16 -> -0.029129 | G32: =G30-G31+G16 -> -0.023586 | H32: =H30-H31+H16 -> 0.010218 | I32: =I30-I31+I16 -> 0.022861 | ... S32: =S30-S31+S16 -> 0.05768
A33: Operating assets | B33: =B10-B31 -> 0.015082 | C33: =C10-C31 -> 0.030387 | D33: =D10-D31 -> 0.049563 | E33: =E10-E31 -> 0.090419 | F33: =F10-F31 -> 0.146935 | G33: =G10-G31 -> 0.166454 | H33: =H10-H31 -> 0.206762 | I33: =I10-I31 -> 0.248878 | ... S33: =S10-S31 -> 0.304544
A34: Operating liabilities | B34: =B11-B30 -> 0.018542 | C34: =C11-C30 -> 0.026019 | D34: =D11-D30 -> 0.027392 | E34: =E11-E30 -> 0.039756 | F34: =F11-F30 -> 0.057854 | G34: =G11-G30 -> 0.066491 | H34: =H11-H30 -> 0.084997 | I34: =I11-I30 -> 0.106662 | ... S34: =S11-S30 -> 0.173131
A35: NOA (nominal, reported PP&E) | B35: =B33-B34 -> -0.00346 | C35: =C33-C34 -> 0.004368 | D35: =D33-D34 -> 0.022171 | E35: =E33-E34 -> 0.050663 | F35: =F33-F34 -> 0.089081 | G35: =G33-G34 -> 0.099963 | H35: =H33-H34 -> 0.121765 | I35: =I33-I34 -> 0.142216 | ... S35: =S33-S34 -> 0.131413
A36: CSE (reported) | B36: =B18 -> 0.02103 | C36: =C18 -> 0.027832 | D36: =D18 -> 0.047791 | E36: =E18 -> 0.076615 | F36: =F18 -> 0.11821 | G36: =G18 -> 0.123549 | H36: =H18 -> 0.111547 | I36: =I18 -> 0.119355 | ... S36: =S18 -> 0.073733
A37: tie: NOA−NFO−CSE (nom) | B37: =B35-B32-B18 -> 0 | C37: =C35-C32-C18 -> 0 | D37: =D35-D32-D18 -> 0 | E37: =E35-E32-E18 -> 0 | F37: =F35-F32-F18 -> 0 | G37: =G35-G32-G18 -> 0 | H37: =H35-H32-H18 -> 0 | I37: =I35-I32-I18 -> 0 | ... S37: =S35-S32-S18 -> 0
A39: ECONOMIC RESTATEMENT (real 2026$)
A40: Real net PP&E (BEA) | B40: =IFERROR(INDEX(ce_real_net_series,MATCH(VALUE(B$5),ce_years,0)),0) -> 0.0034704881 | C40: =IFERROR(INDEX(ce_real_net_series,MATCH(VALUE(C$5),ce_years,0)),0) -> 0.0044065493 | D40: =IFERROR(INDEX(ce_real_net_series,MATCH(VALUE(D$5),ce_years,0)),0) -> 0.0062931021 | E40: =IFERROR(INDEX(ce_real_net_series,MATCH(VALUE(E$5),ce_years,0)),0) -> 0.010650461 | F40: =IFERROR(INDEX(ce_real_net_series,MATCH(VALUE(F$5),ce_years,0)),0) -> 0.019268235 | G40: =IFERROR(INDEX(ce_real_net_series,MATCH(VALUE(G$5),ce_years,0)),0) -> 0.026793353 | H40: =IFERROR(INDEX(ce_real_net_series,MATCH(VALUE(H$5),ce_years,0)),0) -> 0.034968562 | I40: =IFERROR(INDEX(ce_real_net_series,MATCH(VALUE(I$5),ce_years,0)),0) -> 0.044029363 | ... S40: =IFERROR(INDEX(ce_real_net_series,MATCH(VALUE(S$5),ce_years,0)),0) -> 0.067457873
A41: Non-PP&E op net (nom) | B41: =B33-B17-B34 -> -0.005915 | C41: =C33-C17-C34 -> 0.001414 | D41: =D33-D17-D34 -> 0.017403 | E41: =E33-E17-E34 -> 0.042886 | F41: =F33-F17-F34 -> 0.073629 | G41: =G33-G17-G34 -> 0.083366 | H41: =H33-H17-H34 -> 0.101141 | I41: =I33-I17-I34 -> 0.119745 | ... S41: =S33-S17-S34 -> 0.081579
A42: Real non-PP&E op net | B42: =B41*B6 -> -0.0092068041 | C42: =C41*C6 -> 0.0022087748 | D42: =D41*D6 -> 0.026746091 | E42: =E41*E6 -> 0.063893255 | F42: =F41*F6 -> 0.10747132 | G42: =G41*G6 -> 0.11992713 | H42: =H41*H6 -> 0.14317499 | I42: =I41*I6 -> 0.16930981 | ... S42: =S41*S6 -> 0.084918756
A43: Real NOA | B43: =B42+B40 -> -0.005736316 | C43: =C42+C40 -> 0.0066153241 | D43: =D42+D40 -> 0.033039193 | E43: =E42+E40 -> 0.074543716 | F43: =F42+F40 -> 0.12673956 | G43: =G42+G40 -> 0.14672048 | H43: =H42+H40 -> 0.17814356 | I43: =I42+I40 -> 0.21333918 | ... S43: =S42+S40 -> 0.15237663
A44: Real NFO | B44: =B32*B6 -> -0.038119126 | C44: =C32*C6 -> -0.03665254 | D44: =D32*D6 -> -0.039374524 | E44: =E32*E6 -> -0.038664314 | F44: =F32*F6 -> -0.042517652 | G44: =G32*G6 -> -0.033929914 | H44: =H32*H6 -> 0.01446458 | I44: =I32*I6 -> 0.032323618 | ... S44: =S32*S6 -> 0.060041357
A45: Real CSE | B45: =B43-B44 -> 0.03238281 | C45: =C43-C44 -> 0.043267865 | D45: =D43-D44 -> 0.072413717 | E45: =E43-E44 -> 0.11320803 | F45: =F43-F44 -> 0.16925721 | G45: =G43-G44 -> 0.1806504 | H45: =H43-H44 -> 0.16367898 | I45: =I43-I44 -> 0.18101556 | ... S45: =S43-S44 -> 0.092335272
A46: tie: Real NOA−NFO−CSE | B46: =B43-B44-B45 -> 0 | C46: =C43-C44-C45 -> 0 | D46: =D43-D44-D45 -> 0 | E46: =E43-E44-E45 -> 0 | F46: =F43-F44-F45 -> 0 | G46: =G43-G44-G45 -> 0 | H46: =H43-H44-H45 -> 0 | I46: =I43-I44-I45 -> 0 | ... S46: =S43-S44-S45 -> 0
A48: ECONOMIC FLOWS (real 2026$)
A49: Real EBITDA | B49: =(B20+B21)*B6 -> 0.0097671506 | C49: =(C20+C21)*C6 -> 0.017760799 | D49: =(D20+D21)*D6 -> 0.028255294 | E49: =(E20+E21)*E6 -> 0.050341676 | F49: =(F20+F21)*F6 -> 0.080631592 | G49: =(G20+G21)*G6 -> 0.070488081 | H49: =(H20+H21)*H6 -> 0.07432314 | I49: =(I20+I21)*I6 -> 0.1007135 | ... S49: =(S20+S21)*S6 -> 0.15067383
A50: Economic depreciation | B50: =IFERROR(INDEX(ce_econ_dep_series,MATCH(VALUE(B$5),ce_years,0)),0) -> 0.00043938456 | C50: =IFERROR(INDEX(ce_econ_dep_series,MATCH(VALUE(C$5),ce_years,0)),0) -> 0.00056471911 | D50: =IFERROR(INDEX(ce_econ_dep_series,MATCH(VALUE(D$5),ce_years,0)),0) -> 0.0007949093 | E50: =IFERROR(INDEX(ce_econ_dep_series,MATCH(VALUE(E$5),ce_years,0)),0) -> 0.0012777201 | F50: =IFERROR(INDEX(ce_econ_dep_series,MATCH(VALUE(F$5),ce_years,0)),0) -> 0.0022014139 | G50: =IFERROR(INDEX(ce_econ_dep_series,MATCH(VALUE(G$5),ce_years,0)),0) -> 0.0031163311 | H50: =IFERROR(INDEX(ce_econ_dep_series,MATCH(VALUE(H$5),ce_years,0)),0) -> 0.0041833203 | I50: =IFERROR(INDEX(ce_econ_dep_series,MATCH(VALUE(I$5),ce_years,0)),0) -> 0.0054372298 | ... S50: =IFERROR(INDEX(ce_econ_dep_series,MATCH(VALUE(S$5),ce_years,0)),0) -> 0.013286613
A51: Economic OI (pretax) | B51: =B49-B50 -> 0.009327766 | C51: =C49-C50 -> 0.01719608 | D51: =D49-D50 -> 0.027460385 | E51: =E49-E50 -> 0.049063956 | F51: =F49-F50 -> 0.078430178 | G51: =G49-G50 -> 0.06737175 | H51: =H49-H50 -> 0.07013982 | I51: =I49-I50 -> 0.095276269 | ... S51: =S49-S50 -> 0.13738721
A52: Economic OI-after-tax | B52: =(B51*(1-B24)-B24*B50*(1-SUMPRODUCT('Cap Engine'!$B$7:$B$43,'Cap Engine'!$F$7:$F$43)/'Cap Engine'!$B$46)) -> 0.0065249822 | C52: =(C51*(1-C24)-C24*C50*(1-SUMPRODUCT('Cap Engine'!$B$7:$B$43,'Cap Engine'!$F$7:$F$43)/'Cap Engine'!$B$46)) -> 0.01171632 | D52: =(D51*(1-D24)-D24*D50*(1-SUMPRODUCT('Cap Engine'!$B$7:$B$43,'Cap Engine'!$F$7:$F$43)/'Cap Engine'!$B$46)) -> 0.020733665 | E52: =(E51*(1-E24)-E24*E50*(1-SUMPRODUCT('Cap Engine'!$B$7:$B$43,'Cap Engine'!$F$7:$F$43)/'Cap Engine'!$B$46)) -> 0.037148325 | F52: =(F51*(1-F24)-F24*F50*(1-SUMPRODUCT('Cap Engine'!$B$7:$B$43,'Cap Engine'!$F$7:$F$43)/'Cap Engine'!$B$46)) -> 0.058635484 | G52: =(G51*(1-G24)-G24*G50*(1-SUMPRODUCT('Cap Engine'!$B$7:$B$43,'Cap Engine'!$F$7:$F$43)/'Cap Engine'!$B$46)) -> 0.049660113 | H52: =(H51*(1-H24)-H24*H50*(1-SUMPRODUCT('Cap Engine'!$B$7:$B$43,'Cap Engine'!$F$7:$F$43)/'Cap Engine'!$B$46)) -> 0.051693503 | I52: =(I51*(1-I24)-I24*I50*(1-SUMPRODUCT('Cap Engine'!$B$7:$B$43,'Cap Engine'!$F$7:$F$43)/'Cap Engine'!$B$46)) -> 0.069994131 | ... S52: =(S51*(1-S24)-S24*S50*(1-SUMPRODUCT('Cap Engine'!$B$7:$B$43,'Cap Engine'!$F$7:$F$43)/'Cap Engine'!$B$46)) -> 0.11571047
A53: NFE after-tax (real) | B53: =B23*B6*(1-B24) -> 0.00067657879 | C53: =C23*C6*(1-C24) -> 0.00034755196 | D53: =D23*D6*(1-D24) -> 0.00018004835 | E53: =E23*E6*(1-E24) -> 0.00046856111 | F53: =F23*F6*(1-F24) -> 0.00057022651 | G53: =G23*G6*(1-G24) -> 0.00014447379 | H53: =H23*H6*(1-H24) -> 0.00040157085 | I53: =I23*I6*(1-I24) -> 0.00076312124 | ... S53: =S23*S6*(1-S24) -> 0
A54: Economic NI | B54: =B52-B53 -> 0.0058484034 | C54: =C52-C53 -> 0.011368768 | D54: =D52-D53 -> 0.020553616 | E54: =E52-E53 -> 0.036679764 | F54: =F52-F53 -> 0.058065258 | G54: =G52-G53 -> 0.049515639 | H54: =H52-H53 -> 0.051291932 | I54: =I52-I53 -> 0.06923101 | ... S54: =S52-S53 -> 0.11571047
A55: OCI (real) | B55: =B25*B6 -> 1.2452144e-05 | C55: =C25*C6 -> 0.00013121435 | D55: =D25*D6 -> -7.0695867e-05 | E55: =E25*E6 -> 0.00065999888 | F55: =F25*F6 -> 0.00072835691 | G55: =G25*G6 -> -0.00067756252 | H55: =H25*H6 -> 0.001531677 | I55: =I25*I6 -> -0.00048780229 | ... S55: =S25*S6 -> -0.0057990707
A56: Comprehensive income | B56: =B54+B55 -> 0.0058608556 | C56: =C54+C55 -> 0.011499983 | D56: =D54+D55 -> 0.02048292 | E56: =E54+E55 -> 0.037339762 | F56: =F54+F55 -> 0.058793615 | G56: =G54+G55 -> 0.048838077 | H56: =H54+H55 -> 0.052823609 | I56: =I54+I55 -> 0.068743208 | ... S56: =S54+S55 -> 0.1099114
A58: METRICS (economic, ending-balance)
A59: RNOA (econ) | B59: =B52/B43 -> -1.1374865 | C59: =C52/C43 -> 1.7710879 | D59: =D52/D43 -> 0.62754755 | E59: =E52/E43 -> 0.4983428 | F59: =F52/F43 -> 0.46264548 | G59: =G52/G43 -> 0.33846749 | H59: =H52/H43 -> 0.29017891 | I59: =I52/I43 -> 0.32808851 | ... S59: =S52/S43 -> 0.7593715
A60: FLEV (econ) | B60: =B44/B45 -> -1.1771408 | C60: =C44/C45 -> -0.84710768 | D60: =D44/D45 -> -0.543744 | E60: =E44/E45 -> -0.34153331 | F60: =F44/F45 -> -0.25120142 | G60: =G44/G45 -> -0.18782087 | H60: =H44/H45 -> 0.088371643 | I60: =I44/I45 -> 0.17856818 | ... S60: =S44/S45 -> 0.65025375
A61: NBC | B61: =B53/B44 -> -0.017749063 | C61: =C53/C44 -> -0.009482343 | D61: =D53/D44 -> -0.0045727117 | E61: =E53/E44 -> -0.012118697 | F61: =F53/F44 -> -0.013411524 | G61: =G53/G44 -> -0.0042580063 | H61: =H53/H44 -> 0.027762358 | I61: =I53/I44 -> 0.023608782 | ... S61: =S53/S44 -> 0
A62: Spread | B62: =B59-B61 -> -1.1197375 | C62: =C59-C61 -> 1.7805702 | D62: =D59-D61 -> 0.63212027 | E62: =E59-E61 -> 0.5104615 | F62: =F59-F61 -> 0.476057 | G62: =G59-G61 -> 0.3427255 | H62: =H59-H61 -> 0.26241655 | I62: =I59-I61 -> 0.30447972 | ... S62: =S59-S61 -> 0.7593715
A63: ROCE | B63: =B56/B45 -> 0.18098663 | C63: =C56/C45 -> 0.26578577 | D63: =D56/D45 -> 0.28285967 | E63: =E56/E45 -> 0.32983316 | F63: =F56/F45 -> 0.34736254 | G63: =G56/G45 -> 0.27034581 | H63: =H56/H45 -> 0.3227269 | I63: =I56/I45 -> 0.37976409 | ... S63: =S56/S45 -> 1.1903512
A64: Reported ROE (memo) | B64: =B22/B18 -> 0.2298621 | C64: =C22/C18 -> 0.29588244 | D64: =D22/D18 -> 0.2932142 | E64: =E22/E18 -> 0.33834106 | F64: =F22/F18 -> 0.3530412 | G64: =G22/G18 -> 0.2997758 | H64: =H22/H18 -> 0.35420047 | I64: =I22/I18 -> 0.44735453 | ... S64: =S22/S18 -> 1.5191298
A66: CLEAN-SURPLUS (nominal check)
A67: Net distribution D = −(div+repurch) | B67: =-(B26+B27) -> 0.000124 | C67: =-(C26+C27) -> 0.000475 | D67: =-(D26+D27) -> 0.000912 | E67: =-(E26+E27) -> 0.000831 | F67: =-(F26+F27) -> 0.003153 | G67: =-(G26+G27) -> 0.033424 | H67: =-(H26+H27) -> 0.056126 | I67: =-(I26+I27) -> 0.046814 | ... S67: =-(S26+S27) -> 0.106132
A68: Reported CI (nom) = NI+OCI | B68: =B22+B25 -> 0.004842 | C68: =C22+C25 -> 0.008319 | D68: =D22+D25 -> 0.013967 | E68: =E22+E25 -> 0.026365 | F68: =F22+F25 -> 0.042232 | G68: =G22+G25 -> 0.036566 | H68: =H22+H25 -> 0.040592 | I68: =I22+I25 -> 0.053049 | ... S68: =S22+S25 -> 0.106439
A69: ΔCSE (nom) | B69: ="" | C69: =C18-B18 -> 0.006802 | D69: =D18-C18 -> 0.019959 | E69: =E18-D18 -> 0.028824 | F69: =F18-E18 -> 0.041595 | G69: =G18-F18 -> 0.005339 | H69: =H18-G18 -> -0.012002 | I69: =I18-H18 -> 0.007808 | J69: =J18-I18 -> 0.008894 | ... S69: =S18-R18 -> 0.016783
A70: Clean-surplus residual (dirty) | B70: ="" | C70: =C69-(C68-C67) -> -0.001042 | D70: =D69-(D68-D67) -> 0.006904 | E70: =E69-(E68-E67) -> 0.00329 | F70: =F69-(F68-F67) -> 0.002516 | G70: =G69-(G68-G67) -> 0.002197 | H70: =H69-(H68-H67) -> 0.003532 | I70: =I69-(I68-I67) -> 0.001573 | J70: =J69-(J68-J67) -> 0.004445 | ... S70: =S69-(S68-S67) -> 0.016476
A72: ACTIVE (cfg_restatement-selected)
A73: Active NOA | B73: =IF(cfg_restatement="Economic",B43,B35) -> -0.005736316 | C73: =IF(cfg_restatement="Economic",C43,C35) -> 0.0066153241 | D73: =IF(cfg_restatement="Economic",D43,D35) -> 0.033039193 | E73: =IF(cfg_restatement="Economic",E43,E35) -> 0.074543716 | F73: =IF(cfg_restatement="Economic",F43,F35) -> 0.12673956 | G73: =IF(cfg_restatement="Economic",G43,G35) -> 0.14672048 | H73: =IF(cfg_restatement="Economic",H43,H35) -> 0.17814356 | I73: =IF(cfg_restatement="Economic",I43,I35) -> 0.21333918 | ... S73: =IF(cfg_restatement="Economic",S43,S35) -> 0.15237663
A74: Active NFO | B74: =IF(cfg_restatement="Economic",B44,B32) -> -0.038119126 | C74: =IF(cfg_restatement="Economic",C44,C32) -> -0.03665254 | D74: =IF(cfg_restatement="Economic",D44,D32) -> -0.039374524 | E74: =IF(cfg_restatement="Economic",E44,E32) -> -0.038664314 | F74: =IF(cfg_restatement="Economic",F44,F32) -> -0.042517652 | G74: =IF(cfg_restatement="Economic",G44,G32) -> -0.033929914 | H74: =IF(cfg_restatement="Economic",H44,H32) -> 0.01446458 | I74: =IF(cfg_restatement="Economic",I44,I32) -> 0.032323618 | ... S74: =IF(cfg_restatement="Economic",S44,S32) -> 0.060041357
A75: Active CSE | B75: =IF(cfg_restatement="Economic",B45,B18) -> 0.03238281 | C75: =IF(cfg_restatement="Economic",C45,C18) -> 0.043267865 | D75: =IF(cfg_restatement="Economic",D45,D18) -> 0.072413717 | E75: =IF(cfg_restatement="Economic",E45,E18) -> 0.11320803 | F75: =IF(cfg_restatement="Economic",F45,F18) -> 0.16925721 | G75: =IF(cfg_restatement="Economic",G45,G18) -> 0.1806504 | H75: =IF(cfg_restatement="Economic",H45,H18) -> 0.16367898 | I75: =IF(cfg_restatement="Economic",I45,I18) -> 0.18101556 | ... S75: =IF(cfg_restatement="Economic",S45,S18) -> 0.092335272
A76: Active OI-after-tax | B76: =IF(cfg_restatement="Economic",B52,B20*(1-B24)) -> 0.0065249822 | C76: =IF(cfg_restatement="Economic",C52,C20*(1-C24)) -> 0.01171632 | D76: =IF(cfg_restatement="Economic",D52,D20*(1-D24)) -> 0.020733665 | E76: =IF(cfg_restatement="Economic",E52,E20*(1-E24)) -> 0.037148325 | F76: =IF(cfg_restatement="Economic",F52,F20*(1-F24)) -> 0.058635484 | G76: =IF(cfg_restatement="Economic",G52,G20*(1-G24)) -> 0.049660113 | H76: =IF(cfg_restatement="Economic",H52,H20*(1-H24)) -> 0.051693503 | I76: =IF(cfg_restatement="Economic",I52,I20*(1-I24)) -> 0.069994131 | ... S76: =IF(cfg_restatement="Economic",S52,S20*(1-S24)) -> 0.11571047
A77: Active NI | B77: =IF(cfg_restatement="Economic",B54,B22) -> 0.0058484034 | C77: =IF(cfg_restatement="Economic",C54,C22) -> 0.011368768 | D77: =IF(cfg_restatement="Economic",D54,D22) -> 0.020553616 | E77: =IF(cfg_restatement="Economic",E54,E22) -> 0.036679764 | F77: =IF(cfg_restatement="Economic",F54,F22) -> 0.058065258 | G77: =IF(cfg_restatement="Economic",G54,G22) -> 0.049515639 | H77: =IF(cfg_restatement="Economic",H54,H22) -> 0.051291932 | I77: =IF(cfg_restatement="Economic",I54,I22) -> 0.06923101 | ... S77: =IF(cfg_restatement="Economic",S54,S22) -> 0.11571047
A78: Active RNOA | B78: =B76/B73 -> -1.1374865 | C78: =C76/C73 -> 1.7710879 | D78: =D76/D73 -> 0.62754755 | E78: =E76/E73 -> 0.4983428 | F78: =F76/F73 -> 0.46264548 | G78: =G76/G73 -> 0.33846749 | H78: =H76/H73 -> 0.29017891 | I78: =I76/I73 -> 0.32808851 | ... S78: =S76/S73 -> 0.7593715
A80: REAL IS LINES (real 2026$; forecast build-up base)
A81: Real revenue | B81: =IFERROR(INDEX(rep_revenue,MATCH(B$5,rep_years_is,0)),0)*B6 -> 0.050554149 | C81: =IFERROR(INDEX(rep_revenue,MATCH(C$5,rep_years_is,0)),0)*C6 -> 0.066549104 | D81: =IFERROR(INDEX(rep_revenue,MATCH(D$5,rep_years_is,0)),0)*D6 -> 0.10024213 | E81: =IFERROR(INDEX(rep_revenue,MATCH(E$5,rep_years_is,0)),0)*E6 -> 0.16127363 | F81: =IFERROR(INDEX(rep_revenue,MATCH(F$5,rep_years_is,0)),0)*F6 -> 0.22844426 | G81: =IFERROR(INDEX(rep_revenue,MATCH(G$5,rep_years_is,0)),0)*G6 -> 0.24586457 | H81: =IFERROR(INDEX(rep_revenue,MATCH(H$5,rep_years_is,0)),0)*H6 -> 0.25876423 | I81: =IFERROR(INDEX(rep_revenue,MATCH(I$5,rep_years_is,0)),0)*I6 -> 0.33045424 | ... S81: =IFERROR(INDEX(rep_revenue,MATCH(S$5,rep_years_is,0)),0)*S6 -> 0.43319818
A82: Real COGS | B82: =IFERROR(INDEX(rep_cogs,MATCH(B$5,rep_years_is,0)),0)*B6 -> 0.033206756 | C82: =IFERROR(INDEX(rep_cogs,MATCH(C$5,rep_years_is,0)),0)*C6 -> 0.040225007 | D82: =IFERROR(INDEX(rep_cogs,MATCH(D$5,rep_years_is,0)),0)*D6 -> 0.060769245 | E82: =IFERROR(INDEX(rep_cogs,MATCH(E$5,rep_years_is,0)),0)*E6 -> 0.095991847 | F82: =IFERROR(INDEX(rep_cogs,MATCH(F$5,rep_years_is,0)),0)*F6 -> 0.12822293 | G82: =IFERROR(INDEX(rep_cogs,MATCH(G$5,rep_years_is,0)),0)*G6 -> 0.1533593 | H82: =IFERROR(INDEX(rep_cogs,MATCH(H$5,rep_years_is,0)),0)*H6 -> 0.1589122 | I82: =IFERROR(INDEX(rep_cogs,MATCH(I$5,rep_years_is,0)),0)*I6 -> 0.19807459 | ... S82: =IFERROR(INDEX(rep_cogs,MATCH(S$5,rep_years_is,0)),0)*S6 -> 0.23000586
A83: Real gross profit | B83: =B81-B82 -> 0.017347393 | C83: =C81-C82 -> 0.026324097 | D83: =D81-D82 -> 0.039472884 | E83: =E81-E82 -> 0.065281786 | F83: =F81-F82 -> 0.10022133 | G83: =G81-G82 -> 0.092505267 | H83: =H81-H82 -> 0.099852034 | I83: =I81-I82 -> 0.13237964 | ... S83: =S81-S82 -> 0.20319232
A84: Real SG&A | B84: =IFERROR(INDEX(rep_sga,MATCH(B$5,rep_years_is,0)),0)*B6 -> 0.0058540643 | C84: =IFERROR(INDEX(rep_sga,MATCH(C$5,rep_years_is,0)),0)*C6 -> 0.0064810514 | D84: =IFERROR(INDEX(rep_sga,MATCH(D$5,rep_years_is,0)),0)*D6 -> 0.0084788935 | E84: =IFERROR(INDEX(rep_sga,MATCH(E$5,rep_years_is,0)),0)*E6 -> 0.01132129 | F84: =IFERROR(INDEX(rep_sga,MATCH(F$5,rep_years_is,0)),0)*F6 -> 0.013195083 | G84: =IFERROR(INDEX(rep_sga,MATCH(G$5,rep_years_is,0)),0)*G6 -> 0.013997205 | H84: =IFERROR(INDEX(rep_sga,MATCH(H$5,rep_years_is,0)),0)*H6 -> 0.016977266 | I84: =IFERROR(INDEX(rep_sga,MATCH(I$5,rep_years_is,0)),0)*I6 -> 0.020260055 | ... S84: =IFERROR(INDEX(rep_sga,MATCH(S$5,rep_years_is,0)),0)*S6 -> 0.028730955
A90: BUYBACK / REPURCHASE-PREMIUM ROE ADJUSTMENT (JK-original · premium-only)
A91: Additive capital-efficiency view only; never enters AEG value (Penman Ch.5/6). RNOA untouched. Reserve raises the economic-CSE base so ROE falls; cfg_buyback {On|Off}. VP6 proves value-invariance.
A92: cfg_buyback active (1=On) | B92: =IF(cfg_buyback="On",1,0) -> 1 | C92: =IF(cfg_buyback="On",1,0) -> 1 | D92: =IF(cfg_buyback="On",1,0) -> 1 | E92: =IF(cfg_buyback="On",1,0) -> 1 | F92: =IF(cfg_buyback="On",1,0) -> 1 | G92: =IF(cfg_buyback="On",1,0) -> 1 | H92: =IF(cfg_buyback="On",1,0) -> 1 | I92: =IF(cfg_buyback="On",1,0) -> 1 | ... S92: =IF(cfg_buyback="On",1,0) -> 1
A93: Year-end price (contemp.) | B93: =IFERROR(INDEX(md_yeprice,MATCH(B$5,md_years,0)),0) -> 177.5 | C93: =IFERROR(INDEX(md_yeprice,MATCH(C$5,md_years,0)),0) -> 185 | D93: =IFERROR(INDEX(md_yeprice,MATCH(D$5,md_years,0)),0) -> 192.5 | E93: =IFERROR(INDEX(md_yeprice,MATCH(E$5,md_years,0)),0) -> 200 | F93: =IFERROR(INDEX(md_yeprice,MATCH(F$5,md_years,0)),0) -> 207.5 | G93: =IFERROR(INDEX(md_yeprice,MATCH(G$5,md_years,0)),0) -> 215 | H93: =IFERROR(INDEX(md_yeprice,MATCH(H$5,md_years,0)),0) -> 222.5 | I93: =IFERROR(INDEX(md_yeprice,MATCH(I$5,md_years,0)),0) -> 230 | ... S93: =IFERROR(INDEX(md_yeprice,MATCH(S$5,md_years,0)),0) -> 305
A94: Market cap = adj. price x shares [split-consistent] | B94: =IF(IFERROR(INDEX(md_yeprice_adj,MATCH(B$5,md_years,0)),0)=0,B93*B19,INDEX(md_yeprice_adj,MATCH(B$5,md_years,0))*B19) -> 4.48365 | C94: =IF(IFERROR(INDEX(md_yeprice_adj,MATCH(C$5,md_years,0)),0)=0,C93*C19,INDEX(md_yeprice_adj,MATCH(C$5,md_years,0))*C19) -> 4.69826 | D94: =IF(IFERROR(INDEX(md_yeprice_adj,MATCH(D$5,md_years,0)),0)=0,D93*D19,INDEX(md_yeprice_adj,MATCH(D$5,md_years,0))*D19) -> 4.98421 | E94: =IF(IFERROR(INDEX(md_yeprice_adj,MATCH(E$5,md_years,0)),0)=0,E93*E19,INDEX(md_yeprice_adj,MATCH(E$5,md_years,0))*E19) -> 5.2452 | F94: =IF(IFERROR(INDEX(md_yeprice_adj,MATCH(F$5,md_years,0)),0)=0,F93*F19,INDEX(md_yeprice_adj,MATCH(F$5,md_years,0))*F19) -> 5.492525 | G94: =IF(IFERROR(INDEX(md_yeprice_adj,MATCH(G$5,md_years,0)),0)=0,G93*G19,INDEX(md_yeprice_adj,MATCH(G$5,md_years,0))*G19) -> 5.608705 | H94: =IF(IFERROR(INDEX(md_yeprice_adj,MATCH(H$5,md_years,0)),0)=0,H93*H19,INDEX(md_yeprice_adj,MATCH(H$5,md_years,0))*H19) -> 5.4492475 | I94: =IF(IFERROR(INDEX(md_yeprice_adj,MATCH(I$5,md_years,0)),0)=0,I93*I19,INDEX(md_yeprice_adj,MATCH(I$5,md_years,0))*I19) -> 5.32956 | ... S94: =IF(IFERROR(INDEX(md_yeprice_adj,MATCH(S$5,md_years,0)),0)=0,S93*S19,INDEX(md_yeprice_adj,MATCH(S$5,md_years,0))*S19) -> 4.576525
A95: Book/market = repCSE/mktcap | B95: =IF(B94=0,"",B18/B94) -> 0.004690375 | C95: =IF(C94=0,"",C18/C94) -> 0.0059238952 | D95: =IF(D94=0,"",D18/D94) -> 0.0095884804 | E95: =IF(E94=0,"",E18/E94) -> 0.014606688 | F95: =IF(F94=0,"",F18/F94) -> 0.021521978 | G95: =IF(G94=0,"",G18/G94) -> 0.02202808 | H95: =IF(H94=0,"",H18/H94) -> 0.020470166 | I95: =IF(I94=0,"",I18/I94) -> 0.022394907 | ... S95: =IF(S94=0,"",S18/S94) -> 0.016111132
A96: Premium fraction = 1−book/mkt | B96: =IF(B94=0,0,1-B18/B94) -> 0.99530962 | C96: =IF(C94=0,0,1-C18/C94) -> 0.9940761 | D96: =IF(D94=0,0,1-D18/D94) -> 0.99041152 | E96: =IF(E94=0,0,1-E18/E94) -> 0.98539331 | F96: =IF(F94=0,0,1-F18/F94) -> 0.97847802 | G96: =IF(G94=0,0,1-G18/G94) -> 0.97797192 | H96: =IF(H94=0,0,1-H18/H94) -> 0.97952983 | I96: =IF(I94=0,0,1-I18/I94) -> 0.97760509 | ... S96: =IF(S94=0,0,1-S18/S94) -> 0.98388887
A97: Buyback $ (nominal) | B97: =-B27 -> 0.000124 | C97: =-C27 -> 0.000475 | D97: =-D27 -> 0.000912 | E97: =-E27 -> 0.000831 | F97: =-F27 -> 0.000665 | G97: =-G27 -> 0.02286 | H97: =-H27 -> 0.045 | I97: =-I27 -> 0.035253 | ... S97: =-S27 -> 0.090711
A98: Annual premium reserve (real) | B98: =B92*B97*B96*B6 -> 0.00019210295 | C98: =C92*C97*C96*C6 -> 0.00073759043 | D98: =D92*D97*D96*D6 -> 0.001388183 | E98: =E92*E97*E96*E6 -> 0.0012199727 | F98: =F92*F97*F96*F6 -> 0.00094976557 | G98: =G92*G97*G96*G6 -> 0.032161114 | H98: =H92*H97*H96*H6 -> 0.06239792 | I98: =I92*I97*I96*I6 -> 0.048728638 | ... S98: =S92*S97*S96*S6 -> 0.092903323
A99: Cumulative premium reserve | B99: =B98 -> 0.00019210295 | C99: =B99+C98 -> 0.00092969339 | D99: =C99+D98 -> 0.0023178764 | E99: =D99+E98 -> 0.0035378491 | F99: =E99+F98 -> 0.0044876146 | G99: =F99+G98 -> 0.036648729 | H99: =G99+H98 -> 0.099046648 | I99: =H99+I98 -> 0.14777529 | J99: =I99+J98 -> 0.18825766 | ... S99: =R99+S98 -> 0.98812512
A100: Economic CSE (real) | B100: =B45 -> 0.03238281 | C100: =C45 -> 0.043267865 | D100: =D45 -> 0.072413717 | E100: =E45 -> 0.11320803 | F100: =F45 -> 0.16925721 | G100: =G45 -> 0.1806504 | H100: =H45 -> 0.16367898 | I100: =I45 -> 0.18101556 | ... S100: =S45 -> 0.092335272
A101: Adjusted base = CSE+reserve | B101: =B100+B99 -> 0.032574913 | C101: =C100+C99 -> 0.044197558 | D101: =D100+D99 -> 0.074731594 | E101: =E100+E99 -> 0.11674588 | F101: =F100+F99 -> 0.17374483 | G101: =G100+G99 -> 0.21729912 | H101: =H100+H99 -> 0.26272562 | I101: =I100+I99 -> 0.32879084 | ... S101: =S100+S99 -> 1.0804604
A102: Economic CI (real) | B102: =B56 -> 0.0058608556 | C102: =C56 -> 0.011499983 | D102: =D56 -> 0.02048292 | E102: =E56 -> 0.037339762 | F102: =F56 -> 0.058793615 | G102: =G56 -> 0.048838077 | H102: =H56 -> 0.052823609 | I102: =I56 -> 0.068743208 | ... S102: =S56 -> 0.1099114
A103: ROE unadjusted | C103: =IF((C100+B100)=0,"",C102/((C100+B100)/2)) -> 0.30402855 | D103: =IF((D100+C100)=0,"",D102/((D100+C100)/2)) -> 0.35412587 | E103: =IF((E100+D100)=0,"",E102/((E100+D100)/2)) -> 0.40232099 | F103: =IF((F100+E100)=0,"",F102/((F100+E100)/2)) -> 0.4162892 | G103: =IF((G100+F100)=0,"",G102/((G100+F100)/2)) -> 0.27914841 | H103: =IF((H100+G100)=0,"",H102/((H100+G100)/2)) -> 0.30682023 | I103: =IF((I100+H100)=0,"",I102/((I100+H100)/2)) -> 0.39886451 | J103: =IF((J100+I100)=0,"",J102/((J100+I100)/2)) -> 0.30022168 | ... S103: =IF((S100+R100)=0,"",S102/((S100+R100)/2)) -> 1.2829573
A104: ROE ADJUSTED (premium) | C104: =IF((C101+B101)=0,"",C102/((C101+B101)/2)) -> 0.2995861 | D104: =IF((D101+C101)=0,"",D102/((D101+C101)/2)) -> 0.34445584 | E104: =IF((E101+D101)=0,"",E102/((E101+D101)/2)) -> 0.39001729 | F104: =IF((F101+E101)=0,"",F102/((F101+E101)/2)) -> 0.40478827 | G104: =IF((G101+F101)=0,"",G102/((G101+F101)/2)) -> 0.24978306 | H104: =IF((H101+G101)=0,"",H102/((H101+G101)/2)) -> 0.22008702 | I104: =IF((I101+H101)=0,"",I102/((I101+H101)/2)) -> 0.23243041 | J104: =IF((J101+I101)=0,"",J102/((J101+I101)/2)) -> 0.1585592 | ... S104: =IF((S101+R101)=0,"",S102/((S101+R101)/2)) -> 0.10698599
A106: VP6 INVARIANCE — adjustment nets to zero in equity residual-income value
A107: flat real COE r (ρE_LR) | B107: =INDEX(finrate_coe,COLUMNS(finrate_coe)) -> 0.05
A108: DF_t = 1/(1+r)^(t−t0) | B108: =1/(1+$B$107)^(B5-$B$5) -> 1 | C108: =1/(1+$B$107)^(C5-$B$5) -> 0.95238095 | D108: =1/(1+$B$107)^(D5-$B$5) -> 0.90702948 | E108: =1/(1+$B$107)^(E5-$B$5) -> 0.8638376 | F108: =1/(1+$B$107)^(F5-$B$5) -> 0.82270247 | G108: =1/(1+$B$107)^(G5-$B$5) -> 0.78352617 | H108: =1/(1+$B$107)^(H5-$B$5) -> 0.7462154 | I108: =1/(1+$B$107)^(I5-$B$5) -> 0.71068133 | ... S108: =1/(1+$B$107)^(S5-$B$5) -> 0.43629669
A109: RI without = CI − r·CSE(prior) | C109: =C102-$B$107*B100 -> 0.0098808422 | D109: =D102-$B$107*C100 -> 0.018319527 | E109: =E102-$B$107*D100 -> 0.033719077 | F109: =F102-$B$107*E100 -> 0.053133213 | G109: =G102-$B$107*F100 -> 0.040375216 | H109: =H102-$B$107*G100 -> 0.043791089 | I109: =I102-$B$107*H100 -> 0.060559259 | J109: =J102-$B$107*I100 -> 0.047407875 | ... S109: =S102-$B$107*R100 -> 0.10596113
A110: RI with = (CI+Δres) − r·adjbase(prior) | C110: =(C102+(C99-B99))-$B$107*B101 -> 0.010608827 | D110: =(D102+(D99-C99))-$B$107*C101 -> 0.019661226 | E110: =(E102+(E99-D99))-$B$107*D101 -> 0.034823155 | F110: =(F102+(F99-E99))-$B$107*E101 -> 0.053906086 | G110: =(G102+(G99-F99))-$B$107*F101 -> 0.072311949 | H110: =(H102+(H99-G99))-$B$107*G101 -> 0.10435657 | I110: =(I102+(I99-H99))-$B$107*H101 -> 0.10433556 | J110: =(J102+(J99-I99))-$B$107*I101 -> 0.080501484 | ... S110: =(S102+(S99-R99))-$B$107*R101 -> 0.15410336
A112: V_without = CSE₀ + ΣPV(RI_wo) − DF_N·CSE_N | B112: =B100+SUMPRODUCT(C109:S109,C108:S108)-S108*S100 -> 0.61041683
A113: V_with = adjbase₀ + ΣPV(RI_w) − DF_N·adjbase_N | B113: =B101+SUMPRODUCT(C110:S110,C108:S108)-S108*S101 -> 0.61041683
A114: ★ VP6 tie = V_with − V_without | B114: =B113-B112 -> 0 | D114: =IF(ABS(B114)<in_tie_tol,"invariant ✓","BREAK") -> invariant ✓

Sheet Forecast
A1: FORECAST — merged cfg_mode engine (real spine 2026$; NOMINAL published series rows 39-47; cash tax on historical-cost depreciation)
A2: One dual-mode tab. REAL spine (rows 5-36) drives the build; rows 37-38 carry pi_t and the cumulative index; rows 39-47 publish the NOMINAL series consumed by Valuation and DCF Reconciliation. Rows 48-52/34-35 compute cash tax on historical-cost depreciation.
A3: cfg_mode: | B3: =cfg_mode -> Enterprise | C3: financing: | D3: =cfg_funding -> Target FLEV
A4: Period t (0 = last actual) | C4: =D4-1 -> -3 | D4: =E4-1 -> -2 | E4: =F4-1 -> -1 | F4: 0 | G4: =F4+1 -> 1 | H4: =G4+1 -> 2 | I4: =H4+1 -> 3 | J4: =I4+1 -> 4 | K4: =J4+1 -> 5 | L4: =K4+1 -> 6 | M4: =L4+1 -> 7 | N4: =M4+1 -> 8 | ... AJ4: =AI4+1 -> 30
A5: Fiscal year | C5: =TEXT(in_anchor_year+-3,"0") -> 2022 | D5: =TEXT(in_anchor_year+-2,"0") -> 2023 | E5: =TEXT(in_anchor_year+-1,"0") -> 2024 | F5: =TEXT(in_anchor_year+0,"0") -> 2025
A6: INCOME STATEMENT — build to EPS
A7: Revenue | C7: =INDEX(es_real_rev,MATCH(C$5,es_years,0)) -> 0.45155006 | D7: =INDEX(es_real_rev,MATCH(D$5,es_years,0)) -> 0.42155161 | E7: =INDEX(es_real_rev,MATCH(E$5,es_years,0)) -> 0.41775396 | F7: =anchor_rev0 -> 0.43319818 | G7: =F7*(1+G8) -> 0.44619413 | H7: =G7*(1+H8) -> 0.45957995 | I7: =H7*(1+I8) -> 0.47336735 | J7: =I7*(1+J8) -> 0.48756837 | K7: =J7*(1+K8) -> 0.50219542 | L7: =K7*(1+L8) -> 0.51726129 | M7: =L7*(1+M8) -> 0.53277912 | N7: =M7*(1+N8) -> 0.5487625 | ... AJ7: =AI7*(1+AJ8) -> 1.0514857
A8: real revenue growth | D8: =IF(C7=0,"",D7/C7-1) -> -0.066434378 | E8: =IF(D7=0,"",E7/D7-1) -> -0.0090087431 | F8: =IF(E7=0,"",F7/E7-1) -> 0.036969661 | G8: =INDEX(scen_revgrowth,MATCH(cfg_scenario,scen_cols,0)) -> 0.03 | H8: =INDEX(scen_revgrowth,MATCH(cfg_scenario,scen_cols,0)) -> 0.03 | I8: =INDEX(scen_revgrowth,MATCH(cfg_scenario,scen_cols,0)) -> 0.03 | J8: =INDEX(scen_revgrowth,MATCH(cfg_scenario,scen_cols,0)) -> 0.03 | K8: =INDEX(scen_revgrowth,MATCH(cfg_scenario,scen_cols,0)) -> 0.03 | L8: =INDEX(scen_revgrowth,MATCH(cfg_scenario,scen_cols,0)) -> 0.03 | M8: =INDEX(scen_revgrowth,MATCH(cfg_scenario,scen_cols,0)) -> 0.03 | N8: =INDEX(scen_revgrowth,MATCH(cfg_scenario,scen_cols,0)) -> 0.03 | ... AJ8: =INDEX(scen_revgrowth,MATCH(cfg_scenario,scen_cols,0)) -> 0.03
A9: Gross profit | C9: =INDEX(es_real_gp,MATCH(C$5,es_years,0)) -> 0.19556466 | D9: =INDEX(es_real_gp,MATCH(D$5,es_years,0)) -> 0.18603549 | E9: =INDEX(es_real_gp,MATCH(E$5,es_years,0)) -> 0.19302886 | F9: =anchor_gp0 -> 0.20319232 | G9: =G7*G10 -> 0.20928809 | H9: =H7*H10 -> 0.21556673 | I9: =I7*I10 -> 0.22203373 | J9: =J7*J10 -> 0.22869475 | K9: =K7*K10 -> 0.23555559 | L9: =L7*L10 -> 0.24262226 | M9: =M7*M10 -> 0.24990092 | N9: =N7*N10 -> 0.25739795 | ... AJ9: =AJ7*AJ10 -> 0.49320109
A10: gross margin | C10: =IF(C7=0,"",C9/C7) -> 0.43309631 | D10: =IF(D7=0,"",D9/D7) -> 0.4413113 | E10: =IF(E7=0,"",E9/E7) -> 0.4620635 | F10: =IF(F7=0,"",F9/F7) -> 0.46905164 | G10: =$F$10 -> 0.46905164 | H10: =$F$10 -> 0.46905164 | I10: =$F$10 -> 0.46905164 | J10: =$F$10 -> 0.46905164 | K10: =$F$10 -> 0.46905164 | L10: =$F$10 -> 0.46905164 | M10: =$F$10 -> 0.46905164 | N10: =$F$10 -> 0.46905164 | ... AJ10: =$F$10 -> 0.46905164
A11: SG&A | C11: =INDEX(es_real_sga,MATCH(C$5,es_years,0)) -> 0.028735462 | D11: =INDEX(es_real_sga,MATCH(D$5,es_years,0)) -> 0.027421174 | E11: =INDEX(es_real_sga,MATCH(E$5,es_years,0)) -> 0.027880177 | F11: =anchor_sga0 -> 0.028730955 | G11: =G7*G12 -> 0.029592884 | H11: =H7*H12 -> 0.03048067 | I11: =I7*I12 -> 0.031395091 | J11: =J7*J12 -> 0.032336943 | K11: =K7*K12 -> 0.033307052 | L11: =L7*L12 -> 0.034306263 | M11: =M7*M12 -> 0.035335451 | N11: =N7*N12 -> 0.036395515 | ... AJ11: =AJ7*AJ12 -> 0.069737569
A12: SG&A % of revenue | C12: =IF(C7=0,"",C11/C7) -> 0.063637378 | D12: =IF(D7=0,"",D11/D7) -> 0.065048202 | E12: =IF(E7=0,"",E11/E7) -> 0.066738272 | F12: =IF(F7=0,"",F11/F7) -> 0.066322889 | G12: =$F$12 -> 0.066322889 | H12: =$F$12 -> 0.066322889 | I12: =$F$12 -> 0.066322889 | J12: =$F$12 -> 0.066322889 | K12: =$F$12 -> 0.066322889 | L12: =$F$12 -> 0.066322889 | M12: =$F$12 -> 0.066322889 | N12: =$F$12 -> 0.066322889 | ... AJ12: =$F$12 -> 0.066322889
A13: D&A (economic depreciation) | C13: =INDEX(es_dep,MATCH(C$5,es_years,0)) -> 0.012969508 | D13: =INDEX(es_dep,MATCH(D$5,es_years,0)) -> 0.013122975 | E13: =INDEX(es_dep,MATCH(E$5,es_years,0)) -> 0.013126949 | F13: =anchor_econ_dep -> 0.013286613 | G13: =G14*F22 -> 0.013384331 | H13: =H14*G22 -> 0.013544679 | I13: =I14*H22 -> 0.01375769 | J13: =J14*I22 -> 0.01401545 | K13: =K14*J22 -> 0.01431169 | L13: =L14*K22 -> 0.014641465 | M13: =M14*L22 -> 0.01500089 | N13: =N14*M22 -> 0.015386935 | ... AJ13: =AJ14*AI22 -> 0.029054446
A14: depreciation rate (on prior PP&E) | D14: =IF(C22=0,"",D13/C22) -> 0.18575986 | E14: =IF(D22=0,"",E13/D22) -> 0.18821564 | F14: =IF(E22=0,"",F13/E22) -> 0.19841021 | G14: =$F$14 -> 0.19841021 | H14: =$F$14 -> 0.19841021 | I14: =$F$14 -> 0.19841021 | J14: =$F$14 -> 0.19841021 | K14: =$F$14 -> 0.19841021 | L14: =$F$14 -> 0.19841021 | M14: =$F$14 -> 0.19841021 | N14: =$F$14 -> 0.19841021 | ... AJ14: =$F$14 -> 0.19841021
A15: Operating income (EBIT) | C15: =C9-C11-C13 -> 0.15385969 | D15: =D9-D11-D13 -> 0.14549134 | E15: =E9-E11-E13 -> 0.15202173 | F15: ='Econ Statements'!$S$51 -> 0.13738721 | G15: =G9-G11-G13-G61 -> 0.14180971 | H15: =H9-H11-H13-H61 -> 0.14630518 | I15: =I9-I11-I13-I61 -> 0.15088767 | J15: =J9-J11-J13-J61 -> 0.15556927 | K15: =K9-K11-K13-K61 -> 0.16036057 | L15: =L9-L11-L13-L61 -> 0.16527096 | M15: =M9-M11-M13-M61 -> 0.17030891 | N15: =N9-N11-N13-N61 -> 0.17548216 | ... AJ15: =AJ9-AJ11-AJ13-AJ61 -> 0.33667048
A16: Operating income, after tax (OI) | C16: =C15*(1-C17) -> 0.1289275 | D16: =D15*(1-D17) -> 0.12407618 | E16: =E15*(1-E17) -> 0.11539787 | F16: =anchor_oi_at0 -> 0.11571047 | G16: =IF(G4<=cfg_N,(G15*(1-G17))-G35,G60*F24) -> 0.11942295 | H16: =IF(H4<=cfg_N,(H15*(1-H17))-H35,H60*G24) -> 0.12318414 | I16: =IF(I4<=cfg_N,(I15*(1-I17))-I35,I60*H24) -> 0.12703006 | J16: =IF(J4<=cfg_N,(J15*(1-J17))-J35,J60*I24) -> 0.13095391 | K16: =IF(K4<=cfg_N,(K15*(1-K17))-K35,K60*J24) -> 0.010407426 | L16: =IF(L4<=cfg_N,(L15*(1-L17))-L35,L60*K24) -> 0.010554729 | M16: =IF(M4<=cfg_N,(M15*(1-M17))-M35,M60*L24) -> 0.010680016 | N16: =IF(N4<=cfg_N,(N15*(1-N17))-N35,N60*M24) -> 0.010789266 | ... AJ16: =IF(AJ4<=cfg_N,(AJ15*(1-AJ17))-AJ35,AJ60*AI24) -> 0.015032681
A17: tax rate | C17: =IFERROR(INDEX(rep_taxrate,MATCH(C$5,rep_years_is,0)),0) -> 0.162045 | D17: =IFERROR(INDEX(rep_taxrate,MATCH(D$5,rep_years_is,0)),0) -> 0.147192 | E17: =IFERROR(INDEX(rep_taxrate,MATCH(E$5,rep_years_is,0)),0) -> 0.240912 | F17: =IFERROR(INDEX(rep_taxrate,MATCH(F$5,rep_years_is,0)),0) -> 0.1561 | G17: =$F$17 -> 0.1561 | H17: =$F$17 -> 0.1561 | I17: =$F$17 -> 0.1561 | J17: =$F$17 -> 0.1561 | K17: =$F$17 -> 0.1561 | L17: =$F$17 -> 0.1561 | M17: =$F$17 -> 0.1561 | N17: =$F$17 -> 0.1561 | ... AJ17: =$F$17 -> 0.1561
A18: Net financial expense (NFE) = ρD × prior NFO | C18: =INDEX(es_ni,MATCH(C$5,es_years,0))*0+INDEX(es_oiat,MATCH(C$5,es_years,0))-INDEX(es_ni,MATCH(C$5,es_years,0)) -> 0.0028124499 | D18: =INDEX(es_ni,MATCH(D$5,es_years,0))*0+INDEX(es_oiat,MATCH(D$5,es_years,0))-INDEX(es_ni,MATCH(D$5,es_years,0)) -> 0.0036889617 | E18: =INDEX(es_ni,MATCH(E$5,es_years,0))*0+INDEX(es_oiat,MATCH(E$5,es_years,0))-INDEX(es_ni,MATCH(E$5,es_years,0)) -> 0 | F18: =anchor_oi_at0-anchor_ni0 -> 0 | G18: =INDEX(finrate_cod,G4)*F25 -> 0.001166327 | H18: =INDEX(finrate_cod,H4)*G25 -> 0.0014562636 | I18: =INDEX(finrate_cod,I4)*H25 -> 0.001663021 | J18: =INDEX(finrate_cod,J4)*I25 -> 0.0018100456 | K18: =INDEX(finrate_cod,K4)*J25 -> 0.0019140205 | L18: =INDEX(finrate_cod,L4)*K25 -> 0.00198828 | M18: =INDEX(finrate_cod,M4)*L25 -> 0.0020421804 | N18: =INDEX(finrate_cod,N4)*M25 -> 0.0020818281 | ... AJ18: =INDEX(finrate_cod,AJ4)*AI25 -> 0.0055849015
A19: Net income (comprehensive) | C19: =INDEX(es_ni,MATCH(C$5,es_years,0)) -> 0.11134703 | D19: =INDEX(es_ni,MATCH(D$5,es_years,0)) -> 0.10291791 | E19: =INDEX(es_ni,MATCH(E$5,es_years,0)) -> 0.098887969 | F19: =anchor_ni0 -> 0.11571047 | G19: =G16-G18 -> 0.11825662 | H19: =H16-H18 -> 0.12172787 | I19: =I16-I18 -> 0.12536703 | J19: =J16-J18 -> 0.12914386 | K19: =K16-K18 -> 0.0084934053 | L19: =L16-L18 -> 0.0085664486 | M19: =M16-M18 -> 0.0086378357 | N19: =N16-N18 -> 0.0087074381 | ... AJ19: =AJ16-AJ18 -> 0.0094477792
A20: Shares outstanding (mm) | C20: =anchor_shares0 -> 0.015005 | D20: =anchor_shares0 -> 0.015005 | E20: =anchor_shares0 -> 0.015005 | F20: =anchor_shares0 -> 0.015005 | G20: =IF(cfg_mode="Enterprise",F20*(1-G21),F20) -> 0.01455485 | H20: =IF(cfg_mode="Enterprise",G20*(1-H21),G20) -> 0.014118205 | I20: =IF(cfg_mode="Enterprise",H20*(1-I21),H20) -> 0.013694658 | J20: =IF(cfg_mode="Enterprise",I20*(1-J21),I20) -> 0.013283819 | K20: =IF(cfg_mode="Enterprise",J20*(1-K21),J20) -> 0.012885304 | L20: =IF(cfg_mode="Enterprise",K20*(1-L21),K20) -> 0.012498745 | M20: =IF(cfg_mode="Enterprise",L20*(1-M21),L20) -> 0.012123783 | N20: =IF(cfg_mode="Enterprise",M20*(1-N21),M20) -> 0.011760069 | ... AJ20: =IF(cfg_mode="Enterprise",AI20*(1-AJ21),AI20) -> 0.0060171111
A21: net buyback rate [E-driver] | G21: =INDEX(scen_buyback,MATCH(cfg_scenario,scen_cols,0)) -> 0.03 | H21: =INDEX(scen_buyback,MATCH(cfg_scenario,scen_cols,0)) -> 0.03 | I21: =INDEX(scen_buyback,MATCH(cfg_scenario,scen_cols,0)) -> 0.03 | J21: =INDEX(scen_buyback,MATCH(cfg_scenario,scen_cols,0)) -> 0.03 | K21: =INDEX(scen_buyback,MATCH(cfg_scenario,scen_cols,0)) -> 0.03 | L21: =INDEX(scen_buyback,MATCH(cfg_scenario,scen_cols,0)) -> 0.03 | M21: =INDEX(scen_buyback,MATCH(cfg_scenario,scen_cols,0)) -> 0.03 | N21: =INDEX(scen_buyback,MATCH(cfg_scenario,scen_cols,0)) -> 0.03 | ... AJ21: =INDEX(scen_buyback,MATCH(cfg_scenario,scen_cols,0)) -> 0.03
A22: Net PP&E (within NOA) | C22: =INDEX(es_ppe,MATCH(C$5,es_years,0)) -> 0.070644834 | D22: =INDEX(es_ppe,MATCH(D$5,es_years,0)) -> 0.069744197 | E22: =INDEX(es_ppe,MATCH(E$5,es_years,0)) -> 0.066965366 | F22: =anchor_real_net_ppe -> 0.067457873 | G22: =F22+G23-G13 -> 0.068266036 | H22: =G22+H23-H13 -> 0.069339625 | I22: =H22+I23-I13 -> 0.070638752 | J22: =I22+J23-J13 -> 0.072131823 | K22: =J22+K23-K13 -> 0.073793909 | L22: =K22+L23-L13 -> 0.075605433 | M22: =L22+M23-M13 -> 0.077551123 | N22: =M22+N23-N13 -> 0.079619165 | ... AJ22: =AI22+AJ23-AJ13 -> 0.15082734
A23: capital expenditure | G23: =G36*G7 -> 0.014192494 | H23: =H36*H7 -> 0.014618268 | I23: =I36*I7 -> 0.015056816 | J23: =J36*J7 -> 0.015508521 | K23: =K36*K7 -> 0.015973777 | L23: =L36*L7 -> 0.01645299 | M23: =M36*M7 -> 0.01694658 | N23: =N36*N7 -> 0.017454977 | ... AJ23: =AJ36*AJ7 -> 0.033445541
A24: Net operating assets (NOA) | C24: =INDEX(es_noa,MATCH(C$5,es_years,0)) -> 0.16355013 | D24: =INDEX(es_noa,MATCH(D$5,es_years,0)) -> 0.14543838 | E24: =INDEX(es_noa,MATCH(E$5,es_years,0)) -> 0.13657554 | F24: =anchor_real_noa0 -> 0.15237663 | G24: =IF(cfg_mode="Enterprise",F24*(1+G50),G27+G25) -> 0.15618605 | H24: =IF(cfg_mode="Enterprise",G24*(1+H50),H27+H25) -> 0.1600907 | I24: =IF(cfg_mode="Enterprise",H24*(1+I50),I27+I25) -> 0.16409296 | J24: =IF(cfg_mode="Enterprise",I24*(1+J50),J27+J25) -> 0.16819529 | K24: =IF(cfg_mode="Enterprise",J24*(1+K50),K27+K25) -> 0.17240017 | L24: =IF(cfg_mode="Enterprise",K24*(1+L50),L27+L25) -> 0.17671017 | M24: =IF(cfg_mode="Enterprise",L24*(1+M50),M27+M25) -> 0.18112793 | N24: =IF(cfg_mode="Enterprise",M24*(1+N50),N27+N25) -> 0.18565613 | ... AJ24: =IF(cfg_mode="Enterprise",AI24*(1+AJ50),AJ27+AJ25) -> 0.31962028
A25: NFO (financed by) | C25: =INDEX(es_nfo,MATCH(C$5,es_years,0)) -> 0.083108855 | D25: =INDEX(es_nfo,MATCH(D$5,es_years,0)) -> 0.055423063 | E25: =INDEX(es_nfo,MATCH(E$5,es_years,0)) -> 0.057570104 | F25: =anchor_real_nfo0 -> 0.060041357 | G25: =IF(cfg_mode="Enterprise",IF(cfg_funding="Target FLEV",G24*G51/(1+G51),F25+G51*(G24-F24)),G51*G27) -> 0.061542391 | H25: =IF(cfg_mode="Enterprise",IF(cfg_funding="Target FLEV",H24*H51/(1+H51),G25+H51*(H24-G24)),H51*H27) -> 0.063080951 | I25: =IF(cfg_mode="Enterprise",IF(cfg_funding="Target FLEV",I24*I51/(1+I51),H25+I51*(I24-H24)),I51*I27) -> 0.064657975 | J25: =IF(cfg_mode="Enterprise",IF(cfg_funding="Target FLEV",J24*J51/(1+J51),I25+J51*(J24-I24)),J51*J27) -> 0.066274424 | K25: =IF(cfg_mode="Enterprise",IF(cfg_funding="Target FLEV",K24*K51/(1+K51),J25+K51*(K24-J24)),K51*K27) -> 0.067931285 | L25: =IF(cfg_mode="Enterprise",IF(cfg_funding="Target FLEV",L24*L51/(1+L51),K25+L51*(L24-K24)),L51*L27) -> 0.069629567 | M25: =IF(cfg_mode="Enterprise",IF(cfg_funding="Target FLEV",M24*M51/(1+M51),L25+M51*(M24-L24)),M51*M27) -> 0.071370306 | N25: =IF(cfg_mode="Enterprise",IF(cfg_funding="Target FLEV",N24*N51/(1+N51),M25+N51*(N24-M24)),N51*N27) -> 0.073154564 | ... AJ25: =IF(cfg_mode="Enterprise",IF(cfg_funding="Target FLEV",AJ24*AJ51/(1+AJ51),AI25+AJ51*(AJ24-AI24)),AJ51*AJ27) -> 0.1259408
A27: CSE = NOA − NFO (equity: clean-surplus roll) | C27: =INDEX(es_cse,MATCH(C$5,es_years,0)) -> 0.080441275 | D27: =INDEX(es_cse,MATCH(D$5,es_years,0)) -> 0.090015321 | E27: =INDEX(es_cse,MATCH(E$5,es_years,0)) -> 0.079005432 | F27: =anchor_real_cse0 -> 0.092335272 | G27: =IF(cfg_mode="Enterprise",G24-G25,F27+G19-G29*G20-G31) -> 0.094643654 | H27: =IF(cfg_mode="Enterprise",H24-H25,G27+H19-H29*H20-H31) -> 0.097009746 | I27: =IF(cfg_mode="Enterprise",I24-I25,H27+I19-I29*I20-I31) -> 0.099434989 | J27: =IF(cfg_mode="Enterprise",J24-J25,I27+J19-J29*J20-J31) -> 0.10192086 | K27: =IF(cfg_mode="Enterprise",K24-K25,J27+K19-K29*K20-K31) -> 0.10446889 | L27: =IF(cfg_mode="Enterprise",L24-L25,K27+L19-L29*L20-L31) -> 0.10708061 | M27: =IF(cfg_mode="Enterprise",M24-M25,L27+M19-M29*M20-M31) -> 0.10975762 | N27: =IF(cfg_mode="Enterprise",N24-N25,M27+N19-N29*N20-N31) -> 0.11250156 | ... AJ27: =IF(cfg_mode="Enterprise",AJ24-AJ25,AI27+AJ19-AJ29*AJ20-AJ31) -> 0.19367947
A28: FLEV target / funding policy δ [E-driver] | F28: =anchor_real_nfo0/anchor_real_cse0 -> 0.65025375
A29: Dividends per share (DPS) | F29: =anchor_dps0*INDEX(md_deflator,MATCH(in_anchor_year&"",md_years,0)) -> 0.99930137 | G29: =IF(cfg_mode="Enterprise",IF(G20=0,0,(G19-(G27-F27)-G31)/G20),in_payout_seed*G30) -> -2.1748101 | H29: =IF(cfg_mode="Enterprise",IF(H20=0,0,(H19-(H27-G27)-H31)/H20),in_payout_seed*H30) -> -2.2616582 | I29: =IF(cfg_mode="Enterprise",IF(I20=0,0,(I19-(I27-H27)-I31)/I20),in_payout_seed*I30) -> -2.3463785 | J29: =IF(cfg_mode="Enterprise",IF(J20=0,0,(J19-(J27-I27)-J31)/J20),in_payout_seed*J30) -> -2.4310421 | K29: =IF(cfg_mode="Enterprise",IF(K20=0,0,(K19-(K27-J27)-K31)/K20),in_payout_seed*K30) -> -12.182864 | L29: =IF(cfg_mode="Enterprise",IF(L20=0,0,(L19-(L27-K27)-L31)/L20),in_payout_seed*L30) -> -12.88479 | M29: =IF(cfg_mode="Enterprise",IF(M20=0,0,(M19-(M27-L27)-M31)/M20),in_payout_seed*M30) -> -13.627147 | N29: =IF(cfg_mode="Enterprise",IF(N20=0,0,(N19-(N27-M27)-N31)/N20),in_payout_seed*N30) -> -14.412264 | ... AJ29: =IF(cfg_mode="Enterprise",IF(AJ20=0,0,(AJ19-(AJ27-AI27)-AJ31)/AJ20),in_payout_seed*AJ30) -> -49.414162
A30: Earnings per share (EPS = NI ÷ shares) | C30: =IF(C20=0,"",C19/C20) -> 7.4206618 | D30: =IF(D20=0,"",D19/D20) -> 6.8589074 | E30: =IF(E20=0,"",E19/E20) -> 6.5903345 | F30: =IF(F20=0,"",F19/F20) -> 7.7114609 | G30: =G19/G20 -> 8.1248947 | H30: =H19/H20 -> 8.6220505 | I30: =I19/I20 -> 9.1544477 | J30: =J19/J20 -> 9.7218928 | K30: =K19/K20 -> 0.65915444 | L30: =L19/L20 -> 0.68538471 | M30: =M19/M20 -> 0.71247036 | N30: =N19/N20 -> 0.74042406 | ... AJ30: =AJ19/AJ20 -> 1.570152
A31: Share repurchases ($) = shares retired × price | F31: 0 | G31: =(F20-G20)*G32 -> 0.14760228 | H31: =(G20-H20)*H32 -> 0.15129233 | I31: =(H20-I20)*I32 -> 0.15507464 | J31: =(I20-J20)*J32 -> 0.15895151 | K31: =(J20-K20)*K32 -> 0.1629253 | L31: =(K20-L20)*L32 -> 0.16699843 | M31: =(L20-M20)*M32 -> 0.17117339 | N31: =(M20-N20)*N32 -> 0.17545272 | ... AJ31: =(AI20-AJ20)*AJ32 -> 0.30205439
A32: share price (constant P/B, off prior book) | F32: =in_price*INDEX(md_deflator,MATCH(in_anchor_year&"",md_years,0)) -> 327.89576 | G32: =$F$33*F27/F20 -> 327.89576 | H32: =$F$33*G27/G20 -> 346.48779 | I32: =$F$33*H27/H20 -> 366.134 | J32: =$F$33*I27/I20 -> 386.89418 | K32: =$F$33*J27/J20 -> 408.83148 | L32: =$F$33*K27/K20 -> 432.01264 | M32: =$F$33*L27/L20 -> 456.50821 | N32: =$F$33*M27/M20 -> 482.39269 | ... AJ32: =$F$33*AI27/AI20 -> 1623.1087
A33: constant P/B = real price0 / real book0 | F33: =$F$32/($F$27/$F$20) -> 53.284901
A34: depreciation tax penalty (nominal) = t x (econ - tax) dep <STAGE B1> | G34: =MAX(0,in_tax0*(G52-G49)) -> 0.00025776992 | H34: =MAX(0,in_tax0*(H52-H49)) -> 0.00029878564 | I34: =MAX(0,in_tax0*(I52-I49)) -> 0.00032862286 | J34: =MAX(0,in_tax0*(J52-J49)) -> 0.00036541137 | K34: =MAX(0,in_tax0*(K52-K49)) -> 0.0003541691 | L34: =MAX(0,in_tax0*(L52-L49)) -> 0.00028940341 | M34: =MAX(0,in_tax0*(M52-M49)) -> 0.00027572118 | N34: =MAX(0,in_tax0*(N52-N49)) -> 0.00025027364 | ... AJ34: =MAX(0,in_tax0*(AJ52-AJ49)) -> 0.00042991301
A35: depreciation tax penalty (real 2026$) -> charged to OI after tax <STAGE B1> | G35: =G34/G38 -> 0.000250264 | H35: =H34/H38 -> 0.00028280917 | I35: =I34/I38 -> 0.00030404883 | J35: =J34/J38 -> 0.00033100075 | K35: =K34/K38 -> 0.00031436422 | L35: =L34/L38 -> 0.00025180576 | M35: =M34/M38 -> 0.00023517825 | N35: =N34/N38 -> 0.00020923758 | ... AJ35: =AJ34/AJ38 -> 0.00021856599
A36: capex % of revenue [driver] | F36: =IF($F$7=0,"",($F$22-$E$22+$F$13)/$F$7) -> 0.03180789 | G36: =$F$36 -> 0.03180789 | H36: =$F$36 -> 0.03180789 | I36: =$F$36 -> 0.03180789 | J36: =$F$36 -> 0.03180789 | K36: =$F$36 -> 0.03180789 | L36: =$F$36 -> 0.03180789 | M36: =$F$36 -> 0.03180789 | N36: =$F$36 -> 0.03180789 | ... AJ36: =$F$36 -> 0.03180789
A37: pi_t expected inflation fwd [finrate_infl] <STAGE A> | G37: =INDEX(finrate_infl,G4) -> 0.029992 | H37: =INDEX(finrate_infl,H4) -> 0.025728421 | I37: =INDEX(finrate_infl,I4) -> 0.02302958 | J37: =INDEX(finrate_infl,J4) -> 0.021406581 | K37: =INDEX(finrate_infl,K4) -> 0.020526948 | L37: =INDEX(finrate_infl,L4) -> 0.020141491 | M37: =INDEX(finrate_infl,M4) -> 0.020081803 | N37: =INDEX(finrate_infl,N4) -> 0.020240218 | ... AJ37: =INDEX(finrate_infl,AJ4) -> 0.022777
A38: I_t cumulative inflation index (I_0=1) <STAGE A> | F38: 1 | G38: =F38*(1+G37) -> 1.029992 | H38: =G38*(1+H37) -> 1.0564921 | I38: =H38*(1+I37) -> 1.0808226 | J38: =I38*(1+J37) -> 1.1039594 | K38: =J38*(1+K37) -> 1.1266203 | L38: =K38*(1+L37) -> 1.1493121 | M38: =L38*(1+M37) -> 1.1723923 | N38: =M38*(1+N37) -> 1.1961218 | ... AJ38: =AI38*(1+AJ37) -> 1.9669712
A39: NOMINAL D&A (economic depreciation) <STAGE A> | G39: =G13*G38 -> 0.013785754 | H39: =H13*H38 -> 0.014309846 | I39: =I13*I38 -> 0.014869623 | J39: =J13*J38 -> 0.015472487 | K39: =K13*K38 -> 0.016123841 | L39: =L13*L38 -> 0.016827613 | M39: =M13*M38 -> 0.017586929 | N39: =N13*N38 -> 0.018404649 | ... AJ39: =AJ13*AJ38 -> 0.05714926
A40: NOMINAL Operating income, after tax (OI) <STAGE A> | G40: =G16*G38 -> 0.12300468 | H40: =H16*H38 -> 0.13014306 | I40: =I16*I38 -> 0.13729696 | J40: =J16*J38 -> 0.14456779 | K40: =K16*K38 -> 0.011725217 | L40: =L16*L38 -> 0.012130677 | M40: =M16*M38 -> 0.012521169 | N40: =N16*N38 -> 0.012905277 | ... AJ40: =AJ16*AJ38 -> 0.029568851
A41: NOMINAL Net income (comprehensive) <STAGE A> | G41: =G19*G38 -> 0.12180338 | H41: =H19*H38 -> 0.12860453 | I41: =I19*I38 -> 0.13549953 | J41: =J19*J38 -> 0.14256957 | K41: =K19*K38 -> 0.0095688426 | L41: =L19*L38 -> 0.0098455229 | M41: =M19*M38 -> 0.010126932 | N41: =N19*N38 -> 0.010415157 | ... AJ41: =AJ19*AJ38 -> 0.01858351
A42: NOMINAL capital expenditure <STAGE A> | G42: =G23*G38 -> 0.014618155 | H42: =H23*H38 -> 0.015444085 | I42: =I23*I38 -> 0.016273748 | J42: =J23*J38 -> 0.017120777 | K42: =K23*K38 -> 0.01799638 | L42: =L23*L38 -> 0.01890962 | M42: =M23*M38 -> 0.01986804 | N42: =N23*N38 -> 0.020878279 | ... AJ42: =AJ23*AJ38 -> 0.065786417
A43: NOMINAL Net operating assets (NOA) <STAGE A> | G43: =G24*G38 -> 0.16087038 | H43: =H24*H38 -> 0.16913455 | I43: =I24*I38 -> 0.17735539 | J43: =J24*J38 -> 0.18568076 | K43: =K24*K38 -> 0.19422953 | L43: =L24*L38 -> 0.20309514 | M43: =M24*M38 -> 0.212353 | N43: =N24*N38 -> 0.22206734 | ... AJ43: =AJ24*AJ38 -> 0.6286839
A44: NOMINAL NFO (financed by) <STAGE A> | G44: =G25*G38 -> 0.06338817 | H44: =H25*H38 -> 0.066644524 | I44: =I25*I38 -> 0.069883803 | J44: =J25*J38 -> 0.07316427 | K44: =K25*K38 -> 0.076532762 | L44: =L25*L38 -> 0.080026102 | M44: =M25*M38 -> 0.083674 | N44: =N25*N38 -> 0.08750177 | ... AJ44: =AJ25*AJ38 -> 0.24772194
A45: NOMINAL CSE = NOA − NFO (equity: clean-surplus roll) <STAGE A> | G45: =G27*G38 -> 0.097482207 | H45: =H27*H38 -> 0.10249003 | I45: =I27*I38 -> 0.10747159 | J45: =J27*J38 -> 0.11251649 | K45: =K27*K38 -> 0.11769676 | L45: =L27*L38 -> 0.12306904 | M45: =M27*M38 -> 0.128679 | N45: =N27*N38 -> 0.13456557 | ... AJ45: =AJ27*AJ38 -> 0.38096196
A46: NOMINAL Dividends per share (DPS) <STAGE A> | G46: =G29*G38 -> -2.240037 | H46: =H29*H38 -> -2.3894239 | I46: =I29*I38 -> -2.536019 | J46: =J29*J38 -> -2.6837717 | K46: =K29*K38 -> -13.725462 | L46: =L29*L38 -> -14.808645 | M46: =M29*M38 -> -15.976363 | N46: =N29*N38 -> -17.238824 | ... AJ46: =AJ29*AJ38 -> -97.196236
A47: NOMINAL Earnings per share (EPS = NI ÷ shares) <STAGE A> | G47: =G30*G38 -> 8.3685766 | H47: =H30*H38 -> 9.109128 | I47: =I30*I38 -> 9.8943344 | J47: =J30*J38 -> 10.732575 | K47: =K30*K38 -> 0.74261675 | L47: =L30*L38 -> 0.78772092 | M47: =M30*M38 -> 0.83529479 | N47: =N30*N38 -> 0.88563737 | ... AJ47: =AJ30*AJ38 -> 3.0884439
A48: legacy nominal live gross PP&E(t) [tax basis, pre-anchor vintages] <STAGE B1> | G48: =SUMPRODUCT('Cap Engine'!$B$7:$B$43*('Cap Engine'!$J$7:$J$43<=(in_anchor_year+G4))*(((in_anchor_year+G4)-'Cap Engine'!$J$7:$J$43)<in_ppe_life)) -> 0.111216 | H48: =SUMPRODUCT('Cap Engine'!$B$7:$B$43*('Cap Engine'!$J$7:$J$43<=(in_anchor_year+H4))*(((in_anchor_year+H4)-'Cap Engine'!$J$7:$J$43)<in_ppe_life)) -> 0.098482 | I48: =SUMPRODUCT('Cap Engine'!$B$7:$B$43*('Cap Engine'!$J$7:$J$43<=(in_anchor_year+I4))*(((in_anchor_year+I4)-'Cap Engine'!$J$7:$J$43)<in_ppe_life)) -> 0.086031 | J48: =SUMPRODUCT('Cap Engine'!$B$7:$B$43*('Cap Engine'!$J$7:$J$43<=(in_anchor_year+J4))*(((in_anchor_year+J4)-'Cap Engine'!$J$7:$J$43)<in_ppe_life)) -> 0.072718 | K48: =SUMPRODUCT('Cap Engine'!$B$7:$B$43*('Cap Engine'!$J$7:$J$43<=(in_anchor_year+K4))*(((in_anchor_year+K4)-'Cap Engine'!$J$7:$J$43)<in_ppe_life)) -> 0.062223 | L48: =SUMPRODUCT('Cap Engine'!$B$7:$B$43*('Cap Engine'!$J$7:$J$43<=(in_anchor_year+L4))*(((in_anchor_year+L4)-'Cap Engine'!$J$7:$J$43)<in_ppe_life)) -> 0.054914 | M48: =SUMPRODUCT('Cap Engine'!$B$7:$B$43*('Cap Engine'!$J$7:$J$43<=(in_anchor_year+M4))*(((in_anchor_year+M4)-'Cap Engine'!$J$7:$J$43)<in_ppe_life)) -> 0.043829 | N48: =SUMPRODUCT('Cap Engine'!$B$7:$B$43*('Cap Engine'!$J$7:$J$43<=(in_anchor_year+N4))*(((in_anchor_year+N4)-'Cap Engine'!$J$7:$J$43)<in_ppe_life)) -> 0.033121 | ... AJ48: =SUMPRODUCT('Cap Engine'!$B$7:$B$43*('Cap Engine'!$J$7:$J$43<=(in_anchor_year+AJ4))*(((in_anchor_year+AJ4)-'Cap Engine'!$J$7:$J$43)<in_ppe_life)) -> 0
A49: TAX depreciation (nominal, historical cost) <STAGE B1> | G49: =G48/in_ppe_life+SUMPRODUCT(($G$4:G4>G4-in_ppe_life)*$G$23:G23*$G$38:G38)/in_ppe_life -> 0.012134441 | H49: =H48/in_ppe_life+SUMPRODUCT(($G$4:H4>H4-in_ppe_life)*$G$23:H23*$G$38:H38)/in_ppe_life -> 0.01239578 | I49: =I48/in_ppe_life+SUMPRODUCT(($G$4:I4>I4-in_ppe_life)*$G$23:I23*$G$38:I38)/in_ppe_life -> 0.012764415 | J49: =J48/in_ppe_life+SUMPRODUCT(($G$4:J4>J4-in_ppe_life)*$G$23:J23*$G$38:J38)/in_ppe_life -> 0.013131607 | K49: =K48/in_ppe_life+SUMPRODUCT(($G$4:K4>K4-in_ppe_life)*$G$23:K23*$G$38:K38)/in_ppe_life -> 0.01385498 | L49: =L48/in_ppe_life+SUMPRODUCT(($G$4:L4>L4-in_ppe_life)*$G$23:L23*$G$38:L38)/in_ppe_life -> 0.014973651 | M49: =M48/in_ppe_life+SUMPRODUCT(($G$4:M4>M4-in_ppe_life)*$G$23:M23*$G$38:M38)/in_ppe_life -> 0.015820618 | N49: =N48/in_ppe_life+SUMPRODUCT(($G$4:N4>N4-in_ppe_life)*$G$23:N23*$G$38:N38)/in_ppe_life -> 0.016801358 | ... AJ49: =AJ48/in_ppe_life+SUMPRODUCT(($G$4:AJ4>AJ4-in_ppe_life)*$G$23:AJ23*$G$38:AJ38)/in_ppe_life -> 0.054395173
A50: NOA growth (real) [E-driver] | G50: =INDEX(scen_noagrowth,MATCH(cfg_scenario,scen_cols,0)) -> 0.025 | H50: =INDEX(scen_noagrowth,MATCH(cfg_scenario,scen_cols,0)) -> 0.025 | I50: =INDEX(scen_noagrowth,MATCH(cfg_scenario,scen_cols,0)) -> 0.025 | J50: =INDEX(scen_noagrowth,MATCH(cfg_scenario,scen_cols,0)) -> 0.025 | K50: =INDEX(scen_noagrowth,MATCH(cfg_scenario,scen_cols,0)) -> 0.025 | L50: =INDEX(scen_noagrowth,MATCH(cfg_scenario,scen_cols,0)) -> 0.025 | M50: =INDEX(scen_noagrowth,MATCH(cfg_scenario,scen_cols,0)) -> 0.025 | N50: =INDEX(scen_noagrowth,MATCH(cfg_scenario,scen_cols,0)) -> 0.025 | ... AJ50: =INDEX(scen_noagrowth,MATCH(cfg_scenario,scen_cols,0)) -> 0.025
A51: FLEV target (or δ) [driver] | F51: =anchor_real_nfo0/anchor_real_cse0 -> 0.65025375 | G51: =$F$51 -> 0.65025375 | H51: =$F$51 -> 0.65025375 | I51: =$F$51 -> 0.65025375 | J51: =$F$51 -> 0.65025375 | K51: =$F$51 -> 0.65025375 | L51: =$F$51 -> 0.65025375 | M51: =$F$51 -> 0.65025375 | N51: =$F$51 -> 0.65025375 | ... AJ51: =$F$51 -> 0.65025375
A52: economic depreciation (nominal, current cost) <STAGE B1> | G52: =G13*G38 -> 0.013785754 | H52: =H13*H38 -> 0.014309846 | I52: =I13*I38 -> 0.014869623 | J52: =J13*J38 -> 0.015472487 | K52: =K13*K38 -> 0.016123841 | L52: =L13*L38 -> 0.016827613 | M52: =M13*M38 -> 0.017586929 | N52: =N13*N38 -> 0.018404649 | ... AJ52: =AJ13*AJ38 -> 0.05714926
A53: DuPont & Identity checks
A54: RNOA = OI ÷ prior NOA | G54: =IF(F24=0,"",G16/F24) -> 0.78373535 | H54: =IF(G24=0,"",H16/G24) -> 0.78870129 | I54: =IF(H24=0,"",I16/H24) -> 0.79348806 | J54: =IF(I24=0,"",J16/I24) -> 0.79804705 | K54: =IF(J24=0,"",K16/J24) -> 0.061877036 | L54: =IF(K24=0,"",L16/K24) -> 0.061222263 | M54: =IF(L24=0,"",M16/L24) -> 0.060438037 | N54: =IF(M24=0,"",N16/M24) -> 0.059567104 | ... AJ54: =IF(AI24=0,"",AJ16/AI24) -> 0.048208762
A55: FLEV = NFO ÷ CSE | F55: =IF(F27=0,"",F25/F27) -> 0.65025375 | G55: =IF(G27=0,"",G25/G27) -> 0.65025375 | H55: =IF(H27=0,"",H25/H27) -> 0.65025375 | I55: =IF(I27=0,"",I25/I27) -> 0.65025375 | J55: =IF(J27=0,"",J25/J27) -> 0.65025375 | K55: =IF(K27=0,"",K25/K27) -> 0.65025375 | L55: =IF(L27=0,"",L25/L27) -> 0.65025375 | M55: =IF(M27=0,"",M25/M27) -> 0.65025375 | ... AJ55: =IF(AJ27=0,"",AJ25/AJ27) -> 0.65025375
A56: tie: NOA − NFO − CSE | F56: =F24-F25-F27 -> 0 | G56: =G24-G25-G27 -> 0 | H56: =H24-H25-H27 -> 0 | I56: =I24-I25-I27 -> 0 | J56: =J24-J25-J27 -> 0 | K56: =K24-K25-K27 -> 0 | L56: =L24-L25-L27 -> 0 | M56: =M24-M25-M27 -> 0 | ... AJ56: =AJ24-AJ25-AJ27 -> 0
A57: tie: EPS×shares − NI | G57: =G30*G20-G19 -> 0 | H57: =H30*H20-H19 -> 0 | I57: =I30*I20-I19 -> 0 | J57: =J30*J20-J19 -> 0 | K57: =K30*K20-K19 -> 0 | L57: =L30*L20-L19 -> 0 | M57: =M30*M20-M19 -> 0 | N57: =N30*N20-N19 -> 0 | ... AJ57: =AJ30*AJ20-AJ19 -> 0
A58: tie: FCFE − total distribution | G58: =(G16-(G24-F24)-G18+(G25-F25))-(G29*G20+G31) -> 0 | H58: =(H16-(H24-G24)-H18+(H25-G25))-(H29*H20+H31) -> 0 | I58: =(I16-(I24-H24)-I18+(I25-H25))-(I29*I20+I31) -> 0 | J58: =(J16-(J24-I24)-J18+(J25-I25))-(J29*J20+J31) -> 0 | K58: =(K16-(K24-J24)-K18+(K25-J25))-(K29*K20+K31) -> 0 | L58: =(L16-(L24-K24)-L18+(L25-K25))-(L29*L20+L31) -> 0 | M58: =(M16-(M24-L24)-M18+(M25-L25))-(M29*M20+M31) -> 0 | N58: =(N16-(N24-M24)-N18+(N25-M25))-(N29*N20+N31) -> 0 | ... AJ58: =(AJ16-(AJ24-AI24)-AJ18+(AJ25-AI25))-(AJ29*AJ20+AJ31) -> 0
B60: rF_t (leverage-implied, normal-fill charge) | G60: =(INDEX(finrate_coe,G4)+F55*INDEX(finrate_cod,G4))/(1+F55) -> 0.061383349 | H60: =(INDEX(finrate_coe,H4)+G55*INDEX(finrate_cod,H4))/(1+G55) -> 0.062245058 | I60: =(INDEX(finrate_coe,I4)+H55*INDEX(finrate_cod,I4))/(1+H55) -> 0.062501191 | J60: =(INDEX(finrate_coe,J4)+I55*INDEX(finrate_cod,J4))/(1+I55) -> 0.062335852 | K60: =(INDEX(finrate_coe,K4)+J55*INDEX(finrate_cod,K4))/(1+J55) -> 0.061877036 | L60: =(INDEX(finrate_coe,L4)+K55*INDEX(finrate_cod,L4))/(1+K55) -> 0.061222263 | M60: =(INDEX(finrate_coe,M4)+L55*INDEX(finrate_cod,M4))/(1+L55) -> 0.060438037 | N60: =(INDEX(finrate_coe,N4)+M55*INDEX(finrate_cod,N4))/(1+M55) -> 0.059567104 | ... AJ60: =(INDEX(finrate_coe,AJ4)+AI55*INDEX(finrate_cod,AJ4))/(1+AI55) -> 0.048208762
B61: R&D econ charge (real; reconciles fwd EBIT to OI anchor) | F61: =(F9-F11-F13)-F15 -> 0.023787536 | G61: =$F$61*G7/$F$7 -> 0.024501162 | H61: =$F$61*H7/$F$7 -> 0.025236197 | I61: =$F$61*I7/$F$7 -> 0.025993283 | J61: =$F$61*J7/$F$7 -> 0.026773082 | K61: =$F$61*K7/$F$7 -> 0.027576274 | L61: =$F$61*L7/$F$7 -> 0.028403562 | M61: =$F$61*M7/$F$7 -> 0.029255669 | N61: =$F$61*N7/$F$7 -> 0.030133339 | ... AJ61: =$F$61*AJ7/$F$7 -> 0.057738594

Sheet Valuation
A1: VALUATION — AEG equity decomposition · NOMINAL forecast, nominal discounting, real-rate capitalisation, curve-implied annuity factors (value in 2026$/sh)
A2: Equity: AEG on forecast EPS/DPS at ρE (finrate_coe). Financing at ρD (finrate_cod), constant structure. ρF leverage-implied → V(OI)−V(NFE)=V(EPS) as an identity. cfg_valread picks the read; tie proves agreement.
A4: Period t (0 = anchor) | B4: 0 | C4: 1 | D4: 2 | E4: 3 | F4: 4 | G4: 5 | H4: 6 | I4: 7 | J4: 8 | K4: 9 | L4: 10 | M4: 11 | N4: 12 | O4: 13 | P4: 14 | Q4: 15 | R4: 16 | S4: 17 | T4: 18 | U4: 19 | V4: 20 | W4: 21 | X4: 22 | Y4: 23 | Z4: 24 | AA4: 25 | AB4: 26 | AC4: 27 | AD4: 28 | AE4: 29 | AF4: 30
A5: rhoE (NOMINAL per-year = Fisher(finrate_coe, finrate_infl)) | C5: =(1+INDEX(finrate_coe,C4))*(1+C56)-1 -> 0.12131796 | D5: =(1+INDEX(finrate_coe,D4))*(1+D56)-1 -> 0.1153087 | E5: =(1+INDEX(finrate_coe,E4))*(1+E56)-1 -> 0.11101012 | F5: =(1+INDEX(finrate_coe,F4))*(1+F56)-1 -> 0.10788567 | G5: =(1+INDEX(finrate_coe,G4))*(1+G56)-1 -> 0.10557086 | H5: =(1+INDEX(finrate_coe,H4))*(1+H56)-1 -> 0.10379309 | I5: =(1+INDEX(finrate_coe,I4))*(1+I56)-1 -> 0.1023684 | J5: =(1+INDEX(finrate_coe,J4))*(1+J56)-1 -> 0.10117928 | ... AF5: =(1+INDEX(finrate_coe,AF4))*(1+AF56)-1 -> 0.07391585
A6: rhoD (NOMINAL per-year = Fisher(finrate_cod, finrate_infl)) | C6: =(1+INDEX(finrate_cod,C4))*(1+C56)-1 -> 0.05 | D6: =(1+INDEX(finrate_cod,D4))*(1+D56)-1 -> 0.05 | E6: =(1+INDEX(finrate_cod,E4))*(1+E56)-1 -> 0.05 | F6: =(1+INDEX(finrate_cod,F4))*(1+F56)-1 -> 0.05 | G6: =(1+INDEX(finrate_cod,G4))*(1+G56)-1 -> 0.05 | H6: =(1+INDEX(finrate_cod,H4))*(1+H56)-1 -> 0.05 | I6: =(1+INDEX(finrate_cod,I4))*(1+I56)-1 -> 0.05 | J6: =(1+INDEX(finrate_cod,J4))*(1+J56)-1 -> 0.05 | ... AF6: =(1+INDEX(finrate_cod,AF4))*(1+AF56)-1 -> 0.069266394
A7: EPS/sh (real) — per ANCHOR share in Enterprise mode | B7: =anchor_ni0/anchor_shares0 -> 7.7114609 | C7: =IF(cfg_mode="Enterprise",INDEX(fc_ni,C4)/anchor_shares0,INDEX(fc_eps,C4)) -> 8.1175193 | D7: =IF(cfg_mode="Enterprise",INDEX(fc_ni,D4)/anchor_shares0,INDEX(fc_eps,D4)) -> 8.5707785 | E7: =IF(cfg_mode="Enterprise",INDEX(fc_ni,E4)/anchor_shares0,INDEX(fc_eps,E4)) -> 9.0302918 | F7: =IF(cfg_mode="Enterprise",INDEX(fc_ni,F4)/anchor_shares0,INDEX(fc_eps,F4)) -> 9.5014711 | G7: =IF(cfg_mode="Enterprise",INDEX(fc_ni,G4)/anchor_shares0,INDEX(fc_eps,G4)) -> 0.63771027 | H7: =IF(cfg_mode="Enterprise",INDEX(fc_ni,H4)/anchor_shares0,INDEX(fc_eps,H4)) -> 0.65614948 | I7: =IF(cfg_mode="Enterprise",INDEX(fc_ni,I4)/anchor_shares0,INDEX(fc_eps,I4)) -> 0.67490386 | J7: =IF(cfg_mode="Enterprise",INDEX(fc_ni,J4)/anchor_shares0,INDEX(fc_eps,J4)) -> 0.69411241 | ... AF7: =IF(cfg_mode="Enterprise",INDEX(fc_ni,AF4)/anchor_shares0,INDEX(fc_eps,AF4)) -> 1.2384878
A8: DPS/sh (real) — TOTAL distribution (divs+buybacks) per ANCHOR share in Enterprise mode | B8: =anchor_dps0*INDEX(md_deflator,MATCH(in_anchor_year&"",md_years,0)) -> 0.99930137 | C8: =IF(cfg_mode="Enterprise",C7-(C71-(1+C56)*B71),INDEX(fc_dps,C4)) -> 7.9590645 | D8: =IF(cfg_mode="Enterprise",D7-(D71-(1+D56)*C71),INDEX(fc_dps,D4)) -> 8.4041836 | E8: =IF(cfg_mode="Enterprise",E7-(E71-(1+E56)*D71),INDEX(fc_dps,E4)) -> 8.8555995 | F8: =IF(cfg_mode="Enterprise",F7-(F71-(1+F56)*E71),INDEX(fc_dps,F4)) -> 9.3185784 | G8: =IF(cfg_mode="Enterprise",G7-(G71-(1+G56)*F71),INDEX(fc_dps,G4)) -> 0.44639719 | H8: =IF(cfg_mode="Enterprise",H7-(H71-(1+H56)*G71),INDEX(fc_dps,H4)) -> 0.45610391 | I8: =IF(cfg_mode="Enterprise",I7-(I71-(1+I56)*H71),INDEX(fc_dps,I4)) -> 0.46573944 | J8: =IF(cfg_mode="Enterprise",J7-(J71-(1+J56)*I71),INDEX(fc_dps,J4)) -> 0.47537951 | ... AF8: =IF(cfg_mode="Enterprise",AF7-(AF71-(1+AF56)*AE71),INDEX(fc_dps,AF4)) -> 0.61924392
A9: retained/sh = EPS − DPS | B9: =B7-B8 -> 6.7121595 | C9: =C7-C8 -> 0.15845484 | D9: =D7-D8 -> 0.16659492 | E9: =E7-E8 -> 0.17469232 | F9: =F7-F8 -> 0.18289268 | G9: =G7-G8 -> 0.19131308 | H9: =H7-H8 -> 0.20004557 | I9: =I7-I8 -> 0.20916442 | ... AF9: =AF7-AF8 -> 0.61924392
A10: BPS/sh (book, clean surplus) — per ANCHOR share in Enterprise mode | B10: =anchor_real_cse0/anchor_shares0 -> 6.1536336 | C10: =IF(cfg_mode="Enterprise",C71,(1+C56)*B10+C9) -> 6.4966482 | D10: =IF(cfg_mode="Enterprise",D71,(1+D56)*C10+D9) -> 6.8303917 | E10: =IF(cfg_mode="Enterprise",E71,(1+E56)*D10+E9) -> 7.162385 | F10: =IF(cfg_mode="Enterprise",F71,(1+F56)*E10+F9) -> 7.4985999 | G10: =IF(cfg_mode="Enterprise",G71,(1+G56)*F10+G9) -> 7.8438363 | H10: =IF(cfg_mode="Enterprise",H71,(1+H56)*G10+H9) -> 8.2018685 | I10: =IF(cfg_mode="Enterprise",I71,(1+I56)*H10+I9) -> 8.5757412 | J10: =IF(cfg_mode="Enterprise",J71,(1+J56)*I10+J9) -> 8.968049 | ... AF10: =IF(cfg_mode="Enterprise",AF71,(1+AF56)*AE10+AF9) -> 25.389001
A11: NFO/sh — live forecast financing path (per ANCHOR share in Enterprise mode) <P4> | B11: =anchor_real_nfo0/anchor_shares0 -> 4.0014233 | C11: =IF(cfg_mode="Enterprise",INDEX(fc_nfo,C4)/anchor_shares0,INDEX(fc_nfo,C4)/INDEX(fc_shares,C4)) -> 4.2244699 | D11: =IF(cfg_mode="Enterprise",INDEX(fc_nfo,D4)/anchor_shares0,INDEX(fc_nfo,D4)/INDEX(fc_shares,D4)) -> 4.4414878 | E11: =IF(cfg_mode="Enterprise",INDEX(fc_nfo,E4)/anchor_shares0,INDEX(fc_nfo,E4)/INDEX(fc_shares,E4)) -> 4.6573677 | F11: =IF(cfg_mode="Enterprise",INDEX(fc_nfo,F4)/anchor_shares0,INDEX(fc_nfo,F4)/INDEX(fc_shares,F4)) -> 4.8759927 | G11: =IF(cfg_mode="Enterprise",INDEX(fc_nfo,G4)/anchor_shares0,INDEX(fc_nfo,G4)/INDEX(fc_shares,G4)) -> 5.100484 | H11: =IF(cfg_mode="Enterprise",INDEX(fc_nfo,H4)/anchor_shares0,INDEX(fc_nfo,H4)/INDEX(fc_shares,H4)) -> 5.3332957 | I11: =IF(cfg_mode="Enterprise",INDEX(fc_nfo,I4)/anchor_shares0,INDEX(fc_nfo,I4)/INDEX(fc_shares,I4)) -> 5.5764079 | J11: =IF(cfg_mode="Enterprise",INDEX(fc_nfo,J4)/anchor_shares0,INDEX(fc_nfo,J4)/INDEX(fc_shares,J4)) -> 5.8315075 | ... AF11: =IF(cfg_mode="Enterprise",INDEX(fc_nfo,AF4)/anchor_shares0,INDEX(fc_nfo,AF4)/INDEX(fc_shares,AF4)) -> 16.509293
A12: NFE/sh = ρD × NFO/sh | B12: 0 | C12: =C6*C11 -> 0.21122349 | D12: =D6*D11 -> 0.22207439 | E12: =E6*E11 -> 0.23286839 | F12: =F6*F11 -> 0.24379963 | G12: =G6*G11 -> 0.2550242 | H12: =H6*H11 -> 0.26666479 | I12: =I6*I11 -> 0.27882039 | J12: =J6*J11 -> 0.29157537 | ... AF12: =AF6*AF11 -> 1.1435392
A13: OI/sh = EPS + NFE | B13: =B7+B12 -> 7.7114609 | C13: =C7+C12 -> 8.3287428 | D13: =D7+D12 -> 8.7928529 | E13: =E7+E12 -> 9.2631602 | F13: =F7+F12 -> 9.7452707 | G13: =G7+G12 -> 0.89273447 | H13: =H7+H12 -> 0.92281426 | I13: =I7+I12 -> 0.95372425 | ... AF13: =AF7+AF12 -> 2.382027
A14: FLEV = NFO/sh ÷ BPS | B14: =IF(B10=0,"",B11/B10) -> 0.65025375 | C14: =IF(C10=0,"",C11/C10) -> 0.65025375 | D14: =IF(D10=0,"",D11/D10) -> 0.65025375 | E14: =IF(E10=0,"",E11/E10) -> 0.65025375 | F14: =IF(F10=0,"",F11/F10) -> 0.65025375 | G14: =IF(G10=0,"",G11/G10) -> 0.65025375 | H14: =IF(H10=0,"",H11/H10) -> 0.65025375 | I14: =IF(I10=0,"",I11/I10) -> 0.65025375 | ... AF14: =IF(AF10=0,"",AF11/AF10) -> 0.65025375
A15: ρF = (ρE + FLEV·ρD)/(1+FLEV) [levering identity] | C15: =IF(cfg_rf_mode="Single",(1+in_rf_single)*(1+C56)-1,(C5+C14*C6)/(1+C14)) -> 0.093216358 | D15: =IF(cfg_rf_mode="Single",(1+in_rf_single)*(1+D56)-1,(D5+D14*D6)/(1+D14)) -> 0.089574946 | E15: =IF(cfg_rf_mode="Single",(1+in_rf_single)*(1+E56)-1,(E5+E14*E6)/(1+E14)) -> 0.086970147 | F15: =IF(cfg_rf_mode="Single",(1+in_rf_single)*(1+F56)-1,(F5+F14*F6)/(1+F14)) -> 0.085076831 | G15: =IF(cfg_rf_mode="Single",(1+in_rf_single)*(1+G56)-1,(G5+G14*G6)/(1+G14)) -> 0.083674131 | H15: =IF(cfg_rf_mode="Single",(1+in_rf_single)*(1+H56)-1,(H5+H14*H6)/(1+H14)) -> 0.082596862 | I15: =IF(cfg_rf_mode="Single",(1+in_rf_single)*(1+I56)-1,(I5+I14*I6)/(1+I14)) -> 0.081733545 | J15: =IF(cfg_rf_mode="Single",(1+in_rf_single)*(1+J56)-1,(J5+J14*J6)/(1+J14)) -> 0.081012973 | ... AF15: =IF(cfg_rf_mode="Single",(1+in_rf_single)*(1+AF56)-1,(AF5+AF14*AF6)/(1+AF14)) -> 0.072083813
A16: DF^E cumulative | B16: 1 | C16: =B16/(1+C5) -> 0.89180771 | D16: =C16/(1+D5) -> 0.79960616 | E16: =D16/(1+E5) -> 0.71971096 | F16: =E16/(1+F5) -> 0.64962566 | G16: =F16/(1+G5) -> 0.58759296 | H16: =G16/(1+H5) -> 0.53233977 | I16: =H16/(1+I5) -> 0.48290551 | J16: =I16/(1+J5) -> 0.43853487 | ... AF16: =AE16/(1+AF5) -> 0.06816598
A17: DF^D cumulative | B17: 1 | C17: =B17/(1+C6) -> 0.95238095 | D17: =C17/(1+D6) -> 0.90702948 | E17: =D17/(1+E6) -> 0.8638376 | F17: =E17/(1+F6) -> 0.82270247 | G17: =F17/(1+G6) -> 0.78352617 | H17: =G17/(1+H6) -> 0.7462154 | I17: =H17/(1+I6) -> 0.71068133 | J17: =I17/(1+J6) -> 0.67683936 | ... AF17: =AE17/(1+AF6) -> 0.1579384
A18: DF^F cumulative | B18: 1 | C18: =B18/(1+C15) -> 0.91473201 | D18: =C18/(1+D15) -> 0.83953106 | E18: =D18/(1+E15) -> 0.7723589 | F18: =E18/(1+F15) -> 0.71180111 | G18: =F18/(1+G15) -> 0.65684055 | H18: =G18/(1+H15) -> 0.60672682 | I18: =H18/(1+I15) -> 0.5608838 | J18: =I18/(1+J15) -> 0.5188502 | ... AF18: =AE18/(1+AF15) -> 0.093017709
A20: Long-run REAL rates (last tenor) — capitalisation BASE; cap rows 58-60 apply (1+pi_t) | B20: =INDEX(finrate_coe,COLUMNS(finrate_coe)) -> 0.05 | C20: =INDEX(finrate_cod,COLUMNS(finrate_cod)) -> 0.045454086 | D20: =IF(cfg_rf_mode="Single",in_rf_lr,($B$20+O14*$C$20)/(1+O14)) -> 0.048208762 | E20: ← ρE_LR | ρD_LR | ρF_LR
A22: normal EPS = (1+pi)*EPS(t-1) + (rhoE_nom - pi)*retained(t-1) | C22: =(1+C56)*B7+(C5-C56)*B9 -> 8.5557374 | D22: =(1+D56)*C7+(D5-D56)*C9 -> 8.3405647 | E22: =(1+E56)*D7+(E5-E56)*D9 -> 8.7828171 | F22: =(1+F56)*E7+(F5-F56)*E9 -> 9.2387067 | G22: =(1+G56)*F7+(G5-G56)*F9 -> 9.7120612 | H22: =(1+H56)*G7+(H5-H56)*G9 -> 0.66655835 | I22: =(1+I56)*H7+(I5-I56)*H9 -> 0.68578721 | J22: =(1+J56)*I7+(J5-J56)*I9 -> 0.70549363 | ... AF22: =(1+AF56)*AE7+(AF5-AF56)*AE9 -> 1.2707087
A23: AEG(EPS) | C23: =C7-C22 -> -0.43821812 | D23: =D7-D22 -> 0.23021386 | E23: =E7-E22 -> 0.24747474 | F23: =F7-F22 -> 0.26276433 | G23: =G7-G22 -> -9.0743509 | H23: =H7-H22 -> -0.010408875 | I23: =I7-I22 -> -0.010883352 | J23: =J7-J22 -> -0.011381224 | ... AF23: =AF7-AF22 -> -0.032220822
A24: contrib EPS [t<=N] = dRI^E_t x A^E_t | C24: =IF(C4<=cfg_N,C63*C62,0) -> -7.034831 | D24: =IF(D4<=cfg_N,D63*D62,0) -> 6.5690668 | E24: =IF(E4<=cfg_N,E63*E62,0) -> 6.3270166 | F24: =IF(F4<=cfg_N,F63*F62,0) -> 6.1761274 | G24: =IF(G4<=cfg_N,G63*G62,0) -> 0 | H24: =IF(H4<=cfg_N,H63*H62,0) -> 0 | I24: =IF(I4<=cfg_N,I63*I62,0) -> 0 | J24: =IF(J4<=cfg_N,J63*J62,0) -> 0 | ... AF24: =IF(AF4<=cfg_N,AF63*AF62,0) -> 0
A26: normal NFE | C26: =(1+C56)*B12 -> 0 | D26: =(1+D56)*C12 -> 0.21665794 | E26: =(1+E56)*D12 -> 0.22718867 | F26: =(1+F56)*E12 -> 0.2378533 | G26: =(1+G56)*F12 -> 0.2488041 | H26: =(1+H56)*G12 -> 0.26016077 | I26: =(1+I56)*H12 -> 0.2720199 | J26: =(1+J56)*I12 -> 0.28446378 | ... AF26: =(1+AF56)*AE12 -> 8.2227271
A27: AEG(NFE) | C27: =C12-C26 -> 0.21122349 | D27: =D12-D26 -> 0.0054164485 | E27: =E12-E26 -> 0.0056797167 | F27: =F12-F26 -> 0.0059463326 | G27: =G12-G26 -> 0.0062201024 | H27: =H12-H26 -> 0.0065040192 | I27: =I12-I26 -> 0.0068004974 | J27: =J12-J26 -> 0.0071115945 | ... AF27: =AF12-AF26 -> -7.0791879
A28: contrib NFE [t<=N] = dRI^D_t x A^D_t | C28: =IF(C4<=cfg_N,C66*C65,0) -> 4.5720567 | D28: =IF(D4<=cfg_N,D66*D65,0) -> -0.1887704 | E28: =IF(E4<=cfg_N,E66*E65,0) -> -0.070014616 | F28: =IF(F4<=cfg_N,F66*F65,0) -> 0.01510048 | G28: =IF(G4<=cfg_N,G66*G65,0) -> 0 | H28: =IF(H4<=cfg_N,H66*H65,0) -> 0 | I28: =IF(I4<=cfg_N,I66*I65,0) -> 0 | J28: =IF(J4<=cfg_N,J66*J65,0) -> 0 | ... AF28: =IF(AF4<=cfg_N,AF66*AF65,0) -> 0
A30: normal OI | C30: =(1+C56)*B13+(C15-C56)*B9 -> 8.367115 | D30: =(1+D56)*C13+(D15-D56)*C9 -> 8.553145 | E30: =(1+E56)*D13+(E15-E56)*D9 -> 9.0060008 | F30: =(1+F56)*E13+(F15-F56)*E9 -> 9.4725755 | G30: =(1+G56)*F13+(G15-G56)*F9 -> 9.9568605 | H30: =(1+H56)*G13+(H15-H56)*G9 -> 0.922664 | I30: =(1+I56)*H13+(I15-I56)*H9 -> 0.9536792 | J30: =(1+J56)*I13+(J15-J56)*I9 -> 0.98573934 | ... AF30: =(1+AF56)*AE13+(AF15-AF56)*AE9 -> 9.4923536
A31: AEG(OI) | C31: =C13-C30 -> -0.038372212 | D31: =D13-D30 -> 0.23970795 | E31: =E13-E30 -> 0.2571594 | F31: =F13-F30 -> 0.27269519 | G31: =G13-G30 -> -9.064126 | H31: =H13-H30 -> 0.00015026023 | I31: =I13-I30 -> 4.5057195e-05 | J31: =J13-J30 -> -5.1556809e-05 | ... AF31: =AF13-AF30 -> -7.1103266
A32: contrib OI [t<=N] = dRI^F_t x A^F_t | C32: =IF(C4<=cfg_N,C69*C68,0) -> -0.69083017 | D32: =IF(D4<=cfg_N,D69*D68,0) -> 7.3178696 | E32: =IF(E4<=cfg_N,E69*E68,0) -> 7.1660253 | F32: =IF(F4<=cfg_N,F69*F68,0) -> 7.0807303 | G32: =IF(G4<=cfg_N,G69*G68,0) -> 0 | H32: =IF(H4<=cfg_N,H69*H68,0) -> 0 | I32: =IF(I4<=cfg_N,I69*I68,0) -> 0 | J32: =IF(J4<=cfg_N,J69*J68,0) -> 0 | ... AF32: =IF(AF4<=cfg_N,AF69*AF68,0) -> 0
A35: VALUES ($/share)
A36: V(EPS) = equity = [BPS0 + normal-RI1 x A^E1] + Sum contrib | B36: =B43+SUM(C24:AF24) -> 146.5168
A37: V(NFE) = financing = [NFO0 + normal-RFD1 x A^D1] + Sum contrib | B37: =B11+(C26-C64*B11)*C65+SUM(C28:AF28) -> 6.5968394
A38: V(OI) = operations = V(EPS) + V(NFE) [value-additive] | B38: =B36+B37 -> 153.11364
A39: Equity via enterprise = V(OI) − V(NFE) | B39: =B38-B37 -> 146.5168
A40: decorative: V(OI)−V(NFE)−V(EPS). B38 is DEFINED as B36+B37, so this is identically 0 for any inputs. Proves nothing. | B40: =B39-B36 -> 0 | D40: =IF(ABS(B40)<in_tie_tol,"TIE ✓","BREAK") -> TIE ✓
A41: diagnostic: V(OI) direct @ BOOK-weighted rhoF — expected to differ from B38; the real check is Audit CHECK 7 on the DCF tab. | B41: =B70+(C30-C67*B70)*C68+SUM(C32:AF32) -> 170.10632 | D41: illustration only; differs from additive by the multi-rate WACC gap
A42: EQUITY READOUTS ($/share)
A43: Normal value = BPS0 + (normal EPS1 - rho*E1 x BPS0) x A^E1 | B43: =B10+(C22-C61*B10)*C62 -> 134.47942
A44: Intrinsic value in 2026$ (= V(EPS); a time-0 PV, so nominal==real at t=0) | B44: =B36 -> 146.5168
A45: Price in 2026$ = in_price x deflator | B45: =in_price*INDEX(md_deflator,MATCH(in_anchor_year&"",md_years,0)) -> 327.89576
A46: PVGO = price − normal value | B46: =B45-B43 -> 193.41634
A47: Implied P/E = intrinsic / EPS1 (both real 2026$) | B47: =B44/(C7/C57) -> 18.590795
A48: Normal P/E = 1 ÷ ρE_LR | B48: =1/$B$20 -> 20
A49: Growth premium (turns) = implied − normal | B49: =B47-B48 -> -1.4092051
A51: READ (cfg_valread)
A52: Equity path read → V(EPS) | B52: =B36 -> 146.5168
A53: Enterprise path read → V(OI)−V(NFE) | B53: =B39 -> 146.5168
A54: ACTIVE VALUE (toggle-selected) | B54: =IF(cfg_valread="Enterprise path",B53,B52) -> 146.5168
A55: agreement: equity read − enterprise read | B55: =B52-B53 -> 0
A56: pi_t expected inflation fwd [finrate_infl] <STAGE A> | C56: =INDEX(finrate_infl,C4) -> 0.029992 | D56: =INDEX(finrate_infl,D4) -> 0.025728421 | E56: =INDEX(finrate_infl,E4) -> 0.02302958 | F56: =INDEX(finrate_infl,F4) -> 0.021406581 | G56: =INDEX(finrate_infl,G4) -> 0.020526948 | H56: =INDEX(finrate_infl,H4) -> 0.020141491 | I56: =INDEX(finrate_infl,I4) -> 0.020081803 | J56: =INDEX(finrate_infl,J4) -> 0.020240218 | ... AF56: =INDEX(finrate_infl,AF4) -> 0.022777
A57: I_t cumulative inflation index (I_0=1) <STAGE A> | B57: 1 | C57: =B57*(1+C56) -> 1.029992 | D57: =C57*(1+D56) -> 1.0564921 | E57: =D57*(1+E56) -> 1.0808226 | F57: =E57*(1+F56) -> 1.1039594 | G57: =F57*(1+G56) -> 1.1266203 | H57: =G57*(1+H56) -> 1.1493121 | I57: =H57*(1+I56) -> 1.1723923 | J57: =I57*(1+J56) -> 1.1961218 | ... AF57: =AE57*(1+AF56) -> 1.9669712
A58: cap rate E = rhoE_LR(real) x (1+pi_t) <STAGE A> | C58: =$B$20*(1+C56) -> 0.0514996 | D58: =$B$20*(1+D56) -> 0.051286421 | E58: =$B$20*(1+E56) -> 0.051151479 | F58: =$B$20*(1+F56) -> 0.051070329 | G58: =$B$20*(1+G56) -> 0.051026347 | H58: =$B$20*(1+H56) -> 0.051007075 | I58: =$B$20*(1+I56) -> 0.05100409 | J58: =$B$20*(1+J56) -> 0.051012011 | ... AF58: =$B$20*(1+AF56) -> 0.05113885
A59: cap rate D = rhoD_LR(real) x (1+pi_t) <STAGE A> | C59: =$C$20*(1+C56) -> 0.046817344 | D59: =$C$20*(1+D56) -> 0.046623547 | E59: =$C$20*(1+E56) -> 0.046500874 | F59: =$C$20*(1+F56) -> 0.046427102 | G59: =$C$20*(1+G56) -> 0.046387119 | H59: =$C$20*(1+H56) -> 0.046369599 | I59: =$C$20*(1+I56) -> 0.046366886 | J59: =$C$20*(1+J56) -> 0.046374086 | ... AF59: =$C$20*(1+AF56) -> 0.046489393
A60: cap rate F = rhoF_LR(real) x (1+pi_t) <STAGE A> | C60: =$D$20*(1+C56) -> 0.049654639 | D60: =$D$20*(1+D56) -> 0.049449097 | E60: =$D$20*(1+E56) -> 0.049318989 | F60: =$D$20*(1+F56) -> 0.049240746 | G60: =$D$20*(1+G56) -> 0.04919834 | H60: =$D$20*(1+H56) -> 0.049179758 | I60: =$D$20*(1+I56) -> 0.04917688 | J60: =$D$20*(1+J56) -> 0.049184517 | ... AF60: =$D$20*(1+AF56) -> 0.049306813
A61: rho*E = rhoE(nom) - pi [Stage A real capital-charge rate] <AEG-TS> | C61: =C5-C56 -> 0.091325957 | D61: =D5-D56 -> 0.089580282 | E61: =E5-E56 -> 0.087980544 | F61: =F5-F56 -> 0.086479091 | G61: =G5-G56 -> 0.085043912 | H61: =H5-H56 -> 0.083651602 | I61: =I5-I56 -> 0.082286599 | J61: =J5-J56 -> 0.080939057 | ... AF61: =AF5-AF56 -> 0.05113885
A62: A^E_t = SUM(DF^E_t..DF^E_N) + DF^E_N/rhoE_LR [curve-implied annuity] <AEG-TS> | C62: =IF(C4>cfg_N,0,C16+IF(C4=cfg_N,C16/$B$20,D62)) -> 16.053264 | D62: =IF(D4>cfg_N,0,D16+IF(D4=cfg_N,D16/$B$20,E62)) -> 15.161456 | E62: =IF(E4>cfg_N,0,E16+IF(E4=cfg_N,E16/$B$20,F62)) -> 14.36185 | F62: =IF(F4>cfg_N,0,F16+IF(F4=cfg_N,F16/$B$20,G62)) -> 13.642139 | G62: =IF(G4>cfg_N,0,G16+IF(G4=cfg_N,G16/$B$20,H62)) -> 0 | H62: =IF(H4>cfg_N,0,H16+IF(H4=cfg_N,H16/$B$20,I62)) -> 0 | I62: =IF(I4>cfg_N,0,I16+IF(I4=cfg_N,I16/$B$20,J62)) -> 0 | J62: =IF(J4>cfg_N,0,J16+IF(J4=cfg_N,J16/$B$20,K62)) -> 0 | ... AF62: =IF(AF4>cfg_N,0,AF16+IF(AF4=cfg_N,AF16/$B$20,AG62)) -> 0
A63: dRI^E_t = AEG(EPS)_t + pi_t*EPS_(t-1) + [rho*E_(t-1)-rho*E_t(1+pi_(t-1))]*BPS_(t-2) <AEG-TS> | C63: =C23+IF(C4=1,0,C56*B7+(B61-C61*(1+B56))*INDEX($B10:C10,MAX(1,C4-1))) -> -0.43821812 | D63: =D23+IF(D4=1,0,D56*C7+(C61-D61*(1+C56))*INDEX($B10:D10,MAX(1,D4-1))) -> 0.43327414 | E63: =E23+IF(E4=1,0,E56*D7+(D61-E61*(1+D56))*INDEX($B10:E10,MAX(1,E4-1))) -> 0.4405433 | F63: =F23+IF(F4=1,0,F56*E7+(E61-F61*(1+E56))*INDEX($B10:F10,MAX(1,F4-1))) -> 0.45272427 | G63: =G23+IF(G4=1,0,G56*F7+(F61-G61*(1+F56))*INDEX($B10:G10,MAX(1,G4-1))) -> -8.8820745 | H63: =H23+IF(H4=1,0,H56*G7+(G61-H61*(1+G56))*INDEX($B10:H10,MAX(1,H4-1))) -> -4.874573e-16 | I63: =I23+IF(I4=1,0,I56*H7+(H61-I61*(1+H56))*INDEX($B10:I10,MAX(1,I4-1))) -> -8.3266727e-17 | J63: =J23+IF(J4=1,0,J56*I7+(I61-J61*(1+I56))*INDEX($B10:J10,MAX(1,J4-1))) -> 1.474515e-16 | ... AF63: =AF23+IF(AF4=1,0,AF56*AE7+(AE61-AF61*(1+AE56))*INDEX($B10:AF10,MAX(1,AF4-1))) -> -2.4563684e-15
A64: rho*D = rhoD(nom) - pi <AEG-TS> | C64: =C6-C56 -> 0.020008 | D64: =D6-D56 -> 0.024271579 | E64: =E6-E56 -> 0.02697042 | F64: =F6-F56 -> 0.028593419 | G64: =G6-G56 -> 0.029473052 | H64: =H6-H56 -> 0.029858509 | I64: =I6-I56 -> 0.029918197 | J64: =J6-J56 -> 0.029759782 | ... AF64: =AF6-AF56 -> 0.046489393
A65: A^D_t = SUM(DF^D_t..DF^D_N) + DF^D_N/rhoD_LR <AEG-TS> | C65: =IF(C4>cfg_N,0,C17+IF(C4=cfg_N,C17/$C$20,D65)) -> 21.645588 | D65: =IF(D4>cfg_N,0,D17+IF(D4=cfg_N,D17/$C$20,E65)) -> 20.693207 | E65: =IF(E4>cfg_N,0,E17+IF(E4=cfg_N,E17/$C$20,F65)) -> 19.786178 | F65: =IF(F4>cfg_N,0,F17+IF(F4=cfg_N,F17/$C$20,G65)) -> 18.92234 | G65: =IF(G4>cfg_N,0,G17+IF(G4=cfg_N,G17/$C$20,H65)) -> 0 | H65: =IF(H4>cfg_N,0,H17+IF(H4=cfg_N,H17/$C$20,I65)) -> 0 | I65: =IF(I4>cfg_N,0,I17+IF(I4=cfg_N,I17/$C$20,J65)) -> 0 | J65: =IF(J4>cfg_N,0,J17+IF(J4=cfg_N,J17/$C$20,K65)) -> 0 | ... AF65: =IF(AF4>cfg_N,0,AF17+IF(AF4=cfg_N,AF17/$C$20,AG65)) -> 0
A66: dRI^D_t = AEG(NFE)_t + pi_t*NFE_(t-1) + [rho*D_(t-1)-rho*D_t(1+pi_(t-1))]*NFO_(t-2) <AEG-TS> | C66: =C27+IF(C4=1,0,C56*B12+(B64-C64*(1+B56))*INDEX($B11:C11,MAX(1,C4-1))) -> 0.21122349 | D66: =D27+IF(D4=1,0,D56*C12+(C64-D64*(1+C56))*INDEX($B11:D11,MAX(1,D4-1))) -> -0.0091223364 | E66: =E27+IF(E4=1,0,E56*D12+(D64-E64*(1+D56))*INDEX($B11:E11,MAX(1,E4-1))) -> -0.003538562 | F66: =F27+IF(F4=1,0,F56*E12+(E64-F64*(1+E56))*INDEX($B11:F11,MAX(1,F4-1))) -> 0.00079802394 | G66: =G27+IF(G4=1,0,G56*F12+(F64-G64*(1+F56))*INDEX($B11:G11,MAX(1,G4-1))) -> 0.0041893741 | H66: =H27+IF(H4=1,0,H56*G12+(G64-H64*(1+G56))*INDEX($B11:H11,MAX(1,H4-1))) -> 0.0067725855 | I66: =I27+IF(I4=1,0,I56*H12+(H64-I64*(1+H56))*INDEX($B11:I11,MAX(1,I4-1))) -> 0.0087776318 | J66: =J27+IF(J4=1,0,J56*I12+(I64-J64*(1+I56))*INDEX($B11:J11,MAX(1,J4-1))) -> 0.010412517 | ... AF66: =AF27+IF(AF4=1,0,AF56*AE12+(AE64-AF64*(1+AE56))*INDEX($B11:AF11,MAX(1,AF4-1))) -> -0.28926108
A67: rho*F = rhoF(nom) - pi <AEG-TS> | C67: =C15-C56 -> 0.063224358 | D67: =D15-D56 -> 0.063846525 | E67: =E15-E56 -> 0.063940567 | F67: =F15-F56 -> 0.06367025 | G67: =G15-G56 -> 0.063147183 | H67: =H15-H56 -> 0.062455371 | I67: =I15-I56 -> 0.061651742 | J67: =J15-J56 -> 0.060772755 | ... AF67: =AF15-AF56 -> 0.049306813
A68: A^F_t = SUM(DF^F_t..DF^F_N) + DF^F_N/rhoF_LR <AEG-TS> | C68: =IF(C4>cfg_N,0,C18+IF(C4=cfg_N,C18/$D$20,D68)) -> 18.003397 | D68: =IF(D4>cfg_N,0,D18+IF(D4=cfg_N,D18/$D$20,E68)) -> 17.088665 | E68: =IF(E4>cfg_N,0,E18+IF(E4=cfg_N,E18/$D$20,F68)) -> 16.249134 | F68: =IF(F4>cfg_N,0,F18+IF(F4=cfg_N,F18/$D$20,G68)) -> 15.476775 | G68: =IF(G4>cfg_N,0,G18+IF(G4=cfg_N,G18/$D$20,H68)) -> 0 | H68: =IF(H4>cfg_N,0,H18+IF(H4=cfg_N,H18/$D$20,I68)) -> 0 | I68: =IF(I4>cfg_N,0,I18+IF(I4=cfg_N,I18/$D$20,J68)) -> 0 | J68: =IF(J4>cfg_N,0,J18+IF(J4=cfg_N,J18/$D$20,K68)) -> 0 | ... AF68: =IF(AF4>cfg_N,0,AF18+IF(AF4=cfg_N,AF18/$D$20,AG68)) -> 0
A69: dRI^F_t = AEG(OI)_t + pi_t*OI_(t-1) + [rho*F_(t-1)-rho*F_t(1+pi_(t-1))]*NOA_(t-2) <AEG-TS> | C69: =C31+IF(C4=1,0,C56*B13+(B67-C67*(1+B56))*INDEX($B70:C70,MAX(1,C4-1))) -> -0.038372212 | D69: =D31+IF(D4=1,0,D56*C13+(C67-D67*(1+C56))*INDEX($B70:D70,MAX(1,D4-1))) -> 0.42822945 | E69: =E31+IF(E4=1,0,E56*D13+(D67-E67*(1+D56))*INDEX($B70:E70,MAX(1,E4-1))) -> 0.44100967 | F69: =F31+IF(F4=1,0,F56*E13+(E67-F67*(1+E56))*INDEX($B70:F70,MAX(1,F4-1))) -> 0.45750683 | G69: =G31+IF(G4=1,0,G56*F13+(F67-G67*(1+F56))*INDEX($B70:G70,MAX(1,G4-1))) -> -8.8738804 | H69: =H31+IF(H4=1,0,H56*G13+(G67-H67*(1+G56))*INDEX($B70:H70,MAX(1,H4-1))) -> 0.010827702 | I69: =I31+IF(I4=1,0,I56*H13+(H67-I67*(1+H56))*INDEX($B70:I70,MAX(1,I4-1))) -> 0.012905544 | J69: =J31+IF(J4=1,0,J56*I13+(I67-J67*(1+I56))*INDEX($B70:J70,MAX(1,J4-1))) -> 0.01463059 | ... AF69: =AF31+IF(AF4=1,0,AF56*AE13+(AE67-AF67*(1+AE56))*INDEX($B70:AF70,MAX(1,AF4-1))) -> -0.28817892
A70: NOA/sh = BPS/sh + NFO/sh [operating stock for the OI leg] <AEG-TS> | B70: =B10+B11 -> 10.155057 | C70: =C10+C11 -> 10.721118 | D70: =D10+D11 -> 11.271879 | E70: =E10+E11 -> 11.819753 | F70: =F10+F11 -> 12.374593 | G70: =G10+G11 -> 12.94432 | H70: =H10+H11 -> 13.535164 | I70: =I10+I11 -> 14.152149 | ... AF70: =AF10+AF11 -> 41.898294
A71: CSE per ANCHOR share (nominal) = fc_cse / anchor_shares0 [Enterprise-mode book basis] <ENT-FIX> | B71: =anchor_real_cse0/anchor_shares0 -> 6.1536336 | C71: =INDEX(fc_cse,C4)/anchor_shares0 -> 6.4966482 | D71: =INDEX(fc_cse,D4)/anchor_shares0 -> 6.8303917 | E71: =INDEX(fc_cse,E4)/anchor_shares0 -> 7.162385 | F71: =INDEX(fc_cse,F4)/anchor_shares0 -> 7.4985999 | G71: =INDEX(fc_cse,G4)/anchor_shares0 -> 7.8438363 | H71: =INDEX(fc_cse,H4)/anchor_shares0 -> 8.2018685 | I71: =INDEX(fc_cse,I4)/anchor_shares0 -> 8.5757412 | J71: =INDEX(fc_cse,J4)/anchor_shares0 -> 8.968049 | ... AF71: =INDEX(fc_cse,AF4)/anchor_shares0 -> 25.389001

Sheet Scenarios
A1: SCENARIOS — driver overlay (real 2026$)
A2: Blue = scenario driver inputs (the G.1 surface). cfg_scenario picks the active column; the Forecast tab pulls it. Normal ≈ zero-economic-profit floor (no real growth, no buyback).
A4: Driver | B4: Bear | C4: Consensus | D4: Bull | E4: Normal
A5: Real revenue growth | B5: -0.015 | C5: 0.03 | D5: 0.025 | E5: 0
A6: NOA growth (real) | B6: -0.01 | C6: 0.025 | D6: 0.03 | E6: 0
A7: Net buyback rate | B7: 0 | C7: 0.03 | D7: 0.03 | E7: 0

Sheet Implied
A1: IMPLIED EXPECTATIONS — what the price embeds
A2: PVGO decomposition + implied constant real EPS growth (Gordon-equivalent). Re-bracketed to admit negative growth (g > −100%, guarded g < ρE_LR).
A4: PVGO DECOMPOSITION (real 2026$/sh)
A5: Real price | B5: =val_active*0+val_realprice -> 327.89576
A6: Normal (no-growth) value | B6: =val_normalval -> 134.47942
A7: PVGO = price − normal | B7: =val_realprice-val_normalval -> 193.41634
A8: Implied P/E (price ÷ EPS₁) | B8: =val_realprice/val_eps1 -> 40.393592
A9: Normal P/E = 1/ρE_LR | B9: =val_normalPE -> 20
A10: Growth premium (turns) | B10: =val_realprice/val_eps1-val_normalPE -> 20.393592
A12: IMPLIED CONSTANT REAL EPS GROWTH
A13: EPS₁ (real) | B13: =val_eps1 -> 8.1175193
A14: ρE_LR | B14: =val_rhoe_lr -> 0.05
A15: Implied g* = ρE_LR − EPS₁/price [closed form] | B15: =B14-B13/val_realprice -> 0.025243598 | D15: =IF(B15<0,"market implies real EPS DECLINE","market implies real EPS growth") -> market implies real EPS growth
A17: SENSITIVITY GRID — value vs implied growth g (guarded g<ρE_LR)
A18: g | B18: =in_implied_g_start -> -0.08 | C18: =B18+in_implied_g_step -> -0.07 | D18: =C18+in_implied_g_step -> -0.06 | E18: =D18+in_implied_g_step -> -0.05 | F18: =E18+in_implied_g_step -> -0.04 | G18: =F18+in_implied_g_step -> -0.03 | H18: =G18+in_implied_g_step -> -0.02 | I18: =H18+in_implied_g_step -> -0.01 | J18: =I18+in_implied_g_step -> 0 | ... O18: =N18+in_implied_g_step -> 0.05
A19: V(g) = EPS₁/(ρE_LR − g) | B19: =IF($B$14-B18>in_tie_tol,$B$13/($B$14-B18),"n/m") -> 62.442456 | C19: =IF($B$14-C18>in_tie_tol,$B$13/($B$14-C18),"n/m") -> 67.645994 | D19: =IF($B$14-D18>in_tie_tol,$B$13/($B$14-D18),"n/m") -> 73.79563 | E19: =IF($B$14-E18>in_tie_tol,$B$13/($B$14-E18),"n/m") -> 81.175193 | F19: =IF($B$14-F18>in_tie_tol,$B$13/($B$14-F18),"n/m") -> 90.194659 | G19: =IF($B$14-G18>in_tie_tol,$B$13/($B$14-G18),"n/m") -> 101.46899 | H19: =IF($B$14-H18>in_tie_tol,$B$13/($B$14-H18),"n/m") -> 115.96456 | I19: =IF($B$14-I18>in_tie_tol,$B$13/($B$14-I18),"n/m") -> 135.29199 | ... O19: =IF($B$14-O18>in_tie_tol,$B$13/($B$14-O18),"n/m") -> n/m
A20: vs price | B20: =IF(ISNUMBER(B19),IF(B19>=val_realprice,"≥price","<price"),"") -> <price | C20: =IF(ISNUMBER(C19),IF(C19>=val_realprice,"≥price","<price"),"") -> <price | D20: =IF(ISNUMBER(D19),IF(D19>=val_realprice,"≥price","<price"),"") -> <price | E20: =IF(ISNUMBER(E19),IF(E19>=val_realprice,"≥price","<price"),"") -> <price | F20: =IF(ISNUMBER(F19),IF(F19>=val_realprice,"≥price","<price"),"") -> <price | G20: =IF(ISNUMBER(G19),IF(G19>=val_realprice,"≥price","<price"),"") -> <price | H20: =IF(ISNUMBER(H19),IF(H19>=val_realprice,"≥price","<price"),"") -> <price | I20: =IF(ISNUMBER(I19),IF(I19>=val_realprice,"≥price","<price"),"") -> <price | ... O20: =IF(ISNUMBER(O19),IF(O19>=val_realprice,"≥price","<price"),"")

Sheet DCF Reconciliation
A1: DCF RECONCILIATION — five spokes, one hub (NOMINAL forecast; value in 2026$)
A2: DDM · RI · AEG · FCFE-DCF · FCFF-DCF on the SAME forecast, common terminal (constant-RI continuation), leverage-implied ρF. Per Lundholm-O'Keefe (2001): properly implemented, all give one value.
A4: Period t | B4: 0 | C4: 1 | D4: 2 | E4: 3 | F4: 4 | G4: 5 | H4: 6 | I4: 7 | J4: 8 | K4: 9 | L4: 10 | M4: 11 | N4: 12 | O4: 13 | P4: 14 | Q4: 15 | R4: 16 | S4: 17 | T4: 18 | U4: 19 | V4: 20 | W4: 21 | X4: 22 | Y4: 23 | Z4: 24 | AA4: 25 | AB4: 26 | AC4: 27 | AD4: 28 | AE4: 29 | AF4: 30
A5: ρE (finrate_coe) | C5: =(1+INDEX(finrate_coe,C4))*(1+INDEX(finrate_infl,C4))-1 -> 0.12131796 | D5: =(1+INDEX(finrate_coe,D4))*(1+INDEX(finrate_infl,D4))-1 -> 0.1153087 | E5: =(1+INDEX(finrate_coe,E4))*(1+INDEX(finrate_infl,E4))-1 -> 0.11101012 | F5: =(1+INDEX(finrate_coe,F4))*(1+INDEX(finrate_infl,F4))-1 -> 0.10788567 | G5: =(1+INDEX(finrate_coe,G4))*(1+INDEX(finrate_infl,G4))-1 -> 0.10557086 | H5: =(1+INDEX(finrate_coe,H4))*(1+INDEX(finrate_infl,H4))-1 -> 0.10379309 | I5: =(1+INDEX(finrate_coe,I4))*(1+INDEX(finrate_infl,I4))-1 -> 0.1023684 | J5: =(1+INDEX(finrate_coe,J4))*(1+INDEX(finrate_infl,J4))-1 -> 0.10117928 | ... AF5: =(1+INDEX(finrate_coe,AF4))*(1+INDEX(finrate_infl,AF4))-1 -> 0.07391585
A6: ρD (finrate_cod) | C6: =(1+INDEX(finrate_cod,C4))*(1+INDEX(finrate_infl,C4))-1 -> 0.05 | D6: =(1+INDEX(finrate_cod,D4))*(1+INDEX(finrate_infl,D4))-1 -> 0.05 | E6: =(1+INDEX(finrate_cod,E4))*(1+INDEX(finrate_infl,E4))-1 -> 0.05 | F6: =(1+INDEX(finrate_cod,F4))*(1+INDEX(finrate_infl,F4))-1 -> 0.05 | G6: =(1+INDEX(finrate_cod,G4))*(1+INDEX(finrate_infl,G4))-1 -> 0.05 | H6: =(1+INDEX(finrate_cod,H4))*(1+INDEX(finrate_infl,H4))-1 -> 0.05 | I6: =(1+INDEX(finrate_cod,I4))*(1+INDEX(finrate_infl,I4))-1 -> 0.05 | J6: =(1+INDEX(finrate_cod,J4))*(1+INDEX(finrate_infl,J4))-1 -> 0.05 | ... AF6: =(1+INDEX(finrate_cod,AF4))*(1+INDEX(finrate_infl,AF4))-1 -> 0.069266394
A7: NI | B7: =anchor_ni0 -> 0.11571047 | C7: =INDEX(fc_ni,C4) -> 0.12180338 | D7: =INDEX(fc_ni,D4) -> 0.12860453 | E7: =INDEX(fc_ni,E4) -> 0.13549953 | F7: =INDEX(fc_ni,F4) -> 0.14256957 | G7: =INDEX(fc_ni,G4) -> 0.0095688426 | H7: =INDEX(fc_ni,H4) -> 0.0098455229 | I7: =INDEX(fc_ni,I4) -> 0.010126932 | J7: =INDEX(fc_ni,J4) -> 0.010415157 | ... AF7: =INDEX(fc_ni,AF4) -> 0.01858351
A8: OI after tax | B8: =anchor_oi_at0 -> 0.11571047 | C8: =INDEX(fc_oiat,C4) -> 0.12300468 | D8: =INDEX(fc_oiat,D4) -> 0.13014306 | E8: =INDEX(fc_oiat,E4) -> 0.13729696 | F8: =INDEX(fc_oiat,F4) -> 0.14456779 | G8: =INDEX(fc_oiat,G4) -> 0.011725217 | H8: =INDEX(fc_oiat,H4) -> 0.012130677 | I8: =INDEX(fc_oiat,I4) -> 0.012521169 | J8: =INDEX(fc_oiat,J4) -> 0.012905277 | ... AF8: =INDEX(fc_oiat,AF4) -> 0.029568851
A9: CSE | B9: =anchor_real_cse0 -> 0.092335272 | C9: =INDEX(fc_cse,C4) -> 0.097482207 | D9: =INDEX(fc_cse,D4) -> 0.10249003 | E9: =INDEX(fc_cse,E4) -> 0.10747159 | F9: =INDEX(fc_cse,F4) -> 0.11251649 | G9: =INDEX(fc_cse,G4) -> 0.11769676 | H9: =INDEX(fc_cse,H4) -> 0.12306904 | I9: =INDEX(fc_cse,I4) -> 0.128679 | J9: =INDEX(fc_cse,J4) -> 0.13456557 | ... AF9: =INDEX(fc_cse,AF4) -> 0.38096196
A10: NOA | B10: =anchor_real_noa0 -> 0.15237663 | C10: =INDEX(fc_noa,C4) -> 0.16087038 | D10: =INDEX(fc_noa,D4) -> 0.16913455 | E10: =INDEX(fc_noa,E4) -> 0.17735539 | F10: =INDEX(fc_noa,F4) -> 0.18568076 | G10: =INDEX(fc_noa,G4) -> 0.19422953 | H10: =INDEX(fc_noa,H4) -> 0.20309514 | I10: =INDEX(fc_noa,I4) -> 0.212353 | J10: =INDEX(fc_noa,J4) -> 0.22206734 | ... AF10: =INDEX(fc_noa,AF4) -> 0.6286839
A11: NFO | B11: =anchor_real_nfo0 -> 0.060041357 | C11: =INDEX(fc_nfo,C4) -> 0.06338817 | D11: =INDEX(fc_nfo,D4) -> 0.066644524 | E11: =INDEX(fc_nfo,E4) -> 0.069883803 | F11: =INDEX(fc_nfo,F4) -> 0.07316427 | G11: =INDEX(fc_nfo,G4) -> 0.076532762 | H11: =INDEX(fc_nfo,H4) -> 0.080026102 | I11: =INDEX(fc_nfo,I4) -> 0.083674 | J11: =INDEX(fc_nfo,J4) -> 0.08750177 | ... AF11: =INDEX(fc_nfo,AF4) -> 0.24772194
A12: NFE = OI_at − NI | C12: =C8-C7 -> 0.0012013075 | D12: =D8-D7 -> 0.001538531 | E12: =E8-E7 -> 0.0017974308 | F12: =F8-F7 -> 0.0019982168 | G12: =G8-G7 -> 0.0021563743 | H12: =H8-H7 -> 0.0022851542 | I12: =I8-I7 -> 0.0023942367 | J12: =J8-J7 -> 0.00249012 | ... AF12: =AF8-AF7 -> 0.010985341
A13: FLEV = NFO/CSE (prior) | C13: =IF(B9=0,"",B11/B9) -> 0.65025375 | D13: =IF(C9=0,"",C11/C9) -> 0.65025375 | E13: =IF(D9=0,"",D11/D9) -> 0.65025375 | F13: =IF(E9=0,"",E11/E9) -> 0.65025375 | G13: =IF(F9=0,"",F11/F9) -> 0.65025375 | H13: =IF(G9=0,"",G11/G9) -> 0.65025375 | I13: =IF(H9=0,"",H11/H9) -> 0.65025375 | J13: =IF(I9=0,"",I11/I9) -> 0.65025375 | ... AF13: =IF(AE9=0,"",AE11/AE9) -> 0.65025375
A14: ρF = (ρE+FLEV·ρD)/(1+FLEV) | C14: =IF(cfg_rf_mode="Single",(1+in_rf_single)*(1+INDEX(finrate_infl,C4))-1,(C5+C13*C6)/(1+C13)) -> 0.093216358 | D14: =IF(cfg_rf_mode="Single",(1+in_rf_single)*(1+INDEX(finrate_infl,D4))-1,(D5+D13*D6)/(1+D13)) -> 0.089574946 | E14: =IF(cfg_rf_mode="Single",(1+in_rf_single)*(1+INDEX(finrate_infl,E4))-1,(E5+E13*E6)/(1+E13)) -> 0.086970147 | F14: =IF(cfg_rf_mode="Single",(1+in_rf_single)*(1+INDEX(finrate_infl,F4))-1,(F5+F13*F6)/(1+F13)) -> 0.085076831 | G14: =IF(cfg_rf_mode="Single",(1+in_rf_single)*(1+INDEX(finrate_infl,G4))-1,(G5+G13*G6)/(1+G13)) -> 0.083674131 | H14: =IF(cfg_rf_mode="Single",(1+in_rf_single)*(1+INDEX(finrate_infl,H4))-1,(H5+H13*H6)/(1+H13)) -> 0.082596862 | I14: =IF(cfg_rf_mode="Single",(1+in_rf_single)*(1+INDEX(finrate_infl,I4))-1,(I5+I13*I6)/(1+I13)) -> 0.081733545 | J14: =IF(cfg_rf_mode="Single",(1+in_rf_single)*(1+INDEX(finrate_infl,J4))-1,(J5+J13*J6)/(1+J13)) -> 0.081012973 | ... AF14: =IF(cfg_rf_mode="Single",(1+in_rf_single)*(1+INDEX(finrate_infl,AF4))-1,(AF5+AF13*AF6)/(1+AF13)) -> 0.072083813
A15: DF^E | B15: 1 | C15: =B15/(1+C5) -> 0.89180771 | D15: =C15/(1+D5) -> 0.79960616 | E15: =D15/(1+E5) -> 0.71971096 | F15: =E15/(1+F5) -> 0.64962566 | G15: =F15/(1+G5) -> 0.58759296 | H15: =G15/(1+H5) -> 0.53233977 | I15: =H15/(1+I5) -> 0.48290551 | J15: =I15/(1+J5) -> 0.43853487 | ... AF15: =AE15/(1+AF5) -> 0.06816598
A16: DF^F | B16: 1 | C16: =B16/(1+C14) -> 0.91473201 | D16: =C16/(1+D14) -> 0.83953106 | E16: =D16/(1+E14) -> 0.7723589 | F16: =E16/(1+F14) -> 0.71180111 | G16: =F16/(1+G14) -> 0.65684055 | H16: =G16/(1+H14) -> 0.60672682 | I16: =H16/(1+I14) -> 0.5608838 | J16: =I16/(1+J14) -> 0.5188502 | ... AF16: =AE16/(1+AF14) -> 0.093017709
A17: DF^D | B17: 1 | C17: =B17/(1+C6) -> 0.95238095 | D17: =C17/(1+D6) -> 0.90702948 | E17: =D17/(1+E6) -> 0.8638376 | F17: =E17/(1+F6) -> 0.82270247 | G17: =F17/(1+G6) -> 0.78352617 | H17: =G17/(1+H6) -> 0.7462154 | I17: =H17/(1+I6) -> 0.71068133 | J17: =I17/(1+J6) -> 0.67683936 | ... AF17: =AE17/(1+AF6) -> 0.1579384
A19: FCF BUILD-UP | D19: FCFF = OI_at + D&A − capex − ΔWC ≡ OI_at − ΔNOA (identity)
A20: + D&A (economic) | C20: =INDEX(fc_dep,C4) -> 0.013785754 | D20: =INDEX(fc_dep,D4) -> 0.014309846 | E20: =INDEX(fc_dep,E4) -> 0.014869623 | F20: =INDEX(fc_dep,F4) -> 0.015472487 | G20: =INDEX(fc_dep,G4) -> 0.016123841 | H20: =INDEX(fc_dep,H4) -> 0.016827613 | I20: =INDEX(fc_dep,I4) -> 0.017586929 | J20: =INDEX(fc_dep,J4) -> 0.018404649 | ... AF20: =INDEX(fc_dep,AF4) -> 0.05714926
A21: − capex | C21: =INDEX(fc_capex,C4) -> 0.014618155 | D21: =INDEX(fc_capex,D4) -> 0.015444085 | E21: =INDEX(fc_capex,E4) -> 0.016273748 | F21: =INDEX(fc_capex,F4) -> 0.017120777 | G21: =INDEX(fc_capex,G4) -> 0.01799638 | H21: =INDEX(fc_capex,H4) -> 0.01890962 | I21: =INDEX(fc_capex,I4) -> 0.01986804 | J21: =INDEX(fc_capex,J4) -> 0.020878279 | ... AF21: =INDEX(fc_capex,AF4) -> 0.065786417
A22: − ΔWorking capital + other (= ΔNOA − ΔNetPP&E) | C22: =(C10-(1+INDEX(finrate_infl,C4))*B10)-(C21-C20) -> 0.0030912668 | D22: =(D10-(1+INDEX(finrate_infl,D4))*C10)-(D21-D20) -> 0.0029909941 | E22: =(E10-(1+INDEX(finrate_infl,E4))*D10)-(E21-E20) -> 0.0029216159 | F22: =(F10-(1+INDEX(finrate_infl,F4))*E10)-(F21-F20) -> 0.0028805093 | G22: =(G10-(1+INDEX(finrate_infl,G4))*F10)-(G21-G20) -> 0.0028647656 | H22: =(H10-(1+INDEX(finrate_infl,H4))*G10)-(H21-H20) -> 0.0028715329 | I22: =(I10-(1+INDEX(finrate_infl,I4))*H10)-(I21-I20) -> 0.0028982302 | J22: =(J10-(1+INDEX(finrate_infl,J4))*I10)-(J21-J20) -> 0.0029426465 | ... AF22: =(AF10-(1+INDEX(finrate_infl,AF4))*AE10)-(AF21-AF20) -> 0.0066965964
A23: FCFF = OI_at − ΔNOA | C23: =C8-(C10-(1+INDEX(finrate_infl,C4))*B10) -> 0.11908102 | D23: =D8-(D10-(1+INDEX(finrate_infl,D4))*C10) -> 0.12601783 | E23: =E8-(E10-(1+INDEX(finrate_infl,E4))*D10) -> 0.13297122 | F23: =F8-(F10-(1+INDEX(finrate_infl,F4))*E10) -> 0.14003899 | G23: =G8-(G10-(1+INDEX(finrate_infl,G4))*F10) -> 0.0069879114 | H23: =H8-(H10-(1+INDEX(finrate_infl,H4))*G10) -> 0.0071771371 | I23: =I8-(I10-(1+INDEX(finrate_infl,I4))*H10) -> 0.0073418277 | J23: =J8-(J10-(1+INDEX(finrate_infl,J4))*I10) -> 0.007489 | ... AF23: =AF8-(AF10-(1+INDEX(finrate_infl,AF4))*AE10) -> 0.014235097
A24: FCFE = NI − ΔCSE (net distribution) | C24: =C7-(C9-(1+INDEX(finrate_infl,C4))*B9) -> 0.11942576 | D24: =D7-(D9-(1+INDEX(finrate_infl,D4))*C9) -> 0.12610478 | E24: =E7-(E9-(1+INDEX(finrate_infl,E4))*D9) -> 0.13287827 | F24: =F7-(F9-(1+INDEX(finrate_infl,F4))*E9) -> 0.13982527 | G24: =G7-(G9-(1+INDEX(finrate_infl,G4))*F9) -> 0.0066981898 | H24: =H7-(H9-(1+INDEX(finrate_infl,H4))*G9) -> 0.0068438391 | I24: =I7-(I9-(1+INDEX(finrate_infl,I4))*H9) -> 0.0069884203 | J24: =J7-(J9-(1+INDEX(finrate_infl,J4))*I9) -> 0.0071330695 | ... AF24: =AF7-(AF9-(1+INDEX(finrate_infl,AF4))*AE9) -> 0.009291755
A25: FCFD = NFE − ΔNFO | C25: =C12-(C11-(1+INDEX(finrate_infl,C4))*B11) -> -0.00034474546 | D25: =D12-(D11-(1+INDEX(finrate_infl,D4))*C11) -> -8.6945236e-05 | E25: =E12-(E11-(1+INDEX(finrate_infl,E4))*D11) -> 9.2947792e-05 | F25: =F12-(F11-(1+INDEX(finrate_infl,F4))*E11) -> 0.00021372242 | G25: =G12-(G11-(1+INDEX(finrate_infl,G4))*F11) -> 0.00028972161 | H25: =H12-(H11-(1+INDEX(finrate_infl,H4))*G11) -> 0.00033329802 | I25: =I12-(I11-(1+INDEX(finrate_infl,I4))*H11) -> 0.00035340744 | J25: =J12-(J11-(1+INDEX(finrate_infl,J4))*I11) -> 0.0003559305 | ... AF25: =AF12-(AF11-(1+INDEX(finrate_infl,AF4))*AE11) -> 0.0049433422
A27: RI = NI − ρE·CSE(prior) | C27: =C7-(C5-INDEX(finrate_infl,C4))*B9 -> 0.11337077 | D27: =D7-(D5-INDEX(finrate_infl,D4))*C9 -> 0.11987205 | E27: =E7-(E5-INDEX(finrate_infl,E4))*D9 -> 0.1264824 | F27: =F7-(F5-INDEX(finrate_infl,F4))*E9 -> 0.13327553 | G27: =G7-(G5-INDEX(finrate_infl,G4))*F9 -> 0 | H27: =H7-(H5-INDEX(finrate_infl,H4))*G9 -> 0 | I27: =I7-(I5-INDEX(finrate_infl,I4))*H9 -> 0 | J27: =J7-(J5-INDEX(finrate_infl,J4))*I9 -> 0 | ... AF27: =AF7-(AF5-INDEX(finrate_infl,AF4))*AE9 -> 0
A28: ReOI = OI_at − ρF·NOA(prior) | C28: =C8-(C14-INDEX(finrate_infl,C4))*B10 -> 0.11337077 | D28: =D8-(D14-INDEX(finrate_infl,D4))*C10 -> 0.11987205 | E28: =E8-(E14-INDEX(finrate_infl,E4))*D10 -> 0.1264824 | F28: =F8-(F14-INDEX(finrate_infl,F4))*E10 -> 0.13327553 | G28: =G8-(G14-INDEX(finrate_infl,G4))*F10 -> 0 | H28: =H8-(H14-INDEX(finrate_infl,H4))*G10 -> 0 | I28: =I8-(I14-INDEX(finrate_infl,I4))*H10 -> 0 | J28: =J8-(J14-INDEX(finrate_infl,J4))*I10 -> 0 | ... AF28: =AF8-(AF14-INDEX(finrate_infl,AF4))*AE10 -> 0
A29: RFD = NFE − ρD·NFO(prior) | C29: =C12-(C6-INDEX(finrate_infl,C4))*B11 -> 1.7780916e-17 | D29: =D12-(D6-INDEX(finrate_infl,D4))*C11 -> 3.1875544e-17 | E29: =E12-(E6-INDEX(finrate_infl,E4))*D11 -> 1.2143064e-17 | F29: =F12-(F6-INDEX(finrate_infl,F4))*E11 -> -2.2985086e-17 | G29: =G12-(G6-INDEX(finrate_infl,G4))*F11 -> 0 | H29: =H12-(H6-INDEX(finrate_infl,H4))*G11 -> 0 | I29: =I12-(I6-INDEX(finrate_infl,I4))*H11 -> 0 | J29: =J12-(J6-INDEX(finrate_infl,J4))*I11 -> 0 | ... AF29: =AF12-(AF6-INDEX(finrate_infl,AF4))*AE11 -> 0
A31: ρE_LR / ρF_LR / ρD_LR | B31: =INDEX(finrate_coe,COLUMNS(finrate_coe)) -> 0.05 | C31: =IF(cfg_rf_mode="Single",in_rf_lr,(O5*0+INDEX(finrate_coe,COLUMNS(finrate_coe))+O13*INDEX(finrate_cod,COLUMNS(finrate_cod)))/(1+O13)) -> 0.048208762 | D31: =INDEX(finrate_cod,COLUMNS(finrate_cod)) -> 0.045454086
A33: VALUES ($mm; equity per-share below)
A34: V(RI) equity = CSE₀ + ΣPV(RI) + CV | B34: =B9+SUMPRODUCT(C27:AF27,C15:AF15)+(INDEX(C27:AF27,cfg_N)/B31)*INDEX(C15:AF15,cfg_N) -> 2.1984847
A35: V(FCFE) equity = ΣPV(FCFE) + PV(terminal) | B35: =SUMPRODUCT(C24:AF24,C15:AF15)+AF9*AF15+(INDEX(C27:AF27,cfg_N)/B31)*INDEX(C15:AF15,cfg_N) -> 2.1984847
A36: V(net debt) = NFO₀ + ΣPV(RFD) + CV | B36: =B11+SUMPRODUCT(C29:AF29,C17:AF17) -> 0.060041357
A37: V(operations) = V(FCFE)+V(net debt) [additive] | B37: =B35+B36 -> 2.258526
A38: decorative: Equity via FCFF = B37−B36 and B37:=B35+B36, so this is identically B35. Audit B62 therefore repeats B61. | B38: =B37-B36 -> 2.1984847
A39: diagnostic: V(ops) direct = NOA₀+ΣPV(ReOI at ρF)+CV | B39: =B10+SUMPRODUCT(C28:AF28,C16:AF16)+(INDEX(C28:AF28,cfg_N)/C31)*INDEX(C16:AF16,cfg_N) -> 2.517082
A40: diagnostic: direct−additive at the BOOK-weighted rhoF. Cannot tie by construction — see row 48 and Audit CHECK 7. | B40: =(B39-B36)-B38 -> 0.25855599
A42: ★ RECONCILIATION (equity, $mm)
A43: V(FCFE) − V(RI) | B43: =B35-B34 -> 0
A44: Equity(FCFF) − V(RI) | B44: =B38-B34 -> 0
A45: per-share intrinsic (V(RI)/shares) | B45: =B34/anchor_shares0 -> 146.5168
A46: status | B46: =IF(AND(ABS(B43)<in_tie_tol*B34,ABS(B44)<in_tie_tol*B34),"ALL SPOKES TIE ✓","investigate") -> ALL SPOKES TIE ✓
A48: ★ CHECK 7 SUPPORT — value-weighted enterprise rate. rho_F on row 14 is BOOK-weighted, which makes ReOI identical to RI; the enterprise identity needs VALUE weights.
A49: V_E(t) — equity value at end of t [P5 value-weighted enterprise rate] | B49: =B35 -> 2.1984847 | C49: =B49*(1+C5)-C24 -> 2.3457746 | D49: =C49*(1+D5)-D24 -> 2.490158 | E49: =D49*(1+E5)-E24 -> 2.6337125 | F49: =E49*(1+F5)-F24 -> 2.7780271 | G49: =F49*(1+G5)-G24 -> 3.0646076 | H49: =G49*(1+H5)-H24 -> 3.3758488 | I49: =H49*(1+I5)-I24 -> 3.7144407 | J49: =I49*(1+J5)-J24 -> 4.083132 | ... AF49: =AE49*(1+AF5)-AF24 -> 25.783429
A50: V_D(t) — debt value at end of t | B50: =B36 -> 0.060041357 | C50: =B50*(1+C6)-C25 -> 0.06338817 | D50: =C50*(1+D6)-D25 -> 0.066644524 | E50: =D50*(1+E6)-E25 -> 0.069883803 | F50: =E50*(1+F6)-F25 -> 0.07316427 | G50: =F50*(1+G6)-G25 -> 0.076532762 | H50: =G50*(1+H6)-H25 -> 0.080026102 | I50: =H50*(1+I6)-I25 -> 0.083674 | J50: =I50*(1+J6)-J25 -> 0.08750177 | ... AF50: =AE50*(1+AF6)-AF25 -> 0.24772194
A51: rho_F*(t) — VALUE-weighted = (rhoE*V_E + rhoD*V_D)/(V_E+V_D), lagged | C51: =IF((B49+B50)=0,0,(C5*B49+C6*B50)/(B49+B50)) -> 0.11942202 | D51: =IF((C49+C50)=0,0,(D5*C49+D6*C50)/(C49+C50)) -> 0.11359035 | E51: =IF((D49+D50)=0,0,(E5*D49+E6*D50)/(D49+D50)) -> 0.10941986 | F51: =IF((E49+E50)=0,0,(F5*E49+F6*E50)/(E49+E50)) -> 0.10638942 | G51: =IF((F49+F50)=0,0,(G5*F49+G6*F50)/(F49+F50)) -> 0.10414486 | H51: =IF((G49+G50)=0,0,(H5*G49+H6*G50)/(G49+G50)) -> 0.10248244 | I51: =IF((H49+H50)=0,0,(I5*H49+I6*H50)/(H49+H50)) -> 0.10115573 | J51: =IF((I49+I50)=0,0,(J5*I49+J6*I50)/(I49+I50)) -> 0.10005178 | ... AF51: =IF((AE49+AE50)=0,0,(AF5*AE49+AF6*AE50)/(AE49+AE50)) -> 0.073870552
A52: DF^F*(t) cumulative at rho_F* | B52: 1 | C52: =B52/(1+C51) -> 0.89331814 | D52: =C52/(1+D51) -> 0.80219638 | E52: =D52/(1+E51) -> 0.72307736 | F52: =E52/(1+F51) -> 0.65354688 | G52: =F52/(1+G51) -> 0.59190321 | H52: =G52/(1+H51) -> 0.53688221 | I52: =H52/(1+I51) -> 0.48756247 | J52: =I52/(1+J51) -> 0.44321775 | ... AF52: =AE52/(1+AF51) -> 0.069376229
A53: ReOI*(t) = OI_at − (rho_F*(t) − pi_t)*NOA(t−1) [Stage A: the capital charge is at the REAL rate, because the NOA roll is NOA_t = (1+pi)*NOA_(t−1) + OI_at − FCFF] | C53: =C8-(C51-INDEX(finrate_infl,C4))*B10 -> 0.10937764 | D53: =D8-(D51-INDEX(finrate_infl,D4))*C10 -> 0.11600868 | E53: =E8-(E51-INDEX(finrate_infl,E4))*D10 -> 0.12268538 | F53: =F8-(F51-INDEX(finrate_infl,F4))*E10 -> 0.12949563 | G53: =G8-(G51-INDEX(finrate_infl,G4))*F10 -> -0.0038010205 | H53: =H8-(H51-INDEX(finrate_infl,H4))*G10 -> -0.0038623672 | I53: =I8-(I51-INDEX(finrate_infl,I4))*H10 -> -0.0039445515 | J53: =J8-(J51-INDEX(finrate_infl,J4))*I10 -> -0.0040429467 | ... AF53: =AF8-(AF51-INDEX(finrate_infl,AF4))*AE10 -> -0.0010714913
A54: PV(ReOI*) [t<=N] | C54: =IF(C4<=cfg_N,C53*C52,0) -> 0.09770903 | D54: =IF(D4<=cfg_N,D53*D52,0) -> 0.093061744 | E54: =IF(E4<=cfg_N,E53*E52,0) -> 0.088711019 | F54: =IF(F4<=cfg_N,F53*F52,0) -> 0.084631463 | G54: =IF(G4<=cfg_N,G53*G52,0) -> 0 | H54: =IF(H4<=cfg_N,H53*H52,0) -> 0 | I54: =IF(I4<=cfg_N,I53*I52,0) -> 0 | J54: =IF(J4<=cfg_N,J53*J52,0) -> 0 | ... AF54: =IF(AF4<=cfg_N,AF53*AF52,0) -> 0
A55: V(ops) direct @ rho_F* = NOA0 + ΣPV(ReOI*) + PV_N(V_ops,N − NOA_N) — the terminal is the PREMIUM over book, not the whole value | B55: =B10+SUM(C54:AF54)+INDEX(C52:AF52,cfg_N)*(INDEX(C49:AF49,cfg_N)+INDEX(C50:AF50,cfg_N)-INDEX(C10:AF10,cfg_N)) -> 2.258526
A56: ★ TIE: V(ops)@rho_F* − V(ops) additive [GATE: Audit CHECK 7] | B56: =B55-B37 -> 0
A57: Σ |FCFF − (FCFE + FCFD)| flow additivity [GATE: Audit CHECK 7] | B57: =SUMPRODUCT(ABS(C23:AF23-C24:AF24-C25:AF25)) -> 8.3960616e-16
A58: memo: rho_F row 14 stays BOOK-weighted — it is what zeroes residual income in the continuing period. Do not 'fix' it there.
